Workbook

Sheet FBT
A1: =[33]LAND!A1 -> TOMYPAK FLEXIBLE PACKAGING SDN BHD
A2: =[33]LAND!A2 -> FOR THE YEAR ENDED 30 JUNE 2025
A3: LEASEHOLD BUILDING (TAMPOI)
AA4: Closing | AB4: Opening
A5: Acquisition Date | B5: Disposal Date | C5: FA Description | D5: Cost c/f | E5: Addition | F5: Disposal/ Written off | G5: Cost b/f | I5: Years | J5: Acc Depn b/f | K5: Jul | L5: Aug | M5: Sept | N5: Oct | O5: Nov | P5: Dec | Q5: Jan | R5: Feb | S5: Mar | T5: Apr | U5: May | V5: Jun | W5: Current Year Depn | X5: Disposal/ Written off | Y5: Acc Depn c/f | AA5: NBV As At 30/06/2025 | AB5: NBV As At 30/06/2024
A6: 1988 | C6: Sykt Lian Mee-Electrical Installation | D6: 296000 | E6: 0 | F6: 0 | G6: =SUM(D6:F6) -> 296000 | I6: =40 -> 40 | J6: -218837.25 | K6: -616.67 | L6: -616.67 | M6: -616.67 | N6: -616.67 | O6: -616.67 | P6: -616.67 | Q6: -616.67 | R6: -616.67 | S6: -616.67 | T6: 0 | U6: 0 | V6: 0 | W6: =SUM(K6:V6) -> -5550.03 | X6: 0 | Y6: =J6+W6 -> -224387.28 | AA6: =G6+Y6 -> 71612.72 | AB6: =D6+J6 -> 77162.75
C7: Sykt Lian Mee-Additional work | D7: 647.35 | E7: 0 | F7: 0 | G7: =SUM(D7:F7) -> 647.35 | I7: 40 | J7: -479.03 | K7: -1.35 | L7: -1.35 | M7: -1.35 | N7: -1.35 | O7: -1.35 | P7: -1.35 | Q7: -1.35 | R7: -1.35 | S7: -1.35 | T7: 0 | U7: 0 | V7: 0 | W7: =SUM(K7:V7) -> -12.15 | X7: 0 | Y7: =J7+W7 -> -491.18 | AA7: =G7+Y7 -> 156.17 | AB7: =D7+J7 -> 168.32
C8: Flamex-Fire Fighting System | D8: 142500 | E8: 0 | F8: 0 | G8: =SUM(D8:F8) -> 142500 | I8: 40 | J8: -105353.43 | K8: -296.88 | L8: -296.88 | M8: -296.88 | N8: -296.88 | O8: -296.88 | P8: -296.88 | Q8: -296.88 | R8: -296.88 | S8: -296.88 | T8: 0 | U8: 0 | V8: 0 | W8: =SUM(K8:V8) -> -2671.92 | X8: 0 | Y8: =J8+W8 -> -108025.35 | AA8: =G8+Y8 -> 34474.65 | AB8: =D8+J8 -> 37146.57
C9: Sykt Lian Mee-Construction Cost | D9: 1471444.4 | E9: 0 | F9: 0 | G9: =SUM(D9:F9) -> 1471444.4 | I9: 40 | J9: -1087853.2 | K9: -3065.5 | L9: -3065.5 | M9: -3065.5 | N9: -3065.5 | O9: -3065.5 | P9: -3065.5 | Q9: -3065.5 | R9: -3065.5 | S9: -3065.5 | T9: 0 | U9: 0 | V9: 0 | W9: =SUM(K9:V9) -> -27589.5 | X9: 0 | Y9: =J9+W9 -> -1115442.7 | AA9: =G9+Y9 -> 356001.74 | AB9: =D9+J9 -> 383591.24
C10: Jurutera Lee-Professional Fee | D10: 14000 | E10: 0 | F10: 0 | G10: =SUM(D10:F10) -> 14000 | I10: 40 | J10: -10351.38 | K10: -29.17 | L10: -29.17 | M10: -29.17 | N10: -29.17 | O10: -29.17 | P10: -29.17 | Q10: -29.17 | R10: -29.17 | S10: -29.17 | T10: 0 | U10: 0 | V10: 0 | W10: =SUM(K10:V10) -> -262.53 | X10: 0 | Y10: =J10+W10 -> -10613.91 | AA10: =G10+Y10 -> 3386.09 | AB10: =D10+J10 -> 3648.62
C11: LLN-Electrical Supply | D11: 16787 | E11: 0 | F11: 0 | G11: =SUM(D11:F11) -> 16787 | I11: 40 | J11: -12409.95 | K11: -34.97 | L11: -34.97 | M11: -34.97 | N11: -34.97 | O11: -34.97 | P11: -34.97 | Q11: -34.97 | R11: -34.97 | S11: -34.97 | T11: 0 | U11: 0 | V11: 0 | W11: =SUM(K11:V11) -> -314.73 | X11: 0 | Y11: =J11+W11 -> -12724.68 | AA11: =G11+Y11 -> 4062.32 | AB11: =D11+J11 -> 4377.05
C12: Pembinaan CL Tan-Painting,Tiles,Concrete Work | D12: 4670 | E12: 0 | F12: 0 | G12: =SUM(D12:F12) -> 4670 | I12: 40 | J12: 0 | K12: 0 | L12: 0 | M12: 0 | N12: 0 | O12: 0 | P12: 0 | Q12: 0 | R12: 0 | S12: 0 | T12: 0 | U12: 0 | V12: 0 | W12: =SUM(K12:V12) -> 0 | X12: 0 | Y12: =J12+W12 -> 0 | AA12: =G12+Y12 -> 4670 | AB12: =D12+J12 -> 4670
C13: Sykt Lian Mee-Construction Cost | D13: 13184.65 | E13: 0 | F13: 0 | G13: =SUM(D13:F13) -> 13184.65 | I13: 40 | J13: -9748.19 | K13: -27.47 | L13: -27.47 | M13: -27.47 | N13: -27.47 | O13: -27.47 | P13: -27.47 | Q13: -27.47 | R13: -27.47 | S13: -27.47 | T13: 0 | U13: 0 | V13: 0 | W13: =SUM(K13:V13) -> -247.23 | X13: 0 | Y13: =J13+W13 -> -9995.42 | AA13: =G13+Y13 -> 3189.23 | AB13: =D13+J13 -> 3436.46
C14: Consultancy Fee For Fire Fighting System | D14: 1250 | E14: 0 | F14: 0 | G14: =SUM(D14:F14) -> 1250 | I14: 40 | J14: -922.86 | K14: -2.6 | L14: -2.6 | M14: -2.6 | N14: -2.6 | O14: -2.6 | P14: -2.6 | Q14: -2.6 | R14: -2.6 | S14: -2.6 | T14: 0 | U14: 0 | V14: 0 | W14: =SUM(K14:V14) -> -23.4 | X14: 0 | Y14: =J14+W14 -> -946.26 | AA14: =G14+Y14 -> 303.74 | AB14: =D14+J14 -> 327.14
C15: Additional Work At Building | D15: 37129.86 | E15: 0 | F15: 0 | G15: =SUM(D15:F15) -> 37129.86 | I15: 40 | J15: -27449.37 | K15: -77.35 | L15: -77.35 | M15: -77.35 | N15: -77.35 | O15: -77.35 | P15: -77.35 | Q15: -77.35 | R15: -77.35 | S15: -77.35 | T15: 0 | U15: 0 | V15: 0 | W15: =SUM(K15:V15) -> -696.15 | X15: 0 | Y15: =J15+W15 -> -28145.52 | AA15: =G15+Y15 -> 8984.34 | AB15: =D15+J15 -> 9680.49
D16: =SUM(D6:D15) -> 1997613.3 | E16: =SUM(E6:E15) -> 0 | F16: =SUM(F6:F15) -> 0 | G16: =SUM(G6:G15) -> 1997613.3 | J16: =SUM(J6:J15) -> -1473404.7 | K16: =SUM(K6:K15) -> -4151.96 | L16: =SUM(L6:L15) -> -4151.96 | M16: =SUM(M6:M15) -> -4151.96 | N16: =SUM(N6:N15) -> -4151.96 | O16: =SUM(O6:O15) -> -4151.96 | P16: =SUM(P6:P15) -> -4151.96 | Q16: =SUM(Q6:Q15) -> -4151.96 | ... Y16: =SUM(Y6:Y15) -> -1510772.3 | AA16: =SUM(AA6:AA15) -> 486841 | AB16: =SUM(AB6:AB15) -> 524208.64
A18: 1989 | C18: Ismail & Rakan2-Electrical Works 40% | D18: 7200 | E18: 0 | F18: 0 | G18: =SUM(D18:F18) -> 7200 | I18: 40 | J18: -5323.05 | K18: -15 | L18: -15 | M18: -15 | N18: -15 | O18: -15 | P18: -15 | Q18: -15 | R18: -15 | S18: -15 | T18: 0 | U18: 0 | V18: 0 | W18: =SUM(K18:V18) -> -135 | X18: 0 | Y18: =J18+W18 -> -5458.05 | AA18: =G18+Y18 -> 1741.95 | AB18: =D18+J18 -> 1876.95
C19: Sykt Lian Mee-Concrete Trench | D19: 4200 | E19: 0 | F19: 0 | G19: =SUM(D19:F19) -> 4200 | I19: 40 | J19: -3105.11 | K19: -8.75 | L19: -8.75 | M19: -8.75 | N19: -8.75 | O19: -8.75 | P19: -8.75 | Q19: -8.75 | R19: -8.75 | S19: -8.75 | T19: 0 | U19: 0 | V19: 0 | W19: =SUM(K19:V19) -> -78.75 | X19: 0 | Y19: =J19+W19 -> -3183.86 | AA19: =G19+Y19 -> 1016.14 | AB19: =D19+J19 -> 1094.89
D20: =SUM(D18:D19) -> 11400 | E20: =SUM(E18:E19) -> 0 | F20: =SUM(F18:F19) -> 0 | G20: =SUM(G18:G19) -> 11400 | J20: =SUM(J18:J19) -> -8428.16 | K20: =SUM(K18:K19) -> -23.75 | L20: =SUM(L18:L19) -> -23.75 | M20: =SUM(M18:M19) -> -23.75 | N20: =SUM(N18:N19) -> -23.75 | O20: =SUM(O18:O19) -> -23.75 | P20: =SUM(P18:P19) -> -23.75 | Q20: =SUM(Q18:Q19) -> -23.75 | ... Y20: =SUM(Y18:Y19) -> -8641.91 | AA20: =SUM(AA18:AA19) -> 2758.09 | AB20: =SUM(AB18:AB19) -> 2971.84
A22: 1990 | C22: Pembinaan CL Tan-Painting,Tiles,Concrete Work | D22: -4670 | E22: 0 | F22: 0 | G22: =SUM(D22:F22) -> -4670 | J22: 0 | K22: 0 | L22: 0 | M22: 0 | N22: 0 | O22: 0 | P22: 0 | Q22: 0 | R22: 0 | S22: 0 | T22: 0 | U22: 0 | V22: 0 | W22: =SUM(K22:V22) -> 0 | X22: 0 | Y22: =J22+W22 -> 0 | AA22: =G22+Y22 -> -4670 | AB22: =D22+J22 -> -4670
C23: Chun Seng-Contruction Work | D23: 40000 | E23: 0 | F23: 0 | G23: =SUM(D23:F23) -> 40000 | I23: 40 | J23: -29571.48 | K23: -83.33 | L23: -83.33 | M23: -83.33 | N23: -83.33 | O23: -83.33 | P23: -83.33 | Q23: -83.33 | R23: -83.33 | S23: -83.33 | T23: 0 | U23: 0 | V23: 0 | W23: =SUM(K23:V23) -> -749.97 | X23: 0 | Y23: =J23+W23 -> -30321.45 | AA23: =G23+Y23 -> 9678.55 | AB23: =D23+J23 -> 10428.52
C24: Timbalan Yg Dipertua-Extension Fty Application | D24: 220 | E24: 0 | F24: 0 | G24: =SUM(D24:F24) -> 220 | I24: 40 | J24: -163.14 | K24: -0.46 | L24: -0.46 | M24: -0.46 | N24: -0.46 | O24: -0.46 | P24: -0.46 | Q24: -0.46 | R24: -0.46 | S24: -0.46 | T24: 0 | U24: 0 | V24: 0 | W24: =SUM(K24:V24) -> -4.14 | X24: 0 | Y24: =J24+W24 -> -167.28 | AA24: =G24+Y24 -> 52.72 | AB24: =D24+J24 -> 56.86
C25: Audit Adjt-Revaluation Surplus | D25: 2190986.7 | E25: 0 | F25: 0 | G25: =SUM(D25:F25) -> 2190986.7 | I25: 40 | J25: -1619823.2 | K25: -4564.56 | L25: -4564.56 | M25: -4564.56 | N25: -4564.56 | O25: -4564.56 | P25: -4564.56 | Q25: -4564.56 | R25: -4564.56 | S25: -4564.56 | T25: 0 | U25: 0 | V25: 0 | W25: =SUM(K25:V25) -> -41081.04 | X25: 0 | Y25: =J25+W25 -> -1660904.2 | AA25: =G25+Y25 -> 530082.48 | AB25: =D25+J25 -> 571163.52
C26: Audit Adjt-Overstated Of Revaluation Surplus | D26: -953373.55 | E26: 0 | F26: 0 | G26: =SUM(D26:F26) -> -953373.55 | I26: 40 | J26: 704841.64 | K26: 1986.2 | L26: 1986.2 | M26: 1986.2 | N26: 1986.2 | O26: 1986.2 | P26: 1986.2 | Q26: 1986.2 | R26: 1986.2 | S26: 1986.2 | T26: 0 | U26: 0 | V26: 0 | W26: =SUM(K26:V26) -> 17875.8 | X26: 0 | Y26: =J26+W26 -> 722717.44 | AA26: =G26+Y26 -> -230656.11 | AB26: =D26+J26 -> -248531.91
C27: Audit Adjt-Revaluation Surplus Wrongly Charged | D27: -783956.45 | E27: 0 | F27: 0 | G27: =SUM(D27:F27) -> -783956.45 | I27: 40 | J27: 579587.32 | K27: 1633.24 | L27: 1633.24 | M27: 1633.24 | N27: 1633.24 | O27: 1633.24 | P27: 1633.24 | Q27: 1633.24 | R27: 1633.24 | S27: 1633.24 | T27: 0 | U27: 0 | V27: 0 | W27: =SUM(K27:V27) -> 14699.16 | X27: 0 | Y27: =J27+W27 -> 594286.48 | AA27: =G27+Y27 -> -189669.97 | AB27: =D27+J27 -> -204369.13
C28: Sykt Lian Mee-Repaid For Overprovided | D28: -117850.5 | E28: 0 | F28: 0 | G28: =SUM(D28:F28) -> -117850.5 | I28: 40 | J28: 87127.68 | K28: 245.52 | L28: 245.52 | M28: 245.52 | N28: 245.52 | O28: 245.52 | P28: 245.52 | Q28: 245.52 | R28: 245.52 | S28: 245.52 | T28: 0 | U28: 0 | V28: 0 | W28: =SUM(K28:V28) -> 2209.68 | X28: 0 | Y28: =J28+W28 -> 89337.36 | AA28: =G28+Y28 -> -28513.14 | AB28: =D28+J28 -> -30722.82
D29: =SUM(D22:D28) -> 371356.2 | E29: =SUM(E22:E28) -> 0 | F29: =SUM(F22:F28) -> 0 | G29: =SUM(G22:G28) -> 371356.2 | J29: =SUM(J22:J28) -> -278001.16 | K29: =SUM(K22:K28) -> -783.39 | L29: =SUM(L22:L28) -> -783.39 | M29: =SUM(M22:M28) -> -783.39 | N29: =SUM(N22:N28) -> -783.39 | O29: =SUM(O22:O28) -> -783.39 | P29: =SUM(P22:P28) -> -783.39 | Q29: =SUM(Q22:Q28) -> -783.39 | ... Y29: =SUM(Y22:Y28) -> -285051.67 | AA29: =SUM(AA22:AA28) -> 86304.53 | AB29: =SUM(AB22:AB28) -> 93355.04
A31: 1991 | C31: Sykt Lian Mee-2.5% Retention Sum On Extension | D31: 19640.49 | E31: 0 | F31: 0 | G31: =SUM(D31:F31) -> 19640.49 | I31: 40 | J31: -14522.76 | K31: -40.92 | L31: -40.92 | M31: -40.92 | N31: -40.92 | O31: -40.92 | P31: -40.92 | Q31: -40.92 | R31: -40.92 | S31: -40.92 | T31: 0 | U31: 0 | V31: 0 | W31: =SUM(K31:V31) -> -368.28 | X31: 0 | Y31: =J31+W31 -> -14891.04 | AA31: =G31+Y31 -> 4749.45 | AB31: =D31+J31 -> 5117.73
C32: Balance Of Contract Sum Of RM168,000 | D32: 7500 | E32: 0 | F32: 0 | G32: =SUM(D32:F32) -> 7500 | I32: 40 | J32: -5546.98 | K32: -15.63 | L32: -15.63 | M32: -15.63 | N32: -15.63 | O32: -15.63 | P32: -15.63 | Q32: -15.63 | R32: -15.63 | S32: -15.63 | T32: 0 | U32: 0 | V32: 0 | W32: =SUM(K32:V32) -> -140.67 | X32: 0 | Y32: =J32+W32 -> -5687.65 | AA32: =G32+Y32 -> 1812.35 | AB32: =D32+J32 -> 1953.02
C33: Extension Factory Building Fully Completed | D33: 765979.22 | E33: 0 | F33: 0 | G33: =SUM(D33:F33) -> 765979.22 | I33: 40 | J33: -566360.38 | K33: -1595.79 | L33: -1595.79 | M33: -1595.79 | N33: -1595.79 | O33: -1595.79 | P33: -1595.79 | Q33: -1595.79 | R33: -1595.79 | S33: -1595.79 | T33: 0 | U33: 0 | V33: 0 | W33: =SUM(K33:V33) -> -14362.11 | X33: 0 | Y33: =J33+W33 -> -580722.49 | AA33: =G33+Y33 -> 185256.73 | AB33: =D33+J33 -> 199618.84
C34: Sin Sin Construction-Progress Claim On Extension | D34: 52187 | E34: 0 | F34: 0 | G34: =SUM(D34:F34) -> 52187 | I34: 40 | J34: -38585.87 | K34: -108.72 | L34: -108.72 | M34: -108.72 | N34: -108.72 | O34: -108.72 | P34: -108.72 | Q34: -108.72 | R34: -108.72 | S34: -108.72 | T34: 0 | U34: 0 | V34: 0 | W34: =SUM(K34:V34) -> -978.48 | X34: 0 | Y34: =J34+W34 -> -39564.35 | AA34: =G34+Y34 -> 12622.65 | AB34: =D34+J34 -> 13601.13
D35: =SUM(D31:D34) -> 845306.71 | E35: =SUM(E31:E34) -> 0 | F35: =SUM(F31:F34) -> 0 | G35: =SUM(G31:G34) -> 845306.71 | J35: =SUM(J31:J34) -> -625015.99 | K35: =SUM(K31:K34) -> -1761.06 | L35: =SUM(L31:L34) -> -1761.06 | M35: =SUM(M31:M34) -> -1761.06 | N35: =SUM(N31:N34) -> -1761.06 | O35: =SUM(O31:O34) -> -1761.06 | P35: =SUM(P31:P34) -> -1761.06 | Q35: =SUM(Q31:Q34) -> -1761.06 | ... Y35: =SUM(Y31:Y34) -> -640865.53 | AA35: =SUM(AA31:AA34) -> 204441.18 | AB35: =SUM(AB31:AB34) -> 220290.72
A37: 1994 | C37: Revaluation Surplus | D37: 702649.14 | E37: 0 | F37: 0 | G37: =SUM(D37:F37) -> 702649.14 | I37: 40 | J37: -519666.87 | K37: -1463.85 | L37: -1463.85 | M37: -1463.85 | N37: -1463.85 | O37: -1463.85 | P37: -1463.85 | Q37: -1463.85 | R37: -1463.85 | S37: -1463.85 | T37: 0 | U37: 0 | V37: 0 | W37: =SUM(K37:V37) -> -13174.65 | X37: 0 | Y37: =J37+W37 -> -532841.52 | AA37: =G37+Y37 -> 169807.62 | AB37: =D37+J37 -> 182982.27
A39: 1995 | C39: Audit Adjustment On Revaluation Surplus | D39: -331600.59 | E39: 0 | F39: 0 | G39: =SUM(D39:F39) -> -331600.59 | J39: 244554.02 | K39: 690.83 | L39: 690.83 | M39: 690.83 | N39: 690.83 | O39: 690.83 | P39: 690.83 | Q39: 690.83 | R39: 690.83 | S39: 690.83 | T39: 0 | U39: 0 | V39: 0 | W39: =SUM(K39:V39) -> 6217.47 | X39: 0 | Y39: =J39+W39 -> 250771.49 | AA39: =G39+Y39 -> -80829.1 | AB39: =D39+J39 -> -87046.57
C40: Audit Adjt Of Accum Depn On Revaluation | D40: -331157.92 | E40: 0 | F40: 0 | G40: =SUM(D40:F40) -> -331157.92 | J40: 244228.26 | K40: 689.91 | L40: 689.91 | M40: 689.91 | N40: 689.91 | O40: 689.91 | P40: 689.91 | Q40: 689.91 | R40: 689.91 | S40: 689.91 | T40: 0 | U40: 0 | V40: 0 | W40: =SUM(K40:V40) -> 6209.19 | X40: 0 | Y40: =J40+W40 -> 250437.45 | AA40: =G40+Y40 -> -80720.47 | AB40: =D40+J40 -> -86929.66
C41: Jurutera Lee-Professional Fee | D41: 63171.68 | E41: 0 | F41: 0 | G41: =SUM(D41:F41) -> 63171.68 | J41: -46326.72 | K41: -131.61 | L41: -131.61 | M41: -131.61 | N41: -131.61 | O41: -131.61 | P41: -131.61 | Q41: -131.61 | R41: -131.61 | S41: -131.61 | T41: 0 | U41: 0 | V41: 0 | W41: =SUM(K41:V41) -> -1184.49 | X41: 0 | Y41: =J41+W41 -> -47511.21 | AA41: =G41+Y41 -> 15660.47 | AB41: =D41+J41 -> 16844.96
C42: Reclassify Of A/C For Installation & Renovations | D42: -289766.97 | E42: 0 | F42: 0 | G42: =SUM(D42:F42) -> -289766.97 | J42: 213702.76 | K42: 603.68 | L42: 603.68 | M42: 603.68 | N42: 603.68 | O42: 603.68 | P42: 603.68 | Q42: 603.68 | R42: 603.68 | S42: 603.68 | T42: 0 | U42: 0 | V42: 0 | W42: =SUM(K42:V42) -> 5433.12 | X42: 0 | Y42: =J42+W42 -> 219135.88 | AA42: =G42+Y42 -> -70631.09 | AB42: =D42+J42 -> -76064.21
C43: Eliminating Accum Depn of Inst & Ren reclassify | D43: 331600.59 | E43: 0 | F43: 0 | G43: =SUM(D43:F43) -> 331600.59 | J43: -244554.02 | K43: -690.83 | L43: -690.83 | M43: -690.83 | N43: -690.83 | O43: -690.83 | P43: -690.83 | Q43: -690.83 | R43: -690.83 | S43: -690.83 | T43: 0 | U43: 0 | V43: 0 | W43: =SUM(K43:V43) -> -6217.47 | X43: 0 | Y43: =J43+W43 -> -250771.49 | AA43: =G43+Y43 -> 80829.1 | AB43: =D43+J43 -> 87046.57
C44: Capitalise Of Work In Progress | D44: 3952116.6 | E44: 0 | F44: 0 | G44: =SUM(D44:F44) -> 3952116.6 | J44: -2898220 | K44: -8233.58 | L44: -8233.58 | M44: -8233.58 | N44: -8233.58 | O44: -8233.58 | P44: -8233.58 | Q44: -8233.58 | R44: -8233.58 | S44: -8233.58 | T44: 0 | U44: 0 | V44: 0 | W44: =SUM(K44:V44) -> -74102.22 | X44: 0 | Y44: =J44+W44 -> -2972322.3 | AA44: =G44+Y44 -> 979794.31 | AB44: =D44+J44 -> 1053896.5
C45: Capitalise Of Work In Progress | D45: 79580.15 | E45: 0 | F45: 0 | G45: =SUM(D45:F45) -> 79580.15 | J45: -58358.2 | K45: -165.79 | L45: -165.79 | M45: -165.79 | N45: -165.79 | O45: -165.79 | P45: -165.79 | Q45: -165.79 | R45: -165.79 | S45: -165.79 | T45: 0 | U45: 0 | V45: 0 | W45: =SUM(K45:V45) -> -1492.11 | X45: 0 | Y45: =J45+W45 -> -59850.31 | AA45: =G45+Y45 -> 19729.84 | AB45: =D45+J45 -> 21221.95
C46: Lian Mee-Proposed Extension Of FTY | D46: 78144.04 | E46: 0 | F46: 0 | G46: =SUM(D46:F46) -> 78144.04 | J46: -56328.8 | K46: -162.8 | L46: -162.8 | M46: -162.8 | N46: -162.8 | O46: -162.8 | P46: -162.8 | Q46: -162.8 | R46: -162.8 | S46: -162.8 | T46: 0 | U46: 0 | V46: 0 | W46: =SUM(K46:V46) -> -1465.2 | X46: 0 | Y46: =J46+W46 -> -57794 | AA46: =G46+Y46 -> 20350.04 | AB46: =D46+J46 -> 21815.24
C47: Retention Sum For Lian Mee On Pro Ext Of FTY Bldg | D47: -129277 | E47: 0 | F47: 0 | G47: =SUM(D47:F47) -> -129277 | J47: 93188.18 | K47: 269.33 | L47: 269.33 | M47: 269.33 | N47: 269.33 | O47: 269.33 | P47: 269.33 | Q47: 269.33 | R47: 269.33 | S47: 269.33 | T47: 0 | U47: 0 | V47: 0 | W47: =SUM(K47:V47) -> 2423.97 | X47: 0 | Y47: =J47+W47 -> 95612.15 | AA47: =G47+Y47 -> -33664.85 | AB47: =D47+J47 -> -36088.82
D48: =SUM(D39:D47) -> 3422810.5 | E48: =SUM(E39:E47) -> 0 | F48: =SUM(F39:F47) -> 0 | G48: =SUM(G39:G47) -> 3422810.5 | J48: =SUM(J39:J47) -> -2508114.6 | K48: =SUM(K39:K47) -> -7130.86 | L48: =SUM(L39:L47) -> -7130.86 | M48: =SUM(M39:M47) -> -7130.86 | N48: =SUM(N39:N47) -> -7130.86 | O48: =SUM(O39:O47) -> -7130.86 | P48: =SUM(P39:P47) -> -7130.86 | Q48: =SUM(Q39:Q47) -> -7130.86 | ... Y48: =SUM(Y39:Y47) -> -2572292.3 | AA48: =SUM(AA39:AA47) -> 850518.25 | AB48: =SUM(AB39:AB47) -> 914695.99
A50: 2001 | C50: CMTS-Guard House For Locker Place | D50: 12000 | E50: 0 | F50: 0 | G50: =SUM(D50:F50) -> 12000 | I50: 34 | J50: -7970.11 | K50: -29.41 | L50: -29.41 | M50: -29.41 | N50: -29.41 | O50: -29.41 | P50: -29.41 | Q50: -29.41 | R50: -29.41 | S50: -29.41 | T50: 0 | U50: 0 | V50: 0 | W50: =SUM(K50:V50) -> -264.69 | X50: 0 | Y50: =J50+W50 -> -8234.8 | AA50: =G50+Y50 -> 3765.2 | AB50: =D50+J50 -> 4029.89
C51: CMTS-Roof Works For Guard House | D51: 12000 | E51: 0 | F51: 0 | G51: =SUM(D51:F51) -> 12000 | I51: 34 | J51: -7970.11 | K51: -29.41 | L51: -29.41 | M51: -29.41 | N51: -29.41 | O51: -29.41 | P51: -29.41 | Q51: -29.41 | R51: -29.41 | S51: -29.41 | T51: 0 | U51: 0 | V51: 0 | W51: =SUM(K51:V51) -> -264.69 | X51: 0 | Y51: =J51+W51 -> -8234.8 | AA51: =G51+Y51 -> 3765.2 | AB51: =D51+J51 -> 4029.89
C52: CMTS-Corrugated Roof Sheet For Guard House | D52: 998 | E52: 0 | F52: 0 | G52: =SUM(D52:F52) -> 998 | I52: 34 | J52: -663.98 | K52: -2.45 | L52: -2.45 | M52: -2.45 | N52: -2.45 | O52: -2.45 | P52: -2.45 | Q52: -2.45 | R52: -2.45 | S52: -2.45 | T52: 0 | U52: 0 | V52: 0 | W52: =SUM(K52:V52) -> -22.05 | X52: 0 | Y52: =J52+W52 -> -686.03 | AA52: =G52+Y52 -> 311.97 | AB52: =D52+J52 -> 334.02
D53: =SUM(D50:D52) -> 24998 | E53: =SUM(E50:E52) -> 0 | F53: =SUM(F50:F52) -> 0 | G53: =SUM(G50:G52) -> 24998 | J53: =SUM(J50:J52) -> -16604.2 | K53: =SUM(K50:K52) -> -61.27 | L53: =SUM(L50:L52) -> -61.27 | M53: =SUM(M50:M52) -> -61.27 | N53: =SUM(N50:N52) -> -61.27 | O53: =SUM(O50:O52) -> -61.27 | P53: =SUM(P50:P52) -> -61.27 | Q53: =SUM(Q50:Q52) -> -61.27 | ... Y53: =SUM(Y50:Y52) -> -17155.63 | AA53: =SUM(AA50:AA52) -> 7842.37 | AB53: =SUM(AB50:AB52) -> 8393.8
A55: 2004
A56: Jun | C56: JV061/08 Disposal Of 1 Unit Office Cabin | D56: -8300 | E56: 0 | F56: 0 | G56: =SUM(D56:F56) -> -8300 | I56: 40 | J56: 2317.13 | K56: 0 | L56: 0 | M56: 0 | N56: 0 | O56: 0 | P56: 0 | Q56: 0 | R56: 0 | S56: 0 | T56: 0 | U56: 0 | V56: 0 | W56: =SUM(K56:V56) -> 0 | X56: 0 | Y56: =J56+W56 -> 2317.13 | AA56: =G56+Y56 -> -5982.87 | AB56: =D56+J56 -> -5982.87
A58: Dec | C58: E194/12 & JV053/12 Jurutera Lee Professional Fee
C59: For Linkway Of Factory Blk B & C | D59: 9450 | E59: 0 | F59: 0 | G59: =SUM(D59:F59) -> 9450 | I59: 31 | J59: -5715 | K59: -25.4 | L59: -25.4 | M59: -25.4 | N59: -25.4 | O59: -25.4 | P59: -25.4 | Q59: -25.4 | R59: -25.4 | S59: -25.4 | T59: 0 | U59: 0 | V59: 0 | W59: =SUM(K59:V59) -> -228.6 | X59: 0 | Y59: =J59+W59 -> -5943.6 | AA59: =G59+Y59 -> 3506.4 | AB59: =D59+J59 -> 3735
C60: E193/12 Jurutera Lee Professional Fee For
C61: (a) Platform For LPG Burner & Blower In Printing Dept | D61: 5250 | E61: 0 | F61: 0 | G61: =SUM(D61:F61) -> 5250 | I61: 31 | J61: -3174.75 | K61: -14.11 | L61: -14.11 | M61: -14.11 | N61: -14.11 | O61: -14.11 | P61: -14.11 | Q61: -14.11 | R61: -14.11 | S61: -14.11 | T61: 0 | U61: 0 | V61: 0 | W61: =SUM(K61:V61) -> -126.99 | X61: 0 | Y61: =J61+W61 -> -3301.74 | AA61: =G61+Y61 -> 1948.26 | AB61: =D61+J61 -> 2075.25
C62: (b) Carpark Steel Canopy Extension | D62: 2100 | E62: 0 | F62: 0 | G62: =SUM(D62:F62) -> 2100 | I62: 31 | J62: -1271.25 | K62: -5.65 | L62: -5.65 | M62: -5.65 | N62: -5.65 | O62: -5.65 | P62: -5.65 | Q62: -5.65 | R62: -5.65 | S62: -5.65 | T62: 0 | U62: 0 | V62: 0 | W62: =SUM(K62:V62) -> -50.85 | X62: 0 | Y62: =J62+W62 -> -1322.1 | AA62: =G62+Y62 -> 777.9 | AB62: =D62+J62 -> 828.75
C63: (c) Steel Platform Office Extension In Blk A For
C64: QA Office & Lab | D64: 5250 | E64: 0 | F64: 0 | G64: =SUM(D64:F64) -> 5250 | I64: 31 | J64: -3174.75 | K64: -14.11 | L64: -14.11 | M64: -14.11 | N64: -14.11 | O64: -14.11 | P64: -14.11 | Q64: -14.11 | R64: -14.11 | S64: -14.11 | T64: 0 | U64: 0 | V64: 0 | W64: =SUM(K64:V64) -> -126.99 | X64: 0 | Y64: =J64+W64 -> -3301.74 | AA64: =G64+Y64 -> 1948.26 | AB64: =D64+J64 -> 2075.25
C65: CYF Construction-Linkway Of Factory Blk B & C | D65: 120388.75 | E65: 0 | F65: 0 | G65: =SUM(D65:F65) -> 120388.75 | I65: 31 | J65: -72816.75 | K65: -323.63 | L65: -323.63 | M65: -323.63 | N65: -323.63 | O65: -323.63 | P65: -323.63 | Q65: -323.63 | R65: -323.63 | S65: -323.63 | T65: 0 | U65: 0 | V65: 0 | W65: =SUM(K65:V65) -> -2912.67 | X65: 0 | Y65: =J65+W65 -> -75729.42 | AA65: =G65+Y65 -> 44659.33 | AB65: =D65+J65 -> 47572
C66: MBJB-Plan Processing Fee For Linkway | D66: 1650 | E66: 0 | F66: 0 | G66: =SUM(D66:F66) -> 1650 | I66: 31 | J66: -999 | K66: -4.44 | L66: -4.44 | M66: -4.44 | N66: -4.44 | O66: -4.44 | P66: -4.44 | Q66: -4.44 | R66: -4.44 | S66: -4.44 | T66: 0 | U66: 0 | V66: 0 | W66: =SUM(K66:V66) -> -39.96 | X66: 0 | Y66: =J66+W66 -> -1038.96 | AA66: =G66+Y66 -> 611.04 | AB66: =D66+J66 -> 651
D67: =SUM(D56:D66) -> 135788.75 | E67: =SUM(E56:E66) -> 0 | F67: =SUM(F56:F66) -> 0 | G67: =SUM(G56:G66) -> 135788.75 | J67: =SUM(J56:J66) -> -84834.37 | K67: =SUM(K56:K66) -> -387.34 | L67: =SUM(L56:L66) -> -387.34 | M67: =SUM(M56:M66) -> -387.34 | N67: =SUM(N56:N66) -> -387.34 | O67: =SUM(O56:O66) -> -387.34 | P67: =SUM(P56:P66) -> -387.34 | Q67: =SUM(Q56:Q66) -> -387.34 | ... Y67: =SUM(Y56:Y66) -> -88320.43 | AA67: =SUM(AA56:AA66) -> 47468.32 | AB67: =SUM(AB56:AB66) -> 50954.38
D69: =D16+D20+D29+D35+D37+D48+D53+D67 -> 7511922.7 | E69: =E16+E20+E29+E35+E37+E48+E53+E67 -> 0 | F69: =F16+F20+F29+F35+F37+F48+F53+F67 -> 0 | G69: =G16+G20+G29+G35+G37+G48+G53+G67 -> 7511922.7 | J69: =J16+J20+J29+J35+J37+J48+J53+J67 -> -5514070 | K69: =K16+K20+K29+K35+K37+K48+K53+K67 -> -15763.48 | L69: =L16+L20+L29+L35+L37+L48+L53+L67 -> -15763.48 | M69: =M16+M20+M29+M35+M37+M48+M53+M67 -> -15763.48 | N69: =N16+N20+N29+N35+N37+N48+N53+N67 -> -15763.48 | O69: =O16+O20+O29+O35+O37+O48+O53+O67 -> -15763.48 | P69: =P16+P20+P29+P35+P37+P48+P53+P67 -> -15763.48 | Q69: =Q16+Q20+Q29+Q35+Q37+Q48+Q53+Q67 -> -15763.48 | ... Y69: =Y16+Y20+Y29+Y35+Y37+Y48+Y53+Y67 -> -5655941.3 | AA69: =AA16+AA20+AA29+AA35+AA37+AA48+AA53+AA67 -> 1855981.4 | AB69: =AB16+AB20+AB29+AB35+AB37+AB48+AB53+AB67 -> 1997852.7
E72: In Balance Sheet as at 31/3/25 | G72: 7511922.7 | W72: In Balance Sheet as at 31/3/25 | Y72: -5655941.3

Sheet TR
A1: =[33]LAND!A1 -> TOMYPAK FLEXIBLE PACKAGING SDN BHD
A2: =[33]LAND!A2 -> FOR THE YEAR ENDED 30 JUNE 2025
A3: TAMPOI RETROFITTING
A4: 11101-024 | AI4: Closing | AK4: Closing | AL4: Opening
A5: Acquisition Date | B5: Disposal Date | C5: F/A Code | D5: F/A Description | E5: Suppliers | F5: Cost Ctr. 1 | G5: Cost Ctr. 2 | H5: Cost Ctr. 3 | I5: Purchase Order | J5: NO. | K5: Invoice No. | L5: Remarks | M5: Quantity | O5: Cost c/f | P5: Addition | Q5: Disposal/ Written off | R5: Cost b/f | S5: Months | T5: Acc Depn b/f | U5: Jul | V5: Aug | W5: Sept | X5: Oct | Y5: Nov | Z5: Dec | AA5: Jan | AB5: Feb | AC5: Mar | AD5: Apr | AE5: May | AF5: Jun | AG5: Current Year Depn | AH5: Disposal/ Written off | AI5: Acc Depn c/f | AK5: =FBT!AA5 -> NBV As At 30/06/2025 | AL5: =FBT!AB5 -> NBV As At 30/06/2024
A6: 45017 | C6: TR-23-A0100001 | D6: BLOCK A SUPPLY & INSTALL ROOFING FASCIA, CLADDING, HOARDING, ACMV & FIRE FIGHTING SERVICES, MACHINE ROOM, WALL PARTITION & CEILING WORK | E6: CBE M&E ENGINEERING SDN BHD | F6: TAMPOI | G6: MAINT | H6: GENERAL | I6: 2201137/ 2201483 | J6: PU46555/ DT1169/ DT1196/ DT1195/ DT1208/ DT1216/ DT1230/ DT1332 | K6: INV2502/ INV2520/ INV2542/ INV2547/ INV2560/ INV2577/ INV2590/ INV2643 | L6: Installaton | M6: 1 | N6: lot | O6: 3949300.1 | P6: 0 | Q6: 0 | R6: =SUM(O6:Q6) -> 3949300.1 | S6: 120 | T6: -493662.51 | U6: =-$R6/$S6 -> -32910.834 | V6: =-$R6/$S6 -> -32910.834 | W6: =-$R6/$S6 -> -32910.834 | X6: =-$R6/$S6 -> -32910.834 | Y6: =-$R6/$S6 -> -32910.834 | Z6: =-$R6/$S6 -> -32910.834 | AA6: =-$R6/$S6 -> -32910.834 | AB6: =-$R6/$S6 -> -32910.834 | AC6: =-$R6/$S6 -> -32910.834 | AD6: 0 | AE6: 0 | AF6: 0 | AG6: =SUM(U6:AF6) -> -296197.51 | AH6: 0 | AI6: =T6+AG6+AH6 -> -789860.02 | AK6: =R6+AI6 -> 3159440.1 | AL6: =O6+T6 -> 3455637.6 | AP6: ROOF, JACK ROOF, FASCIA, CLADDING & HORADING WORK BLOCK A FACTORY AREA
A7: 45292 | C7: TR-24-A0100002 | D7: SUPPLY & INSTALL RENOVATION WORK AT BLOCK B & BLOCK C (TAMPOI) | E7: CBE M&E ENGINEERING SDN BHD | F7: TAMPOI | G7: MAINT | H7: GENERAL | I7: 2300450 | J7: DT1262/ DT1333/ DT1340/ DT1351/ DT1373/ DT1374/ DT1387 | K7: INV2612/ INV2644/ INV2656/ INV2674/ INV2701/ INV2723/ INV2755 | L7: Installaton | M7: 1 | N7: lot | O7: 3273509 | P7: 0 | Q7: 0 | R7: =SUM(O7:Q7) -> 3273509 | S7: 120 | T7: -163675.45 | U7: =-$R7/$S7 -> -27279.242 | V7: =-$R7/$S7 -> -27279.242 | W7: =-$R7/$S7 -> -27279.242 | X7: =-$R7/$S7 -> -27279.242 | Y7: =-$R7/$S7 -> -27279.242 | Z7: =-$R7/$S7 -> -27279.242 | AA7: =-$R7/$S7 -> -27279.242 | AB7: =-$R7/$S7 -> -27279.242 | AC7: =-$R7/$S7 -> -27279.242 | AD7: 0 | AE7: 0 | AF7: 0 | AG7: =SUM(U7:AF7) -> -245513.17 | AH7: 0 | AI7: =T7+AG7+AH7 -> -409188.62 | AK7: =R7+AI7 -> 2864320.4 | AL7: =O7+T7 -> 3109833.5 | AS7: Date | AT7: % | AU7: Total | AV7: Paid | AW7: TPO
AP8: Original Contract Sum | AU8: 4000000 | AW8: 2201137
O9: =SUM(O6:O8) -> 7222809.1 | P9: =SUM(P6:P8) -> 0 | Q9: =SUM(Q6:Q8) -> 0 | R9: =SUM(R6:R8) -> 7222809.1 | T9: =SUM(T6:T8) -> -657337.96 | U9: =SUM(U6:U8) -> -60190.076 | V9: =SUM(V6:V8) -> -60190.076 | W9: =SUM(W6:W8) -> -60190.076 | X9: =SUM(X6:X8) -> -60190.076 | Y9: =SUM(Y6:Y8) -> -60190.076 | Z9: =SUM(Z6:Z8) -> -60190.076 | AA9: =SUM(AA6:AA8) -> -60190.076 | ... AI9: =SUM(AI6:AI8) -> -1199048.6 | AK9: =SUM(AK6:AK8) -> 6023760.5 | AL9: =SUM(AL6:AL8) -> 6565471.1 | AP9: Less: Billing | AW9: 2201483
AP10: 40% DOWN PAYMENT | AQ10: PU46555 | AR10: INV2502 | AS10: 44770 | AT10: =AU10/AU$8 -> 0.4 | AU10: 1600000 | AV10: 1600000
AG11: In Balance Sheet as at 31/3/25 | AI11: -1199048.6 | AP11: PROGRESS CLAIM #1 | AQ11: DT1169 | AR11: INV2520 | AS11: 44835 | AT11: =AU11/AU$8 -> 0.15112576 | AU11: 604503.02 | AV11: 604503.02
AP12: PROGRESS CLAIM #2 | AQ12: DT1196 | AR12: INV2542 | AS12: 44865 | AT12: =AU12/AU$8 -> 0.16466032 | AU12: 658641.26 | AV12: 658641.26
AP13: PROGRESS CLAIM #3 | AQ13: DT1195 | AR13: INV2547 | AS13: 44879 | AT13: =AU13/AU$8 -> 0.070295625 | AU13: 281182.5 | AV13: 281182.5
AP14: PROGRESS CLAIM #4 | AQ14: DT1208 | AR14: INV2560 | AS14: 44903 | AT14: =AU14/AU$8 -> 0.03806458 | AU14: 152258.32 | AV14: 152258.32
AP15: PROGRESS CLAIM #5 | AQ15: DT1216 | AR15: INV2577 | AS15: 44932 | AT15: =AU15/AU$8 -> 0.059450058 | AU15: 237800.23 | AV15: 237800.23
AP16: PROGRESS CLAIM #6 | AQ16: DT1230 | AR16: INV2590 | AS16: 44957 | AT16: =AU16/AU$8 -> 0.033525345 | AU16: 134101.38 | AV16: =46941+87160.38 -> 134101.38
AP17: PROGRESS CLAIM #7 | AQ17: DT1332 | AR17: INV2643 | AS17: 45084 | AT17: =AU17/AU$8 -> 0.070203235 | AU17: 280812.94 | AV17: 280812.94
AT18: =SUM(AT8:AT17) -> 0.98732491 | AU18: =SUM(AU10:AU17) -> 3949299.6
AU19: =SUM(AU8)-SUM(AU18) -> 50700.35 | AV19: =SUM(AV10:AV18) -> 3949299.6
AP21: Renovation Work at Block B & C
AS22: Date | AT22: % | AU22: Total | AV22: Paid | AW22: Due | AX22: TPO
AP23: Original Contract Sum | AU23: 3280000 | AX23: 2300450
AP24: Less: Billing
AP25: 40% DOWN PAYMENT | AQ25: DT1262 | AR25: INV2612 | AS25: 45007 | AT25: =AU25/AU$23 -> 0.4 | AU25: 1312000 | AV25: 1312000 | AW25: =AU25-AV25 -> 0
AP26: PROGRESS CLAIM #1 | AQ26: DT1333 | AR26: INV2644 | AS26: 45084 | AT26: =AU26/AU$23 -> 0.16587002 | AU26: 544053.67 | AV26: 544053.67 | AW26: =AU26-AV26 -> 0
AP27: PROGRESS CLAIM #2 | AQ27: DT1340 | AR27: INV2656 | AS27: 45111 | AT27: =AU27/AU$23 -> 0.12754377 | AU27: 418343.55 | AV27: 418343.55 | AW27: =AU27-AV27 -> 0
AP28: PROGRESS CLAIM #3 | AQ28: DT1351 | AR28: INV2674 | AS28: 45138 | AT28: =AU28/AU$23 -> 0.069764271 | AU28: 228826.81 | AV28: 228826.81 | AW28: =AU28-AV28 -> 0
AP29: PROGRESS CLAIM #4 | AQ29: DT1373 | AR29: INV2701 | AS29: 45170 | AT29: =AU29/AU$23 -> 0.075523854 | AU29: 247718.24 | AV29: =AU29 -> 247718.24 | AW29: =AU29-AV29 -> 0
AP30: PROGRESS CLAIM #5 | AQ30: DT1374 | AR30: INV2723 | AS30: 45199 | AT30: =AU30/AU$23 -> 0.08027471 | AU30: 263301.05 | AV30: =AU30 -> 263301.05 | AW30: =AU30-AV30 -> 0
AP31: PROGRESS CLAIM #6 | AQ31: DT1387 | AR31: INV2755 | AS31: 45245 | AT31: =AU31/AU$23 -> 0.045560826 | AU31: 149439.51 | AV31: =47000+10000+10000+30000+50000 -> 147000 | AW31: =AU31-AV31 -> 2439.51 | AX31: *Updated up to 31.12.2024
AP32: PROGRESS CLAIM #7 | AQ32: DT1436 | AR32: INV2888 | AS32: 45427 | AT32: =AU32/AU$23 -> 0.033483588 | AU32: 109826.17 | AV32: 0 | AW32: =AU32-AV32 -> 109826.17
AT33: =SUM(AT22:AT32) -> 0.99802104 | AU33: =SUM(AU25:AU32) -> 3273509
AU34: =SUM(AU23)-SUM(AU33) -> 6491 | AV34: =SUM(AV24:AV33) -> 3161243.3 | AW34: =SUM(AW24:AW33) -> 112265.68
F67: `

Sheet IR
A1: =[33]LAND!A1 -> TOMYPAK FLEXIBLE PACKAGING SDN BHD
A2: =[33]LAND!A2 -> FOR THE YEAR ENDED 30 JUNE 2025
A3: INSTALLATION AND RENOVATION
A4: 11101-013 | AI4: Closing | AK4: Closing | AL4: Opening
A5: Acquisition Date | B5: Disposal Date | C5: F/A Code | D5: F/A Description | E5: Suppliers | F5: Cost Ctr. 1 | G5: Cost Ctr. 2 | H5: Cost Ctr. 3 | I5: Purchase Order | J5: NO. | K5: Invoice No. | L5: Remarks | M5: Quantity | O5: Cost c/f | P5: Addition | Q5: Disposal/ Written off | R5: Cost b/f | S5: Months | T5: Acc Depn b/f | U5: Jul | V5: Aug | W5: Sept | X5: Oct | Y5: Nov | Z5: Dec | AA5: Jan | AB5: Feb | AC5: Mar | AD5: Apr | AE5: May | AF5: Jun | AG5: Current Year Depn | AH5: Disposal/ Written off | AI5: Acc Depn c/f | AK5: =FBT!AA5 -> NBV As At 30/06/2025 | AL5: =FBT!AB5 -> NBV As At 30/06/2024
A6: 40755 | C6: IR10-001/01 | D6: GLASS PARTITION AT NEW R&D OFFICE | F6: TAMPOI | G6: RND | H6: General | M6: 1 | N6: Unit | O6: 1900 | P6: 0 | Q6: 0 | R6: =SUM(O6:Q6) -> 1900 | S6: 300 | T6: -1107.82 | U6: -6.33 | V6: =-$R6/$S6 -> -6.3333333 | W6: =-$R6/$S6 -> -6.3333333 | X6: =-$R6/$S6 -> -6.3333333 | Y6: =-$R6/$S6 -> -6.3333333 | Z6: =-$R6/$S6 -> -6.3333333 | AA6: =-$R6/$S6 -> -6.3333333 | AB6: =-$R6/$S6 -> -6.3333333 | AC6: =-$R6/$S6 -> -6.3333333 | AD6: 0 | AE6: 0 | AF6: 0 | AG6: =SUM(U6:AF6) -> -56.996667 | AH6: 0 | AI6: =T6+AG6+AH6 -> -1164.8167 | AK6: =R6+AI6 -> 735.18333 | AL6: =O6+T6 -> 792.18
A7: 44782 | C7: IR-22-A0100090 | D7: WALLPAPER INSTALLATION AT BLOCK A MAIN OFFICE | E7: COB CARPET & RENOVATION SDN BHD | F7: TAMPOI | G7: HR | H7: GENERAL | I7: N/A | J7: PU46717 | K7: 20220086 | L7: Installation works | M7: 14 | N7: ROLL | O7: 6192.63 | P7: 0 | Q7: 0 | R7: =SUM(O7:Q7) -> 6192.63 | S7: 60 | T7: -2373.8345 | U7: -103.21 | V7: =-$R7/$S7 -> -103.2105 | W7: =-$R7/$S7 -> -103.2105 | X7: =-$R7/$S7 -> -103.2105 | Y7: =-$R7/$S7 -> -103.2105 | Z7: =-$R7/$S7 -> -103.2105 | AA7: =-$R7/$S7 -> -103.2105 | AB7: =-$R7/$S7 -> -103.2105 | AC7: =-$R7/$S7 -> -103.2105 | AD7: 0 | AE7: 0 | AF7: 0 | AG7: =SUM(U7:AF7) -> -928.894 | AH7: 0 | AI7: =T7+AG7+AH7 -> -3302.7285 | AK7: =R7+AI7 -> 2889.9015 | AL7: =O7+T7 -> 3818.7955
A8: 44782 | C8: IR-22-B0100090 | D8: DISMANTLE EXISTING WALLPAPER AT BLOCK A MAIN OFFICE | E8: COB CARPET & RENOVATION SDN BHD | F8: TAMPOI | G8: HR | H8: GENERAL | I8: N/A | J8: PU46717 | K8: 20220086 | L8: Installation works | M8: 1600 | N8: SQFT | O8: 1326.99 | P8: 0 | Q8: 0 | R8: =SUM(O8:Q8) -> 1326.99 | S8: 60 | T8: -508.7285 | U8: -22.12 | V8: =-$R8/$S8 -> -22.1165 | W8: =-$R8/$S8 -> -22.1165 | X8: =-$R8/$S8 -> -22.1165 | Y8: =-$R8/$S8 -> -22.1165 | Z8: =-$R8/$S8 -> -22.1165 | AA8: =-$R8/$S8 -> -22.1165 | AB8: =-$R8/$S8 -> -22.1165 | AC8: =-$R8/$S8 -> -22.1165 | AD8: 0 | AE8: 0 | AF8: 0 | AG8: =SUM(U8:AF8) -> -199.052 | AH8: 0 | AI8: =T8+AG8+AH8 -> -707.7805 | AK8: =R8+AI8 -> 619.2095 | AL8: =O8+T8 -> 818.2615
A9: 44782 | C9: IR-22-B0200090 | D9: PAINTING AT BLOCK A MAIN OFFICE | E9: COB CARPET & RENOVATION SDN BHD | F9: TAMPOI | G9: HR | H9: GENERAL | I9: N/A | J9: PU46717 | K9: 20220086 | L9: Installation works | M9: 1 | N9: JOB | O9: 230.38 | P9: 0 | Q9: 0 | R9: =SUM(O9:Q9) -> 230.38 | S9: 36 | T9: -147.195 | U9: -6.4 | V9: =-$R9/$S9 -> -6.3994444 | W9: =-$R9/$S9 -> -6.3994444 | X9: =-$R9/$S9 -> -6.3994444 | Y9: =-$R9/$S9 -> -6.3994444 | Z9: =-$R9/$S9 -> -6.3994444 | AA9: =-$R9/$S9 -> -6.3994444 | AB9: =-$R9/$S9 -> -6.3994444 | AC9: =-$R9/$S9 -> -6.3994444 | AD9: 0 | AE9: 0 | AF9: 0 | AG9: =SUM(U9:AF9) -> -57.595556 | AH9: 0 | AI9: =T9+AG9+AH9 -> -204.79056 | AK9: =R9+AI9 -> 25.589444 | AL9: =O9+T9 -> 83.185
A10: 41214 | C10: IR-00001A01-12 | D10: Extend 4ft For HR Office | F10: TAMPOI | G10: HR | H10: General | M10: 1 | N10: Unit | O10: 469 | P10: 0 | Q10: 0 | R10: =SUM(O10:Q10) -> 469 | S10: 120 | T10: -469 | U10: 0 | V10: 0 | W10: 0 | X10: 0 | Y10: 0 | Z10: 0 | AA10: 0 | AB10: 0 | AC10: 0 | AD10: 0 | AE10: 0 | AF10: 0 | AG10: =SUM(U10:AF10) -> 0 | AH10: 0 | AI10: =T10+AG10+AH10 -> -469 | AK10: =R10+AI10 -> 0 | AL10: =O10+T10 -> 0
A11: 44782 | C11: IR-22-B0100091 | D11: PAINTING JOB AT BLOCK A MAIN OFFICE | E11: FEI XIONG INTERIOR & RENOVATION | F11: TAMPOI | G11: HR | H11: GENERAL | I11: N/A | J11: PU46718 | K11: 0337 | L11: Installation works | M11: 1 | N11: JOB | O11: 4300 | P11: 0 | Q11: 0 | R11: =SUM(O11:Q11) -> 4300 | S11: 60 | T11: -1648.38 | U11: -71.67 | V11: =-$R11/$S11 -> -71.666667 | W11: =-$R11/$S11 -> -71.666667 | X11: =-$R11/$S11 -> -71.666667 | Y11: =-$R11/$S11 -> -71.666667 | Z11: =-$R11/$S11 -> -71.666667 | AA11: =-$R11/$S11 -> -71.666667 | AB11: =-$R11/$S11 -> -71.666667 | AC11: =-$R11/$S11 -> -71.666667 | AD11: 0 | AE11: 0 | AF11: 0 | AG11: =SUM(U11:AF11) -> -645.00333 | AH11: 0 | AI11: =T11+AG11+AH11 -> -2293.3833 | AK11: =R11+AI11 -> 2006.6167 | AL11: =O11+T11 -> 2651.62
A12: 41214 | C12: IR-00002A01-12 | D12: Purchasing Office | F12: TAMPOI | G12: HR | H12: General | M12: 1 | N12: Unit | O12: 3589 | P12: 0 | Q12: 0 | R12: =SUM(O12:Q12) -> 3589 | S12: 120 | T12: -3589 | U12: 0 | V12: 0 | W12: 0 | X12: 0 | Y12: 0 | Z12: 0 | AA12: 0 | AB12: 0 | AC12: 0 | AD12: 0 | AE12: 0 | AF12: 0 | AG12: =SUM(U12:AF12) -> 0 | AH12: 0 | AI12: =T12+AG12+AH12 -> -3589 | AK12: =R12+AI12 -> 0 | AL12: =O12+T12 -> 0
A13: 41214 | C13: IR-00003A01-12 | D13: Door & Window | F13: TAMPOI | G13: HR | H13: General | M13: 1 | N13: Unit | O13: 4196 | P13: 0 | Q13: 0 | R13: =SUM(O13:Q13) -> 4196 | S13: 120 | T13: -4196 | U13: 0 | V13: 0 | W13: 0 | X13: 0 | Y13: 0 | Z13: 0 | AA13: 0 | AB13: 0 | AC13: 0 | AD13: 0 | AE13: 0 | AF13: 0 | AG13: =SUM(U13:AF13) -> 0 | AH13: 0 | AI13: =T13+AG13+AH13 -> -4196 | AK13: =R13+AI13 -> 0 | AL13: =O13+T13 -> 0
A14: 44782 | C14: IR-22-B0200092 | D14: SERVICE INSTALLATION JOB AT BLOCK A MAIN OFFICE RENOVATION WORK AT TAMPOI MAIN OFFICE BLOCK A | E14: KK OFFICEPOINT SDN BHD | F14: TAMPOI | G14: HR | H14: GENERAL | I14: N/A | J14: PU46721 | K14: IN2206-0051 | L14: Installation works | M14: 1 | N14: JOB | O14: 200 | P14: 0 | Q14: 0 | R14: =SUM(O14:Q14) -> 200 | S14: 60 | T14: -76.62 | U14: -3.33 | V14: =-$R14/$S14 -> -3.3333333 | W14: =-$R14/$S14 -> -3.3333333 | X14: =-$R14/$S14 -> -3.3333333 | Y14: =-$R14/$S14 -> -3.3333333 | Z14: =-$R14/$S14 -> -3.3333333 | AA14: =-$R14/$S14 -> -3.3333333 | AB14: =-$R14/$S14 -> -3.3333333 | AC14: =-$R14/$S14 -> -3.3333333 | AD14: 0 | AE14: 0 | AF14: 0 | AG14: =SUM(U14:AF14) -> -29.996667 | AH14: 0 | AI14: =T14+AG14+AH14 -> -106.61667 | AK14: =R14+AI14 -> 93.383333 | AL14: =O14+T14 -> 123.38
A15: 42094 | C15: IR-00012A01-15 | D15: BRAND: CANSTAR CONE; MODEL: CCF58-31A | F15: TAMPOI | G15: CPP | H15: General | M15: 1 | N15: Unit | O15: 47000 | P15: 0 | Q15: 0 | R15: =SUM(O15:Q15) -> 47000 | S15: 120 | T15: -44258.68 | U15: -391.67 | V15: =-$R15/$S15 -> -391.66667 | W15: =-$R15/$S15 -> -391.66667 | X15: =-$R15/$S15 -> -391.66667 | Y15: =-$R15/$S15 -> -391.66667 | Z15: =-$R15/$S15 -> -391.66667 | AA15: =-$R15/$S15+0.35 -> -391.31667 | AB15: 0 | AC15: 0 | AD15: 0 | AE15: 0 | AF15: 0 | AG15: =SUM(U15:AF15) -> -2741.32 | AH15: 0 | AI15: =T15+AG15+AH15 -> -47000 | AK15: =R15+AI15 -> 0 | AL15: =O15+T15 -> 2741.32
A16: 44826 | C16: IR-22-A0100093 | D16: MATERIALS, LABOUR, EQUIPMENT AND CONSUMABLE TO FABRICATE AND INSTALL MACHINERY FOUNDATION | E16: F-I ENGINEERING SDN BHD | F16: TAMPOI | G16: MAINT | H16: GENERAL | I16: 2200932 | J16: DT 1023/ DT 1091/ DT 1164 | K16: 6780/ 6899/ 6921 | L16: Installation works | M16: 1 | N16: Unit | O16: 560000 | P16: 0 | Q16: 0 | R16: =SUM(O16:Q16) -> 560000 | S16: 120 | T16: -102666.71 | U16: -4666.67 | V16: =-$R16/$S16 -> -4666.6667 | W16: =-$R16/$S16 -> -4666.6667 | X16: =-$R16/$S16 -> -4666.6667 | Y16: =-$R16/$S16 -> -4666.6667 | Z16: =-$R16/$S16 -> -4666.6667 | AA16: =-$R16/$S16 -> -4666.6667 | AB16: =-$R16/$S16 -> -4666.6667 | AC16: =-$R16/$S16 -> -4666.6667 | AD16: 0 | AE16: 0 | AF16: 0 | AG16: =SUM(U16:AF16) -> -42000.003 | AH16: 0 | AI16: =T16+AG16+AH16 -> -144666.71 | AK16: =R16+AI16 -> 415333.29 | AL16: =O16+T16 -> 457333.29
A17: 44859 | C17: IR-22-A0100094 | D17: CONSTRUCT R.C PIT STRUCTURE, PROVIDE ALL FORMWORK, TIE ROD AND CAST 200MM THICK CONCRETE WITH BRC A8, T12 STARTER BAR 300 C/C ON EXISTING CONCRETE FLOOR | E17: F-I ENGINEERING SDN BHD | F17: TAMPOI | G17: MAINT | H17: GENERAL | I17: 2201338 | J17: DT 1122/ DT1170 | K17: 6907/ 6942 | L17: Installation works | M17: 1 | N17: Unit | O17: 43000 | P17: 0 | Q17: 0 | R17: =SUM(O17:Q17) -> 43000 | S17: 120 | T17: -7524.96 | U17: -358.33 | V17: =-$R17/$S17 -> -358.33333 | W17: =-$R17/$S17 -> -358.33333 | X17: =-$R17/$S17 -> -358.33333 | Y17: =-$R17/$S17 -> -358.33333 | Z17: =-$R17/$S17 -> -358.33333 | AA17: =-$R17/$S17 -> -358.33333 | AB17: =-$R17/$S17 -> -358.33333 | AC17: =-$R17/$S17 -> -358.33333 | AD17: 0 | AE17: 0 | AF17: 0 | AG17: =SUM(U17:AF17) -> -3224.9967 | AH17: 0 | AI17: =T17+AG17+AH17 -> -10749.957 | AK17: =R17+AI17 -> 32250.043 | AL17: =O17+T17 -> 35475.04
A18: 42124 | C18: IR-00013A01-15 | D18: GOLD AROWANA (30X60 INS) | F18: TAMPOI | G18: HR | H18: General | M18: 1 | N18: Unit | O18: 20888 | P18: 0 | Q18: 0 | R18: =SUM(O18:Q18) -> 20888 | S18: 120 | T18: -19495.81 | U18: -174.07 | V18: =-$R18/$S18 -> -174.06667 | W18: =-$R18/$S18 -> -174.06667 | X18: =-$R18/$S18 -> -174.06667 | Y18: =-$R18/$S18 -> -174.06667 | Z18: =-$R18/$S18 -> -174.06667 | AA18: =-$R18/$S18 -> -174.06667 | AB18: -173.72 | AC18: 0 | AD18: 0 | AE18: 0 | AF18: 0 | AG18: =SUM(U18:AF18) -> -1392.19 | AH18: 0 | AI18: =T18+AG18+AH18 -> -20888 | AK18: =R18+AI18 -> 0 | AL18: =O18+T18 -> 1392.19
A19: 43221 | C19: IR-00041A01-18 | D19: 2500AMP SSB-2 SUB BOARD REPLACE (EXPLOSION) | F19: TAMPOI | G19: CORPORAT | H19: GENERAL | M19: 1 | N19: UNIT | O19: 270333.96 | P19: 0 | Q19: 0 | R19: =SUM(O19:Q19) -> 270333.96 | S19: 120 | T19: -166705.75 | U19: -2252.78 | V19: =-$R19/$S19 -> -2252.783 | W19: =-$R19/$S19 -> -2252.783 | X19: =-$R19/$S19 -> -2252.783 | Y19: =-$R19/$S19 -> -2252.783 | Z19: =-$R19/$S19 -> -2252.783 | AA19: =-$R19/$S19 -> -2252.783 | AB19: =-$R19/$S19 -> -2252.783 | AC19: =-$R19/$S19 -> -2252.783 | AD19: 0 | AE19: 0 | AF19: 0 | AG19: =SUM(U19:AF19) -> -20275.044 | AH19: 0 | AI19: =T19+AG19+AH19 -> -186980.79 | AK19: =R19+AI19 -> 83353.169 | AL19: =O19+T19 -> 103628.21
A20: 44782 | C20: IR-22-A0100091 | D20: 2 SETS OF ALUMINIUM DOOR (3X7) FOR BLOCK A MAIN OFFICE | E20: FEI XIONG INTERIOR & RENOVATION | F20: TAMPOI | G20: HR | H20: GENERAL | I20: N/A | J20: PU46718 | K20: 0337 | M20: 2 | N20: SET | O20: 2150 | P20: 0 | Q20: 0 | R20: =SUM(O20:Q20) -> 2150 | S20: 120 | T20: -412.13 | U20: -17.92 | V20: =-$R20/$S20 -> -17.916667 | W20: =-$R20/$S20 -> -17.916667 | X20: =-$R20/$S20 -> -17.916667 | Y20: =-$R20/$S20 -> -17.916667 | Z20: =-$R20/$S20 -> -17.916667 | AA20: =-$R20/$S20 -> -17.916667 | AB20: =-$R20/$S20 -> -17.916667 | AC20: =-$R20/$S20 -> -17.916667 | AD20: 0 | AE20: 0 | AF20: 0 | AG20: =SUM(U20:AF20) -> -161.25333 | AH20: 0 | AI20: =T20+AG20+AH20 -> -573.38333 | AK20: =R20+AI20 -> 1576.6167 | AL20: =O20+T20 -> 1737.87
A21: 44782 | C21: IR-22-A0100092 | D21: KALPHA 6+8 SEATER CLUSTER WORKSTATION WITH 14 X SILVER ALLUMINIUM & WIRE FLIPPER CASINGS-RENOVATION WORK AT TAMPOI MAIN OFFICE BLOCK A | E21: KK OFFICEPOINT SDN BHD | F21: TAMPOI | G21: HR | H21: GENERAL | I21: N/A | J21: PU46721 | K21: IN2206-0051 | M21: 1 | N21: SET | O21: 5700 | P21: 0 | Q21: 0 | R21: =SUM(O21:Q21) -> 5700 | S21: 120 | T21: -1092.5 | U21: -47.5 | V21: =-$R21/$S21 -> -47.5 | W21: =-$R21/$S21 -> -47.5 | X21: =-$R21/$S21 -> -47.5 | Y21: =-$R21/$S21 -> -47.5 | Z21: =-$R21/$S21 -> -47.5 | AA21: =-$R21/$S21 -> -47.5 | AB21: =-$R21/$S21 -> -47.5 | AC21: =-$R21/$S21 -> -47.5 | AD21: 0 | AE21: 0 | AF21: 0 | AG21: =SUM(U21:AF21) -> -427.5 | AH21: 0 | AI21: =T21+AG21+AH21 -> -1520 | AK21: =R21+AI21 -> 4180 | AL21: =O21+T21 -> 4607.5
A22: 44942 | C22: IR-23-A0100098 | D22: PROVISION OF MATERIALS, LABOUR, EQUIPMENT AND CONSUMABLE TO FABRICATE AND INSTALL MACHINERY FOUNDATION | E22: F-I ENGINEERING SDN BHD | F22: TAMPOI | G22: MAINT | H22: GENERAL | I22: 2201578 | J22: DT 1172/ DT 1225 | K22: 6947/ 6992 | L22: Installation works | M22: 1 | N22: Unit | O22: 44070 | P22: 0 | Q22: 0 | R22: =SUM(O22:Q22) -> 44070 | S22: 120 | T22: -6610.5 | U22: -367.25 | V22: =-$R22/$S22 -> -367.25 | W22: =-$R22/$S22 -> -367.25 | X22: =-$R22/$S22 -> -367.25 | Y22: =-$R22/$S22 -> -367.25 | Z22: =-$R22/$S22 -> -367.25 | AA22: =-$R22/$S22 -> -367.25 | AB22: =-$R22/$S22 -> -367.25 | AC22: =-$R22/$S22 -> -367.25 | AD22: 0 | AE22: 0 | AF22: 0 | AG22: =SUM(U22:AF22) -> -3305.25 | AH22: 0 | AI22: =T22+AG22+AH22 -> -9915.75 | AK22: =R22+AI22 -> 34154.25 | AL22: =O22+T22 -> 37459.5
A23: 44965 | C23: IR-23-A0100100 | D23: MANIFOLD AND PIPING SYSTEM OF GC P-AIR MANIFOLD SYSTEM P-AIR PIPING SYSTEM NITROGEN MANIFOLD AND PIPING SYSTEM HYDROGEN MANIFOLD AND PIPING SYSTEM HELIUM MANIFOLD AND PIPING SYSTEM MANIFOLD AND PIPING SYSTEM OF OTR OXYGEN MANIFOLD AND PIPING SYSTEM 98% NITROGEN 2% HYDROGEN MANIFOLD AND PIPING SYSTEM MANIFOLD AND PIPING SYSTEM OF WVTR NITROGEN MANIFOLD AND PIPING SYSTEM | E23: PIALA ENGINEERING & SERVICES | F23: TAMPOI | G23: QC | H23: GENERAL | I23: 2300145 | J23: DT 1241/ DT 1227 | K23: INV000860/ INV000858 | L23: Installation works | M23: 1 | N23: Unit | O23: 51000 | P23: 0 | Q23: 0 | R23: =SUM(O23:Q23) -> 51000 | S23: 120 | T23: -7225 | U23: -425 | V23: =-$R23/$S23 -> -425 | W23: =-$R23/$S23 -> -425 | X23: =-$R23/$S23 -> -425 | Y23: =-$R23/$S23 -> -425 | Z23: =-$R23/$S23 -> -425 | AA23: =-$R23/$S23 -> -425 | AB23: =-$R23/$S23 -> -425 | AC23: =-$R23/$S23 -> -425 | AD23: 0 | AE23: 0 | AF23: 0 | AG23: =SUM(U23:AF23) -> -3825 | AH23: 0 | AI23: =T23+AG23+AH23 -> -11050 | AK23: =R23+AI23 -> 39950 | AL23: =O23+T23 -> 43775
A24: 44970 | C24: IR-23-A0100102 | D24: ADDITIONAL WORK OF MS STAIRCASE FOR BLOCK A TO SUPPLY & INSTALL ESCAPE LADDER FROM BLOCK A LABORATORY OFFICE TO GROUND FLOOR,USING METAL PLATFORM & STAIRCASE C/W PAINTING | E24: CBE M&E ENGINEERING SDN BHD | F24: TAMPOI | G24: MAINT | H24: GENERAL | I24: 2201898 | J24: 49394 | K24: INV2594 | L24: Installation works | M24: 1 | N24: lot | O24: 10625 | P24: 0 | Q24: 0 | R24: =SUM(O24:Q24) -> 10625 | S24: 120 | T24: -1505.195 | U24: -88.54 | V24: =-$R24/$S24 -> -88.541667 | W24: =-$R24/$S24 -> -88.541667 | X24: =-$R24/$S24 -> -88.541667 | Y24: =-$R24/$S24 -> -88.541667 | Z24: =-$R24/$S24 -> -88.541667 | AA24: =-$R24/$S24 -> -88.541667 | AB24: =-$R24/$S24 -> -88.541667 | AC24: =-$R24/$S24 -> -88.541667 | AD24: 0 | AE24: 0 | AF24: 0 | AG24: =SUM(U24:AF24) -> -796.87333 | AH24: 0 | AI24: =T24+AG24+AH24 -> -2302.0683 | AK24: =R24+AI24 -> 8322.9317 | AL24: =O24+T24 -> 9119.805
A25: 44970 | C25: IR-23-A0100101 | D25: ADDITIONAL RC PLINTH & STEEL PLATFORM FOR SMOKE SPILL SYSTEM EQUIPMENT | E25: CBE M&E ENGINEERING SDN BHD | F25: TAMPOI | G25: MAINT | H25: GENERAL | I25: 2300037 | J25: DT 1243 | K25: INV2593 | L25: Installation works | M25: 1 | N25: lot | O25: 75331 | P25: 0 | Q25: 0 | R25: =SUM(O25:Q25) -> 75331 | S25: 120 | T25: -10671.905 | U25: -627.76 | V25: =-$R25/$S25 -> -627.75833 | W25: =-$R25/$S25 -> -627.75833 | X25: =-$R25/$S25 -> -627.75833 | Y25: =-$R25/$S25 -> -627.75833 | Z25: =-$R25/$S25 -> -627.75833 | AA25: =-$R25/$S25 -> -627.75833 | AB25: =-$R25/$S25 -> -627.75833 | AC25: =-$R25/$S25 -> -627.75833 | AD25: 0 | AE25: 0 | AF25: 0 | AG25: =SUM(U25:AF25) -> -5649.8267 | AH25: 0 | AI25: =T25+AG25+AH25 -> -16321.732 | AK25: =R25+AI25 -> 59009.268 | AL25: =O25+T25 -> 64659.095
A26: 44782 | C26: IR-22-B0100092 | D26: KALPHA L-SHAPED TABLE WITH WOODEN DIVIDE PANEL & 1X SILVER ALUMINIUM WIRE FLIPPER CASING-RENOVATION WORK AT TAMPOI MAIN OFFICE BLOCK A | E26: KK OFFICEPOINT SDN BHD | F26: TAMPOI | G26: HR | H26: GENERAL | I26: N/A | J26: PU46721 | K26: IN2206-0051 | M26: 1 | N26: Unit | O26: 980 | P26: 0 | Q26: 0 | R26: =SUM(O26:Q26) -> 980 | S26: 60 | T26: -375.62 | U26: -16.33 | V26: =-$R26/$S26 -> -16.333333 | W26: =-$R26/$S26 -> -16.333333 | X26: =-$R26/$S26 -> -16.333333 | Y26: =-$R26/$S26 -> -16.333333 | Z26: =-$R26/$S26 -> -16.333333 | AA26: =-$R26/$S26 -> -16.333333 | AB26: =-$R26/$S26 -> -16.333333 | AC26: =-$R26/$S26 -> -16.333333 | AD26: 0 | AE26: 0 | AF26: 0 | AG26: =SUM(U26:AF26) -> -146.99667 | AH26: 0 | AI26: =T26+AG26+AH26 -> -522.61667 | AK26: =R26+AI26 -> 457.38333 | AL26: =O26+T26 -> 604.38
A27: 44782 | C27: IR-22-B0300092 | D27: WOODEN MOBILE PEDESTAL 3-DRAWER-RENOVATION WORK AT TAMPOI MAIN OFFICE BLOCK A | E27: KK OFFICEPOINT SDN BHD | F27: TAMPOI | G27: HR | H27: GENERAL | I27: N/A | J27: PU46721 | K27: IN2206-0051 | M27: 15 | N27: Unit | O27: 3120 | P27: 0 | Q27: 0 | R27: =SUM(O27:Q27) -> 3120 | S27: 120 | T27: -598 | U27: -26 | V27: =-$R27/$S27 -> -26 | W27: =-$R27/$S27 -> -26 | X27: =-$R27/$S27 -> -26 | Y27: =-$R27/$S27 -> -26 | Z27: =-$R27/$S27 -> -26 | AA27: =-$R27/$S27 -> -26 | AB27: =-$R27/$S27 -> -26 | AC27: =-$R27/$S27 -> -26 | AD27: 0 | AE27: 0 | AF27: 0 | AG27: =SUM(U27:AF27) -> -234 | AH27: 0 | AI27: =T27+AG27+AH27 -> -832 | AK27: =R27+AI27 -> 2288 | AL27: =O27+T27 -> 2522
A28: 44865 | C28: IR-22-A0100095 | D28: KALPHA 6 SEATER CLUSTER WORKSTATION WITH 3 X WOODEN PANEL + 6X SILVER WIRE FLIPPER CASINGS | E28: KK OFFICEPOINT SDN BHD | F28: TAMPOI | G28: HR | H28: GENERAL | I28: N/A | J28: PU47690 | K28: IN2209-0757 | M28: 1 | N28: SET | O28: 2450 | P28: 0 | Q28: 0 | R28: =SUM(O28:Q28) -> 2450 | S28: 120 | T28: -428.79 | U28: -20.42 | V28: =-$R28/$S28 -> -20.416667 | W28: =-$R28/$S28 -> -20.416667 | X28: =-$R28/$S28 -> -20.416667 | Y28: =-$R28/$S28 -> -20.416667 | Z28: =-$R28/$S28 -> -20.416667 | AA28: =-$R28/$S28 -> -20.416667 | AB28: =-$R28/$S28 -> -20.416667 | AC28: =-$R28/$S28 -> -20.416667 | AD28: 0 | AE28: 0 | AF28: 0 | AG28: =SUM(U28:AF28) -> -183.75333 | AH28: 0 | AI28: =T28+AG28+AH28 -> -612.54333 | AK28: =R28+AI28 -> 1837.4567 | AL28: =O28+T28 -> 2021.21
A29: 45002 | C29: IR-23-A0100105 | D29: PRINTING OFFICE LABOUR SUPPLY AND TOOLS TO DISMANTLE EXISTING CEILING,TABLE & PARTITION C/W SITE CLEANING PRINTING OFFICE 2' X 4' X 9MM THK LAMINATED CEILING BOARD & FRAME ONE LAYER 12MM THK PLASTERING PARTITION TWO LAYER 12MM THK PLASTERING PARTITION 3' X 7' ALUMINIUM DOOR C/W DOOR FRAME WALL PAINTING WORKS | E29: F-I ENGINEERING SDN BHD | F29: TAMPOI | G29: MAINT | H29: GENERAL | I29: 2300274 | J29: 49111 | K29: 7028 | L29: Installation works | M29: 1 | N29: Unit | O29: 11526.92 | P29: 0 | Q29: 0 | R29: =SUM(O29:Q29) -> 11526.92 | S29: 120 | T29: -1536.939 | U29: -96.06 | V29: =-$R29/$S29 -> -96.057667 | W29: =-$R29/$S29 -> -96.057667 | X29: =-$R29/$S29 -> -96.057667 | Y29: =-$R29/$S29 -> -96.057667 | Z29: =-$R29/$S29 -> -96.057667 | AA29: =-$R29/$S29 -> -96.057667 | AB29: =-$R29/$S29 -> -96.057667 | AC29: =-$R29/$S29 -> -96.057667 | AD29: 0 | AE29: 0 | AF29: 0 | AG29: =SUM(U29:AF29) -> -864.52133 | AH29: 0 | AI29: =T29+AG29+AH29 -> -2401.4603 | AK29: =R29+AI29 -> 9125.4597 | AL29: =O29+T29 -> 9989.981
A30: 45063 | C30: IR-23-A0100107 | D30: SUPPLY & LAY ADDITIONAL UV COATING ON SURFACE | E30: CBE M&E ENGINEERING SDN BHD | F30: TAMPOI | G30: MAINT | H30: GENERAL | I30: 2300771 | J30: DT1303/ DT1304/ DT1305 | K30: INV2632/ INV2632-A/ INV2632-B | L30: Installation works | M30: 1 | N30: lot | O30: 283300 | P30: 0 | Q30: 0 | R30: =SUM(O30:Q30) -> 283300 | S30: 120 | T30: -33051.65 | U30: -2360.83 | V30: =-$R30/$S30 -> -2360.8333 | W30: =-$R30/$S30 -> -2360.8333 | X30: =-$R30/$S30 -> -2360.8333 | Y30: =-$R30/$S30 -> -2360.8333 | Z30: =-$R30/$S30 -> -2360.8333 | AA30: =-$R30/$S30 -> -2360.8333 | AB30: =-$R30/$S30 -> -2360.8333 | AC30: =-$R30/$S30 -> -2360.8333 | AD30: 0 | AE30: 0 | AF30: 0 | AG30: =SUM(U30:AF30) -> -21247.497 | AH30: 0 | AI30: =T30+AG30+AH30 -> -54299.147 | AK30: =R30+AI30 -> 229000.85 | AL30: =O30+T30 -> 250248.35
A31: 44865 | C31: IR-22-B0100095 | D31: MOBILE PEDESTAL 2-DRAWER 1 FILING | E31: KK OFFICEPOINT SDN BHD | F31: TAMPOI | G31: HR | H31: GENERAL | I31: N/A | J31: PU47690 | K31: IN2209-0757 | M31: 6 | N31: Unit | O31: 1248 | P31: 0 | Q31: 0 | R31: =SUM(O31:Q31) -> 1248 | S31: 120 | T31: -218.4 | U31: -10.4 | V31: =-$R31/$S31 -> -10.4 | W31: =-$R31/$S31 -> -10.4 | X31: =-$R31/$S31 -> -10.4 | Y31: =-$R31/$S31 -> -10.4 | Z31: =-$R31/$S31 -> -10.4 | AA31: =-$R31/$S31 -> -10.4 | AB31: =-$R31/$S31 -> -10.4 | AC31: =-$R31/$S31 -> -10.4 | AD31: 0 | AE31: 0 | AF31: 0 | AG31: =SUM(U31:AF31) -> -93.6 | AH31: 0 | AI31: =T31+AG31+AH31 -> -312 | AK31: =R31+AI31 -> 936 | AL31: =O31+T31 -> 1029.6
A32: 44935 | C32: IR-23-A0100096 | D32: TAMPOI BLOCK A PT 8C RIGHT TO LEFT TO SUPPLY LABOUR AND MATERIAL TO INSTALL EXHAUST DUCTING TO ROOFTOP 3M C/W ROOFING (INCLUDE INVERTER CAP,NUMBERING AND SAMPLING PORT) TO SUPPLY LABOUR MATERIAL TO INSTALL BURNER DUCTING AND JOINT TO MACHINE C/W 100MM FIBERGLASS EXTERNAL INSULATION TO SUPPLY LABOUR AND MATERIAL TO INSTALL SOLVENT EXHAUST DUCTING TO ROOFTOP 3M C/W ROOFING(INCLUDE INVERTER CAP,NUMBERING AND SAMPLING PORT) TO SUPPLY LABOUR AND MATERIAL TO INSTALL 2NOS EXHAUST BLOWER (NO INCLUDE WIRING WORK) TO SUPPLY LABOUR AND MATERIAL TO INSTALL FILTER BOX C/W PRESSURE GAUGE METER(INCLUDE CARBON FILTER) | E32: BAN KIM ENGINEERING WORKS | F32: TAMPOI | G32: MAINT | H32: GENERAL | I32: 2200956 | J32: PU48411 | K32: 23/01-008 | L32: Installation works | M32: 1 | N32: Unit | O32: 103000 | P32: 0 | Q32: 0 | R32: =SUM(O32:Q32) -> 103000 | S32: 120 | T32: -15449.97 | U32: -858.33 | V32: =-$R32/$S32 -> -858.33333 | W32: =-$R32/$S32 -> -858.33333 | X32: =-$R32/$S32 -> -858.33333 | Y32: =-$R32/$S32 -> -858.33333 | Z32: =-$R32/$S32 -> -858.33333 | AA32: =-$R32/$S32 -> -858.33333 | AB32: =-$R32/$S32 -> -858.33333 | AC32: =-$R32/$S32 -> -858.33333 | AD32: 0 | AE32: 0 | AF32: 0 | AG32: =SUM(U32:AF32) -> -7724.9967 | AH32: 0 | AI32: =T32+AG32+AH32 -> -23174.967 | AK32: =R32+AI32 -> 79825.033 | AL32: =O32+T32 -> 87550.03
A33: 44939 | C33: IR-23-A0100097 | D33: TAMPOI BLOCK A PT 9C TO SUPPLY LABOUR AND MATERIAL TO INSTALL EXHAUST DUCTING TO ROOFTOP 3M C/W ROOFING (INCLUDE INVERTER CAP,NUMBERING AND SAMPLING PORT) TO SUPPLY LABOUR MATERIAL TO INSTALL BURNER DUCTING AND JOINT TO MACHINE C/W 100MM FIBERGLASS EXTERNAL INSULATION TO SUPPLY LABOUR AND MATERIAL TO INSTALL SOLVENT EXHAUST DUCTING TO ROOFTOP 3M C/W ROOFING(INCLUDE INVERTER CAP,NUMBERING AND SAMPLING PORT) TO SUPPLY LABOUR AND MATERIAL TO INSTALL 2NOS EXHAUST BLOWER (NO INCLUDE WIRING WORK) TO SUPPLY LABOUR AND MATERIAL TO INSTALL FILTER BOX C/W PRESSURE GAUGE METER(INCLUDE CARBON FILTER) | E33: BAN KIM ENGINEERING WORKS | F33: TAMPOI | G33: MAINT | H33: GENERAL | I33: 2200954 | J33: PU48668 | K33: 23/01-020 | L33: Installation works | M33: 1 | N33: Unit | O33: 105000 | P33: 0 | Q33: 0 | R33: =SUM(O33:Q33) -> 105000 | S33: 120 | T33: -15750 | U33: -875 | V33: =-$R33/$S33 -> -875 | W33: =-$R33/$S33 -> -875 | X33: =-$R33/$S33 -> -875 | Y33: =-$R33/$S33 -> -875 | Z33: =-$R33/$S33 -> -875 | AA33: =-$R33/$S33 -> -875 | AB33: =-$R33/$S33 -> -875 | AC33: =-$R33/$S33 -> -875 | AD33: 0 | AE33: 0 | AF33: 0 | AG33: =SUM(U33:AF33) -> -7875 | AH33: 0 | AI33: =T33+AG33+AH33 -> -23625 | AK33: =R33+AI33 -> 81375 | AL33: =O33+T33 -> 89250
A34: 45078 | C34: IR-23-A0100111 | D34: ADDITIONAL CEILING WORK BLOCK A & C TO SUPPLY & INSTALL 9MM GYPSUM CEILING FOR AREA | E34: CBE M&E ENGINEERING SDN BHD | F34: TAMPOI | G34: MAINT | H34: GENERAL | I34: 2300869 | J34: PU50340 | K34: INV2640 | L34: Installation works | M34: 1 | N34: Unit | O34: 7000 | P34: 0 | Q34: 0 | R34: =SUM(O34:Q34) -> 7000 | S34: 120 | T34: -758.32 | U34: -58.33 | V34: =-$R34/$S34 -> -58.333333 | W34: =-$R34/$S34 -> -58.333333 | X34: =-$R34/$S34 -> -58.333333 | Y34: =-$R34/$S34 -> -58.333333 | Z34: =-$R34/$S34 -> -58.333333 | AA34: =-$R34/$S34 -> -58.333333 | AB34: =-$R34/$S34 -> -58.333333 | AC34: =-$R34/$S34 -> -58.333333 | AD34: 0 | AE34: 0 | AF34: 0 | AG34: =SUM(U34:AF34) -> -524.99667 | AH34: 0 | AI34: =T34+AG34+AH34 -> -1283.3167 | AK34: =R34+AI34 -> 5716.6833 | AL34: =O34+T34 -> 6241.68
A35: 45084 | C35: IR-23-A0100112 | D35: ADDITIONAL DOOR & WINDOW AT BASEMENT BLOCK C SUPPLY & INSTALL ALUMINIUM WINDOW C/W 4.5MM | E35: CBE M&E ENGINEERING SDN BHD | F35: TAMPOI | G35: MAINT | H35: GENERAL | I35: 2300922 | J35: PU50342 | K35: INV2645 | L35: Installation works | M35: 1 | N35: Unit | O35: 7200 | P35: 0 | Q35: 0 | R35: =SUM(O35:Q35) -> 7200 | S35: 120 | T35: -780 | U35: -60 | V35: =-$R35/$S35 -> -60 | W35: =-$R35/$S35 -> -60 | X35: =-$R35/$S35 -> -60 | Y35: =-$R35/$S35 -> -60 | Z35: =-$R35/$S35 -> -60 | AA35: =-$R35/$S35 -> -60 | AB35: =-$R35/$S35 -> -60 | AC35: =-$R35/$S35 -> -60 | AD35: 0 | AE35: 0 | AF35: 0 | AG35: =SUM(U35:AF35) -> -540 | AH35: 0 | AI35: =T35+AG35+AH35 -> -1320 | AK35: =R35+AI35 -> 5880 | AL35: =O35+T35 -> 6420
A36: 44958 | C36: IR-23-A0100099 | D36: TO SUPPLY & INSTALL S/S304 2B EXHAUST VENTILATION SYSTEM FOR SUPER COMBI & DUPLEX COMBI LINEAR TANDE | E36: GUAN SHENG ENGINEERING SDN BHD | F36: TAMPOI | G36: MAINT | H36: GENERAL | I36: 2201330 | J36: DT1124/ DT1175/ DT1191/ DT1254/ DT1264/ DT1267 | K36: INV002675/ INV002689/ INV002688/ INV002796/ INV002835/ INV002834 | M36: 1 | N36: Unit | O36: 580888 | P36: 0 | Q36: 0 | R36: =SUM(O36:Q36) -> 580888 | S36: 120 | T36: -82292.44 | U36: -4840.73 | V36: =-$R36/$S36 -> -4840.7333 | W36: =-$R36/$S36 -> -4840.7333 | X36: =-$R36/$S36 -> -4840.7333 | Y36: =-$R36/$S36 -> -4840.7333 | Z36: =-$R36/$S36 -> -4840.7333 | AA36: =-$R36/$S36 -> -4840.7333 | AB36: =-$R36/$S36 -> -4840.7333 | AC36: =-$R36/$S36 -> -4840.7333 | AD36: 0 | AE36: 0 | AF36: 0 | AG36: =SUM(U36:AF36) -> -43566.597 | AH36: 0 | AI36: =T36+AG36+AH36 -> -125859.04 | AK36: =R36+AI36 -> 455028.96 | AL36: =O36+T36 -> 498595.56
A37: 45131 | C37: IR-23-A0100115 | D37: BLOCK B (CYLINDER ROOM) SURFACE PREPARATION TO GRIND THE FLOOR TO PREPARE SUBSTRATE TO RECEIVE NEW FLOOR FINISHES FLOORING AT CYLINDER ROOM & CYLINDER STORE ROOMFLOOR FINISHES SUPPLY & APPLY BC CRETE MF UV (2MM) SELF SMOOTHING THERMAL SHOCK POLYURETHANE FLOOR FINISHES SUPPLY & APPLY BC DECK UV (2COATS) A UV STABLE 2 COMPONENTS COATING BASED ON HIGH QUALITY POLYESTER BRANCHED POLYURETHANE RESIN BLOCK B (CYLINDER ROOM) SURFACE PREPARATION TO GRIND THE FLOOR TO PREPARE SUBSTRATE TO RECEIVE NEW FLOOR FINISHES FLOOR FINISHES SUPPLY & APPLY BC CRETE MF UV (2MM) SELF SMOOTHING THERMAL SHOCK POLYURETHANE FLOOR FINISHES | E37: CBE M&E ENGINEERING SDN BHD | F37: TAMPOI | G37: MAINT | H37: GENERAL | I37: 2301152 | J37: PU50745 | K37: INV2664 | L37: Installation works | M37: 1 | N37: Unit | O37: 68260 | P37: 0 | Q37: 0 | R37: =SUM(O37:Q37) -> 68260 | S37: 120 | T37: -6825.99 | U37: -568.83 | V37: =-$R37/$S37 -> -568.83333 | W37: =-$R37/$S37 -> -568.83333 | X37: =-$R37/$S37 -> -568.83333 | Y37: =-$R37/$S37 -> -568.83333 | Z37: =-$R37/$S37 -> -568.83333 | AA37: =-$R37/$S37 -> -568.83333 | AB37: =-$R37/$S37 -> -568.83333 | AC37: =-$R37/$S37 -> -568.83333 | AD37: 0 | AE37: 0 | AF37: 0 | AG37: =SUM(U37:AF37) -> -5119.4967 | AH37: 0 | AI37: =T37+AG37+AH37 -> -11945.487 | AK37: =R37+AI37 -> 56314.513 | AL37: =O37+T37 -> 61434.01
A38: 44974 | C38: IR-23-A0100103 | D38: 3MM THK 304 S/STEEL PLATE C/W CUT,BEND & WELDING (PRINTING LINE 1 (6 COLOR)) | E38: F-I ENGINEERING SDN BHD | F38: TAMPOI | G38: MAINT | H38: GENERAL | I38: 2201815 | J38: DT1284/ DT1283 | K38: 6970/ 7011 | M38: 1 | N38: Unit | O38: 58520 | P38: 0 | Q38: 0 | R38: =SUM(O38:Q38) -> 58520 | S38: 120 | T38: -8290.36 | U38: -487.67 | V38: =-$R38/$S38 -> -487.66667 | W38: =-$R38/$S38 -> -487.66667 | X38: =-$R38/$S38 -> -487.66667 | Y38: =-$R38/$S38 -> -487.66667 | Z38: =-$R38/$S38 -> -487.66667 | AA38: =-$R38/$S38 -> -487.66667 | AB38: =-$R38/$S38 -> -487.66667 | AC38: =-$R38/$S38 -> -487.66667 | AD38: 0 | AE38: 0 | AF38: 0 | AG38: =SUM(U38:AF38) -> -4389.0033 | AH38: 0 | AI38: =T38+AG38+AH38 -> -12679.363 | AK38: =R38+AI38 -> 45840.637 | AL38: =O38+T38 -> 50229.64
A39: 45124 | C39: IR-23-A0100114 | D39: LAMINATION OFFICE LABOUR SUPPLY AND TOOLS TO DISMANTLE EXISTING CEILING,TABLE & PARTITION C/W SITE CLEANING TWO LAYER 12MM THK PLASTERING PARTITION | E39: F-I ENGINEERING SDN BHD | F39: TAMPOI | G39: MAINT | H39: General | I39: 2300307 | J39: PU50466 | K39: 7096 | L39: Installation works | M39: 1 | N39: Unit | O39: 17000 | P39: 0 | Q39: 0 | R39: =SUM(O39:Q39) -> 17000 | S39: 120 | T39: -1700 | U39: =-$R39/$S39 -> -141.66667 | V39: =-$R39/$S39 -> -141.66667 | W39: =-$R39/$S39 -> -141.66667 | X39: =-$R39/$S39 -> -141.66667 | Y39: =-$R39/$S39 -> -141.66667 | Z39: =-$R39/$S39 -> -141.66667 | AA39: =-$R39/$S39 -> -141.66667 | AB39: =-$R39/$S39 -> -141.66667 | AC39: =-$R39/$S39 -> -141.66667 | AD39: 0 | AE39: 0 | AF39: 0 | AG39: =SUM(U39:AF39) -> -1275 | AH39: 0 | AI39: =T39+AG39+AH39 -> -2975 | AK39: =R39+AI39 -> 14025 | AL39: =O39+T39 -> 15300
A40: 44974 | C40: IR-23-A0100104 | D40: 3MM 304 S/STEEL PLATE C/W CUT & WELDING (PRINTING LINE 2 (8 COLOR)) | E40: F-I ENGINEERING SDN BHD | F40: TAMPOI | G40: MAINT | H40: GENERAL | I40: 2201813 | J40: PU48827 | K40: 6971/ 700 | M40: 1 | N40: Unit | O40: 58520 | P40: 0 | Q40: 0 | R40: =SUM(O40:Q40) -> 58520 | S40: 120 | T40: -8290.36 | U40: -487.67 | V40: =-$R40/$S40 -> -487.66667 | W40: =-$R40/$S40 -> -487.66667 | X40: =-$R40/$S40 -> -487.66667 | Y40: =-$R40/$S40 -> -487.66667 | Z40: =-$R40/$S40 -> -487.66667 | AA40: =-$R40/$S40 -> -487.66667 | AB40: =-$R40/$S40 -> -487.66667 | AC40: =-$R40/$S40 -> -487.66667 | AD40: 0 | AE40: 0 | AF40: 0 | AG40: =SUM(U40:AF40) -> -4389.0033 | AH40: 0 | AI40: =T40+AG40+AH40 -> -12679.363 | AK40: =R40+AI40 -> 45840.637 | AL40: =O40+T40 -> 50229.64
A41: 45063 | C41: IR-23-A0100106 | D41: SUPPLY & RELOCATE RAPID DOOR AT BLOCK A | E41: CBE M&E ENGINEERING SDN BHD | F41: TAMPOI | G41: MAINT | H41: GENERAL | I41: 2300662 | J41: PU49778 | K41: INV2630 | M41: 1 | N41: Unit | O41: 12000 | P41: 0 | Q41: 0 | R41: =SUM(O41:Q41) -> 12000 | S41: 120 | T41: -1400 | U41: -100 | V41: =-$R41/$S41 -> -100 | W41: =-$R41/$S41 -> -100 | X41: =-$R41/$S41 -> -100 | Y41: =-$R41/$S41 -> -100 | Z41: =-$R41/$S41 -> -100 | AA41: =-$R41/$S41 -> -100 | AB41: =-$R41/$S41 -> -100 | AC41: =-$R41/$S41 -> -100 | AD41: 0 | AE41: 0 | AF41: 0 | AG41: =SUM(U41:AF41) -> -900 | AH41: 0 | AI41: =T41+AG41+AH41 -> -2300 | AK41: =R41+AI41 -> 9700 | AL41: =O41+T41 -> 10600
A42: 45070 | C42: IR-23-A0100109 | D42: TO SUPPLY AND INSTALL S/S 304 2B EXHAUST VENTILATION SYSTEM FOR SINGLE AND TANDEM EXTUDE LAMINATION MACHINE | E42: GUAN SHENG ENGINEERING SDN BHD | F42: TAMPOI | G42: MAINT | H42: GENERAL | I42: 2200949 | J42: DT1028/ DT1217/ DT1218/ DT1255/ DT1266/ DT1273/ DT1335 | K42: INV002612/ INV002773/ INV002774/ INV002833/ INV002852/ INV002806/ INV002891 | M42: 1 | N42: Unit | O42: 488600 | P42: 0 | Q42: 0 | R42: =SUM(O42:Q42) -> 488600 | S42: 120 | T42: -57003.35 | U42: -4071.67 | V42: =-$R42/$S42 -> -4071.6667 | W42: =-$R42/$S42 -> -4071.6667 | X42: =-$R42/$S42 -> -4071.6667 | Y42: =-$R42/$S42 -> -4071.6667 | Z42: =-$R42/$S42 -> -4071.6667 | AA42: =-$R42/$S42 -> -4071.6667 | AB42: =-$R42/$S42 -> -4071.6667 | AC42: =-$R42/$S42 -> -4071.6667 | AD42: 0 | AE42: 0 | AF42: 0 | AG42: =SUM(U42:AF42) -> -36645.003 | AH42: 0 | AI42: =T42+AG42+AH42 -> -93648.353 | AK42: =R42+AI42 -> 394951.65 | AL42: =O42+T42 -> 431596.65
A43: 45139 | C43: IR-23-A0100121 | D43: SUPPLY & INSTALL 2" X 2" X 4.5MM(THK) SHS FOR PARTITION STRUCTURE INCLUDING WELDING ON THE EXISTING STRUCTURE ADDITIONAL PARTITION AT 2ND FLOOR PACKING AREA BLOCK C SUPPLY & INSTALL 9MM GYMSUM BOARD FOR THE PACKING AREA C/W ALUMINIUM C-CHANNEL AT 4~5M HEIGHT SUPPLY & INSTALL PVC CURTAIN SUPPLY & INSTALL ALUMINIUM WINDOW C/W 4.5MM (THK) POLYCARBORATE PANEL DIMENSION: 1200MM X 1200MM(H) SUPPLY & INSTALL CEILING BOARD FOR PACKING ROOM SUPPLY & PAINTING FOR PARTITION & CEILING | E43: CBE M&E ENGINEERING SDN BHD | F43: TAMPOI | G43: MAINT | H43: GENERAL | I43: 2300882 | J43: PU50919 | K43: INV2677 | L43: Installation works | M43: 1 | N43: Unit | O43: 60000 | P43: 0 | Q43: 0 | R43: =SUM(O43:Q43) -> 60000 | S43: 120 | T43: -5500 | U43: =-$R43/$S43 -> -500 | V43: =-$R43/$S43 -> -500 | W43: =-$R43/$S43 -> -500 | X43: =-$R43/$S43 -> -500 | Y43: =-$R43/$S43 -> -500 | Z43: =-$R43/$S43 -> -500 | AA43: =-$R43/$S43 -> -500 | AB43: =-$R43/$S43 -> -500 | AC43: =-$R43/$S43 -> -500 | AD43: 0 | AE43: 0 | AF43: 0 | AG43: =SUM(U43:AF43) -> -4500 | AH43: 0 | AI43: =T43+AG43+AH43 -> -10000 | AK43: =R43+AI43 -> 50000 | AL43: =O43+T43 -> 54500
A44: 45139 | C44: IR-23-A0100120 | D44: FLOORING FOR BLOCK C EXTERNAL WALKWAY | E44: CBE M&E ENGINEERING SDN BHD | F44: TAMPOI | G44: MAINT | H44: General | I44: 2300937 | J44: PU50920 | K44: INV2676 | L44: Installation works | M44: 1 | N44: Unit | O44: 25000 | P44: 0 | Q44: 0 | R44: =SUM(O44:Q44) -> 25000 | S44: 120 | T44: -2291.6667 | U44: =-$R44/$S44 -> -208.33333 | V44: =-$R44/$S44 -> -208.33333 | W44: =-$R44/$S44 -> -208.33333 | X44: =-$R44/$S44 -> -208.33333 | Y44: =-$R44/$S44 -> -208.33333 | Z44: =-$R44/$S44 -> -208.33333 | AA44: =-$R44/$S44 -> -208.33333 | AB44: =-$R44/$S44 -> -208.33333 | AC44: =-$R44/$S44 -> -208.33333 | AD44: 0 | AE44: 0 | AF44: 0 | AG44: =SUM(U44:AF44) -> -1875 | AH44: 0 | AI44: =T44+AG44+AH44 -> -4166.6667 | AK44: =R44+AI44 -> 20833.333 | AL44: =O44+T44 -> 22708.333
A45: 45139 | C45: IR-23-A0100123 | D45: BLOCK C (2ND FLOOR TOILET) | E45: CBE M&E ENGINEERING SDN BHD | F45: TAMPOI | G45: MAINT | H45: General | I45: 2301231 | J45: PU50921 | K45: INV2680 | L45: Installation works | M45: 1 | N45: Unit | O45: 14000 | P45: 0 | Q45: 0 | R45: =SUM(O45:Q45) -> 14000 | S45: 120 | T45: -1283.3333 | U45: =-$R45/$S45 -> -116.66667 | V45: =-$R45/$S45 -> -116.66667 | W45: =-$R45/$S45 -> -116.66667 | X45: =-$R45/$S45 -> -116.66667 | Y45: =-$R45/$S45 -> -116.66667 | Z45: =-$R45/$S45 -> -116.66667 | AA45: =-$R45/$S45 -> -116.66667 | AB45: =-$R45/$S45 -> -116.66667 | AC45: =-$R45/$S45 -> -116.66667 | AD45: 0 | AE45: 0 | AF45: 0 | AG45: =SUM(U45:AF45) -> -1050 | AH45: 0 | AI45: =T45+AG45+AH45 -> -2333.3333 | AK45: =R45+AI45 -> 11666.667 | AL45: =O45+T45 -> 12716.667
A46: 45076 | C46: IR-23-A0100110 | D46: FOR NEW WAREHOUS GAN SENG SUPPLY MACHINERY C/W MOB & DEMOB FOR INSTALLAING THE NETTING 1.SCISSOR LIFT FOR NETTING INSTALLATION SUPPLY MACHINERY C/W MOB & DEMOB FOR INSTALLAING THE NETTING 2. CRANE 25TON FOR HOISTING SCISSOR LIFT TO WORKING PLATFORM SUPPLY & INSTALL NETTING MOUNTING ON THE EXSITING ALUM. LOUVERS AT JACK ROOF IN HIGH LEVEL | E46: CBE M&E ENGINEERING SDN BHD | F46: N/A | G46: N/A | H46: N/A | I46: 2300687 | J46: PU50023 | K46: INV2639 | M46: 1 | N46: Unit | O46: 35000 | P46: 0 | Q46: 0 | R46: =SUM(O46:Q46) -> 35000 | S46: 120 | T46: -3791.68 | U46: -291.67 | V46: =-$R46/$S46 -> -291.66667 | W46: =-$R46/$S46 -> -291.66667 | X46: =-$R46/$S46 -> -291.66667 | Y46: =-$R46/$S46 -> -291.66667 | Z46: =-$R46/$S46 -> -291.66667 | AA46: =-$R46/$S46 -> -291.66667 | AB46: =-$R46/$S46 -> -291.66667 | AC46: =-$R46/$S46 -> -291.66667 | AD46: 0 | AE46: 0 | AF46: 0 | AG46: =SUM(U46:AF46) -> -2625.0033 | AH46: 0 | AI46: =T46+AG46+AH46 -> -6416.6833 | AK46: =R46+AI46 -> 28583.317 | AL46: =O46+T46 -> 31208.32
A47: 45103 | C47: IR-23-A0100113 | D47: 3MM 304 S/STEEL PLATE C/W CUT & WELDING (PRINTING LINE 3 & 4) 3MM 304 S/STEEL PLATE C/W WELDING (PRINTING CYLINDER MACHINE) | E47: F-I ENGINEERING SDN BHD | F47: TAMPOI | G47: MAINT | H47: GENERAL | I47: 2300435 | J47: DT 1258/ PU50337 | K47: 7030/ 7080 | M47: 1 | N47: Unit | O47: 109060 | P47: 0 | Q47: 0 | R47: =SUM(O47:Q47) -> 109060 | S47: 120 | T47: -11814.82 | U47: -908.83 | V47: =-$R47/$S47 -> -908.83333 | W47: =-$R47/$S47 -> -908.83333 | X47: =-$R47/$S47 -> -908.83333 | Y47: =-$R47/$S47 -> -908.83333 | Z47: =-$R47/$S47 -> -908.83333 | AA47: =-$R47/$S47 -> -908.83333 | AB47: =-$R47/$S47 -> -908.83333 | AC47: =-$R47/$S47 -> -908.83333 | AD47: 0 | AE47: 0 | AF47: 0 | AG47: =SUM(U47:AF47) -> -8179.4967 | AH47: 0 | AI47: =T47+AG47+AH47 -> -19994.317 | AK47: =R47+AI47 -> 89065.683 | AL47: =O47+T47 -> 97245.18
A48: 45170 | C48: IR-23-A0100125 | D48: WALL CLADDING BLOCK B AND FACTORY UPKEEP | E48: CBE M&E ENGINEERING SDN BHD | F48: TAMPOI | G48: MAINT | H48: General | I48: 2301288 | J48: PU51357 | K48: INV2699 | L48: Installation works | M48: 1 | N48: Unit | O48: 50000 | P48: 0 | Q48: 0 | R48: =SUM(O48:Q48) -> 50000 | S48: 120 | T48: -4166.6667 | U48: =-$R48/$S48 -> -416.66667 | V48: =-$R48/$S48 -> -416.66667 | W48: =-$R48/$S48 -> -416.66667 | X48: =-$R48/$S48 -> -416.66667 | Y48: =-$R48/$S48 -> -416.66667 | Z48: =-$R48/$S48 -> -416.66667 | AA48: =-$R48/$S48 -> -416.66667 | AB48: =-$R48/$S48 -> -416.66667 | AC48: =-$R48/$S48 -> -416.66667 | AD48: 0 | AE48: 0 | AF48: 0 | AG48: =SUM(U48:AF48) -> -3750 | AH48: 0 | AI48: =T48+AG48+AH48 -> -7916.6667 | AK48: =R48+AI48 -> 42083.333 | AL48: =O48+T48 -> 45833.333
A49: 45191 | C49: IR-23-A0100127 | D49: SUPPLY & INSTALL WATERPROOFING WORKS AT BLOCK C WATER TANK AREA | E49: CBE M&E ENGINEERING SDN BHD | F49: TAMPOI | G49: MAINT | H49: General | I49: 2301420 | J49: PU51315 | K49: INV2716 | L49: Installation works | M49: 1 | N49: Unit | O49: 12500 | P49: 0 | Q49: 0 | R49: =SUM(O49:Q49) -> 12500 | S49: 120 | T49: -1041.6667 | U49: =-$R49/$S49 -> -104.16667 | V49: =-$R49/$S49 -> -104.16667 | W49: =-$R49/$S49 -> -104.16667 | X49: =-$R49/$S49 -> -104.16667 | Y49: =-$R49/$S49 -> -104.16667 | Z49: =-$R49/$S49 -> -104.16667 | AA49: =-$R49/$S49 -> -104.16667 | AB49: =-$R49/$S49 -> -104.16667 | AC49: =-$R49/$S49 -> -104.16667 | AD49: 0 | AE49: 0 | AF49: 0 | AG49: =SUM(U49:AF49) -> -937.5 | AH49: 0 | AI49: =T49+AG49+AH49 -> -1979.1667 | AK49: =R49+AI49 -> 10520.833 | AL49: =O49+T49 -> 11458.333
A50: 45191 | C50: IR-23-A0100128 | D50: SUPPLY & INSTALL MS BARRIER & VINVL STICKER AT BLOCK C | E50: CBE M&E ENGINEERING SDN BHD | F50: TAMPOI | G50: MAINT | H50: General | I50: 2301419 | J50: PU51316 | K50: INV2717 | L50: Installation works | M50: 1 | N50: Unit | O50: 13500 | P50: 0 | Q50: 0 | R50: =SUM(O50:Q50) -> 13500 | S50: 120 | T50: -1125 | U50: =-$R50/$S50 -> -112.5 | V50: =-$R50/$S50 -> -112.5 | W50: =-$R50/$S50 -> -112.5 | X50: =-$R50/$S50 -> -112.5 | Y50: =-$R50/$S50 -> -112.5 | Z50: =-$R50/$S50 -> -112.5 | AA50: =-$R50/$S50 -> -112.5 | AB50: =-$R50/$S50 -> -112.5 | AC50: =-$R50/$S50 -> -112.5 | AD50: 0 | AE50: 0 | AF50: 0 | AG50: =SUM(U50:AF50) -> -1012.5 | AH50: 0 | AI50: =T50+AG50+AH50 -> -2137.5 | AK50: =R50+AI50 -> 11362.5 | AL50: =O50+T50 -> 12375
A51: 45191 | C51: IR-23-A0100126 | D51: SUPPLY & INSTALL STEEL STRUCTURE FOR COVER WALKWAY AT LEFT SIDE BLOCK C USING HOLLOW SECTION PIPE DIMENSION: 229(L) X 5(W) X 9(H) | E51: CBE M&E ENGINEERING SDN BHD | F51: TAMPOI | G51: MAINT | H51: General | I51: 2300936 | J51: PU51450 | K51: INV2715 | L51: Installation works | M51: 1 | N51: Unit | O51: 72000 | P51: 0 | Q51: 0 | R51: =SUM(O51:Q51) -> 72000 | S51: 120 | T51: -6000 | U51: =-$R51/$S51 -> -600 | V51: =-$R51/$S51 -> -600 | W51: =-$R51/$S51 -> -600 | X51: =-$R51/$S51 -> -600 | Y51: =-$R51/$S51 -> -600 | Z51: =-$R51/$S51 -> -600 | AA51: =-$R51/$S51 -> -600 | AB51: =-$R51/$S51 -> -600 | AC51: =-$R51/$S51 -> -600 | AD51: 0 | AE51: 0 | AF51: 0 | AG51: =SUM(U51:AF51) -> -5400 | AH51: 0 | AI51: =T51+AG51+AH51 -> -11400 | AK51: =R51+AI51 -> 60600 | AL51: =O51+T51 -> 66000
A52: 45215 | C52: IR-23-A0100129 | D52: Supply & Install noise insulation using Rockwol 40kg/m2 in partition for lot ( WAREHOUSE OFFICE ) | E52: CBE M&E ENGINEERING SDN BHD | F52: TAMPOI | G52: STORE | I52: 2301446 | J52: PU51570 | K52: INV2729 | L52: Installation works | M52: 1 | N52: Unit | O52: 22000 | P52: 0 | Q52: 0 | R52: =SUM(O52:Q52) -> 22000 | S52: 120 | T52: -1650 | U52: =-$R52/$S52 -> -183.33333 | V52: =-$R52/$S52 -> -183.33333 | W52: =-$R52/$S52 -> -183.33333 | X52: =-$R52/$S52 -> -183.33333 | Y52: =-$R52/$S52 -> -183.33333 | Z52: =-$R52/$S52 -> -183.33333 | AA52: =-$R52/$S52 -> -183.33333 | AB52: =-$R52/$S52 -> -183.33333 | AC52: =-$R52/$S52 -> -183.33333 | AD52: 0 | AE52: 0 | AF52: 0 | AG52: =SUM(U52:AF52) -> -1650 | AH52: 0 | AI52: =T52+AG52+AH52 -> -3300 | AK52: =R52+AI52 -> 18700 | AL52: =O52+T52 -> 20350
A53: 45236 | C53: IR-23-A0100130 | D53: ADDITIONAL WORK OF ROOFING & FASCIA FOR BLOCK A OFFICE SUPPLY & REPLACE ROOFING USING 0.47TCT CLIP LOCK METHOD SUPPLY & REPLACE FASCIA USING 0.35MM TCT SUPPLY & INSTALL USING 0.4MM(THK) X 1200MM(W) STAINLESS STEEL GUTTER SUPPLY & INSTALL Ø6" UPVC PIPE FOR RAIN WATER DOWN PIPE SUPPLY & INSTALL ALUMINIUM STRIP CEILING | E53: CBE M&E ENGINEERING SDN BHD | F53: ` | G53: MAINT | H53: GENERAL | I53: 2300086 | J53: PU51798 | K53: INV2748 | L53: Installation works | M53: 1 | N53: Unit | O53: 123000 | P53: 0 | Q53: 0 | R53: =SUM(O53:Q53) -> 123000 | S53: 120 | T53: -8200 | U53: =-$R53/$S53 -> -1025 | V53: =-$R53/$S53 -> -1025 | W53: =-$R53/$S53 -> -1025 | X53: =-$R53/$S53 -> -1025 | Y53: =-$R53/$S53 -> -1025 | Z53: =-$R53/$S53 -> -1025 | AA53: =-$R53/$S53 -> -1025 | AB53: =-$R53/$S53 -> -1025 | AC53: =-$R53/$S53 -> -1025 | AD53: 0 | AE53: 0 | AF53: 0 | AG53: =SUM(U53:AF53) -> -9225 | AH53: 0 | AI53: =T53+AG53+AH53 -> -17425 | AK53: =R53+AI53 -> 105575 | AL53: =O53+T53 -> 114800
A54: 45236 | C54: IR-23-A0100131 | D54: SICK BAY & NOISE INSULATION PARTITION FOR BLOCK B & C | E54: CBE M&E ENGINEERING SDN BHD | F54: TAMPOI | G54: MAINT | H54: General | I54: 2301612 | J54: PU51797 | K54: INV2749 | L54: Installation works | M54: 1 | N54: Unit | O54: 13000 | P54: 0 | Q54: 0 | R54: =SUM(O54:Q54) -> 13000 | S54: 120 | T54: -866.66667 | U54: =-$R54/$S54 -> -108.33333 | V54: =-$R54/$S54 -> -108.33333 | W54: =-$R54/$S54 -> -108.33333 | X54: =-$R54/$S54 -> -108.33333 | Y54: =-$R54/$S54 -> -108.33333 | Z54: =-$R54/$S54 -> -108.33333 | AA54: =-$R54/$S54 -> -108.33333 | AB54: =-$R54/$S54 -> -108.33333 | AC54: =-$R54/$S54 -> -108.33333 | AD54: 0 | AE54: 0 | AF54: 0 | AG54: =SUM(U54:AF54) -> -975 | AH54: 0 | AI54: =T54+AG54+AH54 -> -1841.6667 | AK54: =R54+AI54 -> 11158.333 | AL54: =O54+T54 -> 12133.333
A55: 45252 | C55: IR-23-A0100132 | D55: REPLACEMENT OF PIR/FRAME WINDOW DOOR ETC | E55: CBE M&E ENGINEERING SDN BHD | F55: TAMPOI | G55: MAINT | H55: General | I55: 2301580 | J55: PU52061 | K55: INV2761 | L55: Installation works | M55: 1 | N55: Unit | O55: 59000 | P55: 0 | Q55: 0 | R55: =SUM(O55:Q55) -> 59000 | S55: 120 | T55: -3933.3333 | U55: =-$R55/$S55 -> -491.66667 | V55: =-$R55/$S55 -> -491.66667 | W55: =-$R55/$S55 -> -491.66667 | X55: =-$R55/$S55 -> -491.66667 | Y55: =-$R55/$S55 -> -491.66667 | Z55: =-$R55/$S55 -> -491.66667 | AA55: =-$R55/$S55 -> -491.66667 | AB55: =-$R55/$S55 -> -491.66667 | AC55: =-$R55/$S55 -> -491.66667 | AD55: 0 | AE55: 0 | AF55: 0 | AG55: =SUM(U55:AF55) -> -4425 | AH55: 0 | AI55: =T55+AG55+AH55 -> -8358.3333 | AK55: =R55+AI55 -> 50641.667 | AL55: =O55+T55 -> 55066.667
A56: 45131 | C56: IR-23-A0100118 | D56: SUPPLY & INSTALL ADDITIONAL ROLLER SHUTTER AT BLOCK B CYLINDER ROOM C/W MOTORISED OPERATED & 24V RELAY | E56: CBE M&E ENGINEERING SDN BHD | F56: TAMPOI | G56: MAINT | H56: General | I56: 2301156 | J56: PU50741 | K56: INV2668 | M56: 1 | N56: Unit | O56: 9500 | P56: 0 | Q56: 0 | R56: =SUM(O56:Q56) -> 9500 | S56: 120 | T56: -950 | U56: =-$R56/$S56 -> -79.166667 | V56: =-$R56/$S56 -> -79.166667 | W56: =-$R56/$S56 -> -79.166667 | X56: =-$R56/$S56 -> -79.166667 | Y56: =-$R56/$S56 -> -79.166667 | Z56: =-$R56/$S56 -> -79.166667 | AA56: =-$R56/$S56 -> -79.166667 | AB56: =-$R56/$S56 -> -79.166667 | AC56: =-$R56/$S56 -> -79.166667 | AD56: 0 | AE56: 0 | AF56: 0 | AG56: =SUM(U56:AF56) -> -712.5 | AH56: 0 | AI56: =T56+AG56+AH56 -> -1662.5 | AK56: =R56+AI56 -> 7837.5 | AL56: =O56+T56 -> 8550
A57: 45131 | C57: IR-23-A0100116 | D57: SUPPLY & INSTALL ADDITIONAL PARTITION | E57: CBE M&E ENGINEERING SDN BHD | F57: TAMPOI | G57: MAINT | H57: General | I57: 2301153 | J57: PU50744 | K57: INV2665 | M57: 1 | N57: Unit | O57: 14300 | P57: 0 | Q57: 0 | R57: =SUM(O57:Q57) -> 14300 | S57: 120 | T57: -1430 | U57: =-$R57/$S57 -> -119.16667 | V57: =-$R57/$S57 -> -119.16667 | W57: =-$R57/$S57 -> -119.16667 | X57: =-$R57/$S57 -> -119.16667 | Y57: =-$R57/$S57 -> -119.16667 | Z57: =-$R57/$S57 -> -119.16667 | AA57: =-$R57/$S57 -> -119.16667 | AB57: =-$R57/$S57 -> -119.16667 | AC57: =-$R57/$S57 -> -119.16667 | AD57: 0 | AE57: 0 | AF57: 0 | AG57: =SUM(U57:AF57) -> -1072.5 | AH57: 0 | AI57: =T57+AG57+AH57 -> -2502.5 | AK57: =R57+AI57 -> 11797.5 | AL57: =O57+T57 -> 12870
A58: 45286 | C58: IR-23-A0100135 | D58: ADDITIONAL UV (SATIN COAT) FOR FLOORING AT BLOCK C | E58: CBE M&E ENGINEERING SDN BHD | F58: TAMPOI | G58: MAINT | H58: GENERAL | I58: 2301221 | J58: PU52429 | K58: INV2783 | L58: Installation works | M58: 1 | N58: Unit | O58: 253000 | P58: 0 | Q58: 0 | R58: =SUM(O58:Q58) -> 253000 | S58: 120 | T58: -14758.333 | U58: =-$R58/$S58 -> -2108.3333 | V58: =-$R58/$S58 -> -2108.3333 | W58: =-$R58/$S58 -> -2108.3333 | X58: =-$R58/$S58 -> -2108.3333 | Y58: =-$R58/$S58 -> -2108.3333 | Z58: =-$R58/$S58 -> -2108.3333 | AA58: =-$R58/$S58 -> -2108.3333 | AB58: =-$R58/$S58 -> -2108.3333 | AC58: =-$R58/$S58 -> -2108.3333 | AD58: 0 | AE58: 0 | AF58: 0 | AG58: =SUM(U58:AF58) -> -18975 | AH58: 0 | AI58: =T58+AG58+AH58 -> -33733.333 | AK58: =R58+AI58 -> 219266.67 | AL58: =O58+T58 -> 238241.67
A59: 45286 | C59: IR-23-A0100136 | D59: WALL CLADDING | E59: CBE M&E ENGINEERING SDN BHD | F59: TAMPOI | G59: MAINT | H59: General | I59: 2301631 | J59: PU52430 | K59: INV2784 | L59: Installation works | M59: 1 | N59: Unit | O59: 24000 | P59: 0 | Q59: 0 | R59: =SUM(O59:Q59) -> 24000 | S59: 120 | T59: -1400 | U59: =-$R59/$S59 -> -200 | V59: =-$R59/$S59 -> -200 | W59: =-$R59/$S59 -> -200 | X59: =-$R59/$S59 -> -200 | Y59: =-$R59/$S59 -> -200 | Z59: =-$R59/$S59 -> -200 | AA59: =-$R59/$S59 -> -200 | AB59: =-$R59/$S59 -> -200 | AC59: =-$R59/$S59 -> -200 | AD59: 0 | AE59: 0 | AF59: 0 | AG59: =SUM(U59:AF59) -> -1800 | AH59: 0 | AI59: =T59+AG59+AH59 -> -3200 | AK59: =R59+AI59 -> 20800 | AL59: =O59+T59 -> 22600
A60: 45131 | C60: IR-23-A0100117 | D60: SUPPLY & INSTALL ADDITIONAL PARTITION | E60: CBE M&E ENGINEERING SDN BHD | F60: TAMPOI | G60: MAINT | H60: General | I60: 2301154 | J60: PU50751 | K60: INV2666 | M60: 1 | N60: Unit | O60: 17000 | P60: 0 | Q60: 0 | R60: =SUM(O60:Q60) -> 17000 | S60: 120 | T60: -1700 | U60: =-$R60/$S60 -> -141.66667 | V60: =-$R60/$S60 -> -141.66667 | W60: =-$R60/$S60 -> -141.66667 | X60: =-$R60/$S60 -> -141.66667 | Y60: =-$R60/$S60 -> -141.66667 | Z60: =-$R60/$S60 -> -141.66667 | AA60: =-$R60/$S60 -> -141.66667 | AB60: =-$R60/$S60 -> -141.66667 | AC60: =-$R60/$S60 -> -141.66667 | AD60: 0 | AE60: 0 | AF60: 0 | AG60: =SUM(U60:AF60) -> -1275 | AH60: 0 | AI60: =T60+AG60+AH60 -> -2975 | AK60: =R60+AI60 -> 14025 | AL60: =O60+T60 -> 15300
A61: 45134 | C61: IR-23-A0100119 | D61: 3MM THK 304 S/STEEL PLATE C/W CUT,BEND & WELDING (NM SOLVENTLESS MACHINE) | E61: F-I ENGINEERING SDN BHD | F61: TAMPOI | G61: MAINT | H61: GENERAL | I61: 2201814 | J61: PU50740 | K61: 7902 | M61: 1 | N61: Unit | O61: 53200 | P61: 0 | Q61: 0 | R61: =SUM(O61:Q61) -> 53200 | S61: 120 | T61: -5319.99 | U61: -443.33 | V61: =-$R61/$S61 -> -443.33333 | W61: =-$R61/$S61 -> -443.33333 | X61: =-$R61/$S61 -> -443.33333 | Y61: =-$R61/$S61 -> -443.33333 | Z61: =-$R61/$S61 -> -443.33333 | AA61: =-$R61/$S61 -> -443.33333 | AB61: =-$R61/$S61 -> -443.33333 | AC61: =-$R61/$S61 -> -443.33333 | AD61: 0 | AE61: 0 | AF61: 0 | AG61: =SUM(U61:AF61) -> -3989.9967 | AH61: 0 | AI61: =T61+AG61+AH61 -> -9309.9867 | AK61: =R61+AI61 -> 43890.013 | AL61: =O61+T61 -> 47880.01
A62: 45139 | C62: IR-23-A0100122 | D62: HEAVY DUTY TYPE ( 300mm(W) X 3mm(thk) PVC STRIP CURTAIN C/W BRACKET SUPPORT | E62: CBE M&E ENGINEERING SDN BHD | G62: STORE | I62: 2300994 | J62: PU50997 | K62: INV2678 | M62: 1 | N62: Unit | O62: 8100 | P62: 0 | Q62: 0 | R62: =SUM(O62:Q62) -> 8100 | S62: 120 | T62: -742.5 | U62: =-$R62/$S62 -> -67.5 | V62: =-$R62/$S62 -> -67.5 | W62: =-$R62/$S62 -> -67.5 | X62: =-$R62/$S62 -> -67.5 | Y62: =-$R62/$S62 -> -67.5 | Z62: =-$R62/$S62 -> -67.5 | AA62: =-$R62/$S62 -> -67.5 | AB62: =-$R62/$S62 -> -67.5 | AC62: =-$R62/$S62 -> -67.5 | AD62: 0 | AE62: 0 | AF62: 0 | AG62: =SUM(U62:AF62) -> -607.5 | AH62: 0 | AI62: =T62+AG62+AH62 -> -1350 | AK62: =R62+AI62 -> 6750 | AL62: =O62+T62 -> 7357.5
A63: 45147 | C63: IR-23-A0100124 | D63: ADDITIONAL WORK AT BLOCK A, & B TOILET & PRODUCTION AREA | E63: CBE M&E ENGINEERING SDN BHD | F63: TAMPOI | G63: MAINT | H63: General | I63: 2301230 | J63: PU50995 | K63: INV2685 | M63: 1 | N63: Unit | O63: 11000 | P63: 0 | Q63: 0 | R63: =SUM(O63:Q63) -> 11000 | S63: 120 | T63: -1008.3333 | U63: =-$R63/$S63 -> -91.666667 | V63: =-$R63/$S63 -> -91.666667 | W63: =-$R63/$S63 -> -91.666667 | X63: =-$R63/$S63 -> -91.666667 | Y63: =-$R63/$S63 -> -91.666667 | Z63: =-$R63/$S63 -> -91.666667 | AA63: =-$R63/$S63 -> -91.666667 | AB63: =-$R63/$S63 -> -91.666667 | AC63: =-$R63/$S63 -> -91.666667 | AD63: 0 | AE63: 0 | AF63: 0 | AG63: =SUM(U63:AF63) -> -825 | AH63: 0 | AI63: =T63+AG63+AH63 -> -1833.3333 | AK63: =R63+AI63 -> 9166.6667 | AL63: =O63+T63 -> 9991.6667
A64: 45358 | C64: IR-24-A0100140 | D64: RENOVATION OF GUARD HOUSE | E64: CBE M&E ENGINEERING SDN BHD | F64: TAMPOI | G64: MAINT | H64: GENERAL | I64: 2301921 | J64: PU53299 | K64: INV2837 | L64: Installation works | M64: 1 | N64: Unit | O64: 52800 | P64: 0 | Q64: 0 | R64: =SUM(O64:Q64) -> 52800 | S64: 120 | T64: -1760 | U64: =-$R64/$S64 -> -440 | V64: =-$R64/$S64 -> -440 | W64: =-$R64/$S64 -> -440 | X64: =-$R64/$S64 -> -440 | Y64: =-$R64/$S64 -> -440 | Z64: =-$R64/$S64 -> -440 | AA64: =-$R64/$S64 -> -440 | AB64: =-$R64/$S64 -> -440 | AC64: =-$R64/$S64 -> -440 | AD64: 0 | AE64: 0 | AF64: 0 | AG64: =SUM(U64:AF64) -> -3960 | AH64: 0 | AI64: =T64+AG64+AH64 -> -5720 | AK64: =R64+AI64 -> 47080 | AL64: =O64+T64 -> 51040
A65: 45261 | C65: IR-23-A0100133 | D65: AIR COOLED PACKAGE AIR CONDITIONING SYSTEM AT BASEMENT SLITTING DEPT | E65: ACMV SYNERGY SDN. BHD. | F65: TAMPOI | G65: MAINT | H65: GENERAL | I65: 2301447 | J65: PU52369 | K65: 11/040/23 | M65: 1 | N65: Unit | O65: 222000 | P65: 0 | Q65: 0 | R65: =SUM(O65:Q65) -> 222000 | S65: 120 | T65: -12950 | U65: =-$R65/$S65 -> -1850 | V65: =-$R65/$S65 -> -1850 | W65: =-$R65/$S65 -> -1850 | X65: =-$R65/$S65 -> -1850 | Y65: =-$R65/$S65 -> -1850 | Z65: =-$R65/$S65 -> -1850 | AA65: =-$R65/$S65 -> -1850 | AB65: =-$R65/$S65 -> -1850 | AC65: =-$R65/$S65 -> -1850 | AD65: 0 | AE65: 0 | AF65: 0 | AG65: =SUM(U65:AF65) -> -16650 | AH65: 0 | AI65: =T65+AG65+AH65 -> -29600 | AK65: =R65+AI65 -> 192400 | AL65: =O65+T65 -> 209050
A66: 45372 | C66: IR-24-A0100143 | D66: SUPPLY & INSTALL PU FLOORING AT BLOCK C METALISE DEPARTMENT OFFICE | E66: CBE M&E ENGINEERING SDN BHD | F66: TAMPOI | G66: MAINT | H66: GENERAL | I66: 2400398 | J66: PU53406 | K66: INV2850 | L66: Installation works | M66: 1 | N66: Unit | O66: 4500 | P66: 0 | Q66: 0 | R66: =SUM(O66:Q66) -> 4500 | S66: 120 | T66: -150 | U66: =-$R66/$S66 -> -37.5 | V66: =-$R66/$S66 -> -37.5 | W66: =-$R66/$S66 -> -37.5 | X66: =-$R66/$S66 -> -37.5 | Y66: =-$R66/$S66 -> -37.5 | Z66: =-$R66/$S66 -> -37.5 | AA66: =-$R66/$S66 -> -37.5 | AB66: =-$R66/$S66 -> -37.5 | AC66: =-$R66/$S66 -> -37.5 | AD66: 0 | AE66: 0 | AF66: 0 | AG66: =SUM(U66:AF66) -> -337.5 | AH66: 0 | AI66: =T66+AG66+AH66 -> -487.5 | AK66: =R66+AI66 -> 4012.5 | AL66: =O66+T66 -> 4350
A67: 45268 | C67: IR-23-A0100134 | D67: NON RADIATIVE LIGHTING PROTECTION SYSTEM FOR BLOCK A,B & C | E67: CBE M&E ENGINEERING SDN BHD | F67: TAMPOI | G67: MAINT | H67: GENERAL | I67: 2301691 | J67: PU52246 | K67: INV2770 | M67: 1 | N67: Unit | O67: 75500 | P67: 0 | Q67: 0 | R67: =SUM(O67:Q67) -> 75500 | S67: 120 | T67: -4404.1667 | U67: =-$R67/$S67 -> -629.16667 | V67: =-$R67/$S67 -> -629.16667 | W67: =-$R67/$S67 -> -629.16667 | X67: =-$R67/$S67 -> -629.16667 | Y67: =-$R67/$S67 -> -629.16667 | Z67: =-$R67/$S67 -> -629.16667 | AA67: =-$R67/$S67 -> -629.16667 | AB67: =-$R67/$S67 -> -629.16667 | AC67: =-$R67/$S67 -> -629.16667 | AD67: 0 | AE67: 0 | AF67: 0 | AG67: =SUM(U67:AF67) -> -5662.5 | AH67: 0 | AI67: =T67+AG67+AH67 -> -10066.667 | AK67: =R67+AI67 -> 65433.333 | AL67: =O67+T67 -> 71095.833
A68: 45309 | C68: IR-24-A0100137 | D68: SUPPLY & INSTALL 9MM GYMSUM BOARD PARTITION | E68: CBE M&E ENGINEERING SDN BHD | F68: TAMPOI | G68: MAINT | H68: General | I68: 2302020 | J68: PU52709 | K68: INV2802 | M68: 1 | N68: Unit | O68: 12800 | P68: 0 | Q68: 0 | R68: =SUM(O68:Q68) -> 12800 | S68: 120 | T68: -640 | U68: =-$R68/$S68 -> -106.66667 | V68: =-$R68/$S68 -> -106.66667 | W68: =-$R68/$S68 -> -106.66667 | X68: =-$R68/$S68 -> -106.66667 | Y68: =-$R68/$S68 -> -106.66667 | Z68: =-$R68/$S68 -> -106.66667 | AA68: =-$R68/$S68 -> -106.66667 | AB68: =-$R68/$S68 -> -106.66667 | AC68: =-$R68/$S68 -> -106.66667 | AD68: 0 | AE68: 0 | AF68: 0 | AG68: =SUM(U68:AF68) -> -960 | AH68: 0 | AI68: =T68+AG68+AH68 -> -1600 | AK68: =R68+AI68 -> 11200 | AL68: =O68+T68 -> 12160
A69: 45316 | C69: IR-24-A0100138 | D69: SUPPLY & INSTALL MS BARRIER AT BASEMENT C PRODUCTION AREA | E69: CBE M&E ENGINEERING SDN BHD | F69: TAMPOI | G69: MAINT | H69: General | I69: 2302015 | J69: PU52708 | K69: INV2810 | M69: 1 | N69: Unit | O69: 26040 | P69: 0 | Q69: 0 | R69: =SUM(O69:Q69) -> 26040 | S69: 120 | T69: -1302 | U69: =-$R69/$S69 -> -217 | V69: =-$R69/$S69 -> -217 | W69: =-$R69/$S69 -> -217 | X69: =-$R69/$S69 -> -217 | Y69: =-$R69/$S69 -> -217 | Z69: =-$R69/$S69 -> -217 | AA69: =-$R69/$S69 -> -217 | AB69: =-$R69/$S69 -> -217 | AC69: =-$R69/$S69 -> -217 | AD69: 0 | AE69: 0 | AF69: 0 | AG69: =SUM(U69:AF69) -> -1953 | AH69: 0 | AI69: =T69+AG69+AH69 -> -3255 | AK69: =R69+AI69 -> 22785 | AL69: =O69+T69 -> 24738
A70: 45358 | C70: IR-24-A0100141 | D70: REPLACE ROOFING & S/S GUTTER AT CONSUMER SWITCH ROOM & MAINTENANCE | E70: CBE M&E ENGINEERING SDN BHD | F70: TAMPOI | G70: MAINT | H70: GENERAL | I70: 2400039 | J70: PU53282 | K70: INV2838 | M70: 1 | N70: Unit | O70: 33392.1 | P70: 0 | Q70: 0 | R70: =SUM(O70:Q70) -> 33392.1 | S70: 120 | T70: -1113.07 | U70: =-$R70/$S70 -> -278.2675 | V70: =-$R70/$S70 -> -278.2675 | W70: =-$R70/$S70 -> -278.2675 | X70: =-$R70/$S70 -> -278.2675 | Y70: =-$R70/$S70 -> -278.2675 | Z70: =-$R70/$S70 -> -278.2675 | AA70: =-$R70/$S70 -> -278.2675 | AB70: =-$R70/$S70 -> -278.2675 | AC70: =-$R70/$S70 -> -278.2675 | AD70: 0 | AE70: 0 | AF70: 0 | AG70: =SUM(U70:AF70) -> -2504.4075 | AH70: 0 | AI70: =T70+AG70+AH70 -> -3617.4775 | AK70: =R70+AI70 -> 29774.622 | AL70: =O70+T70 -> 32279.03
A71: 45358 | C71: IR-24-A0100139 | D71: ADDITIONAL PVC CURTAIN FOR NEW CHILLER ROOM AT BLOCK C | E71: CBE M&E ENGINEERING SDN BHD | F71: TAMPOI | G71: MAINT | H71: GENERAL | I71: 2301810 | J71: PU53283 | K71: INV2836 | M71: 1 | N71: Unit | O71: 6000 | P71: 0 | Q71: 0 | R71: =SUM(O71:Q71) -> 6000 | S71: 120 | T71: -200 | U71: =-$R71/$S71 -> -50 | V71: =-$R71/$S71 -> -50 | W71: =-$R71/$S71 -> -50 | X71: =-$R71/$S71 -> -50 | Y71: =-$R71/$S71 -> -50 | Z71: =-$R71/$S71 -> -50 | AA71: =-$R71/$S71 -> -50 | AB71: =-$R71/$S71 -> -50 | AC71: =-$R71/$S71 -> -50 | AD71: 0 | AE71: 0 | AF71: 0 | AG71: =SUM(U71:AF71) -> -450 | AH71: 0 | AI71: =T71+AG71+AH71 -> -650 | AK71: =R71+AI71 -> 5350 | AL71: =O71+T71 -> 5800
A72: 45372 | C72: IR-24-A0100142 | D72: SUPPLY & INSTALL 4" TRANSPARENT PVC CURTAIN C/W BRACKET AT BLOCK A | E72: CBE M&E ENGINEERING SDN BHD | F72: TAMPOI | G72: MAINT | H72: GENERAL | I72: 2400397 | J72: PU53405 | K72: INV2849 | M72: 1 | N72: Unit | O72: 2850 | P72: 0 | Q72: 0 | R72: =SUM(O72:Q72) -> 2850 | S72: 120 | T72: -95 | U72: =-$R72/$S72 -> -23.75 | V72: =-$R72/$S72 -> -23.75 | W72: =-$R72/$S72 -> -23.75 | X72: =-$R72/$S72 -> -23.75 | Y72: =-$R72/$S72 -> -23.75 | Z72: =-$R72/$S72 -> -23.75 | AA72: =-$R72/$S72 -> -23.75 | AB72: =-$R72/$S72 -> -23.75 | AC72: =-$R72/$S72 -> -23.75 | AD72: 0 | AE72: 0 | AF72: 0 | AG72: =SUM(U72:AF72) -> -213.75 | AH72: 0 | AI72: =T72+AG72+AH72 -> -308.75 | AK72: =R72+AI72 -> 2541.25 | AL72: =O72+T72 -> 2755
A73: 42449 | C73: IR-00014C01-16 | D73: 32 PCS FOR FLOORING C/W WELDING & SUPPORTS | F73: TAMPOI | G73: METZ | H73: General | L73: Installation works | M73: 1 | N73: Unit | O73: 5500 | P73: 0 | Q73: 0 | R73: =SUM(O73:Q73) -> 5500 | S73: 120 | T73: -4718.0267 | U73: -54.83 | V73: =-$R73/$S73 -> -45.833333 | W73: =-$R73/$S73 -> -45.833333 | X73: =-$R73/$S73 -> -45.833333 | Y73: =-$R73/$S73 -> -45.833333 | Z73: =-$R73/$S73 -> -45.833333 | AA73: =-$R73/$S73 -> -45.833333 | AB73: =-$R73/$S73 -> -45.833333 | AC73: =-$R73/$S73 -> -45.833333 | AD73: 0 | AE73: 0 | AF73: 0 | AG73: =SUM(U73:AF73) -> -421.49667 | AH73: 0 | AI73: =T73+AG73+AH73 -> -5139.5233 | AK73: =R73+AI73 -> 360.47667 | AL73: =O73+T73 -> 781.97333
A74: 43040 | C74: IR-00017A01-17 | D74: SUPPLY AND INSTALLATION FOR SENAI CANTEEN - GLASS WINDOW, POLYCABONET WINDOW, PRESSURE WATER PUMP, U CAPPING ROOF EGDE, SINK & FLEXIBLE PIPE & VALVE & PIPING WORKS, REPLACE DRAIN COVER AND REPAIR TANK RECEIVER | F74: SENAI | G74: CORPORAT | H74: GENERAL | L74: Installation works | M74: 1 | N74: UNIT | O74: 19608.32 | P74: 0 | Q74: 0 | R74: =SUM(O74:Q74) -> 19608.32 | S74: 36 | T74: -19608.32 | U74: 0 | V74: 0 | W74: 0 | X74: 0 | Y74: 0 | Z74: 0 | AA74: 0 | AB74: 0 | AC74: 0 | AD74: 0 | AE74: 0 | AF74: 0 | AG74: =SUM(U74:AF74) -> 0 | AH74: 0 | AI74: =T74+AG74+AH74 -> -19608.32 | AK74: =R74+AI74 -> 0 | AL74: =O74+T74 -> 0
A75: 45422 | C75: IR-24-A0100145 | D75: INSTALL SLIDING DOOR IN BETWEEN BLOCK A & BLOCK C | E75: CBE M&E ENGINEERING SDN BHD | F75: TAMPOI | G75: MAINT | H75: GENERAL | I75: 2400593 | J75: DT 1429 | K75: INV2883 | M75: 1 | N75: Unit | O75: 68400 | P75: 0 | Q75: 0 | R75: =SUM(O75:Q75) -> 68400 | S75: 120 | T75: 0 | U75: 0 | V75: 0 | W75: 0 | X75: 0 | Y75: 0 | Z75: 0 | AA75: 0 | AB75: 0 | AC75: 0 | AD75: 0 | AE75: 0 | AF75: 0 | AG75: =SUM(U75:AF75) -> 0 | AH75: 0 | AI75: =T75+AG75+AH75 -> 0 | AK75: =R75+AI75 -> 68400 | AL75: =O75+T75 -> 68400
A76: 43282 | C76: IR-00043A01-18 | D76: HACKING EXISTING BRICKWALL AND PLASTERING PARTITION AT BLOCK 4 BAG MAKING AREA INCLUDING TOUCH UP PLASTERING FOR AFFECTED BEAM AND COLUMN, CONSTRUCTION BRICKWALL C/W PLASTERING BOTHSIDE AND CONCRETE STIFFENER AND WALL PAINTING | F76: SENAI | G76: BAGMAKE | H76: GENERAL | L76: Installation works | M76: 1 | N76: UNIT | O76: 20000 | P76: 0 | Q76: 0 | R76: =SUM(O76:Q76) -> 20000 | S76: 96 | T76: -14791.46 | U76: -208.33 | V76: =-$R76/$S76 -> -208.33333 | W76: =-$R76/$S76 -> -208.33333 | X76: =-$R76/$S76 -> -208.33333 | Y76: =-$R76/$S76 -> -208.33333 | Z76: =-$R76/$S76 -> -208.33333 | AA76: =-$R76/$S76 -> -208.33333 | AB76: =-$R76/$S76 -> -208.33333 | AC76: =-$R76/$S76 -> -208.33333 | AD76: 0 | AE76: 0 | AF76: 0 | AG76: =SUM(U76:AF76) -> -1874.9967 | AH76: 0 | AI76: =T76+AG76+AH76 -> -16666.457 | AK76: =R76+AI76 -> 3333.5433 | AL76: =O76+T76 -> 5208.54
A77: 43466 | C77: IR-00058A01-19 | D77: PLASTER PARTITION INCLUDING PLASTER PARTITION, METAL RUNNER, LABOUR CHARGES, JOTON PAINT, PAINTING WORK CHARGES, MAXI LIGHT PAINT, PAINTING WORK CHARGES, SWING DOOR AND HANDERING CHARGES FOR CONSTRUCTION OF FIRST AIDS ROOM AT BLK 7 OFFICE | F77: SENAI | G77: CORPORAT | H77: GENERAL | L77: Installation works | M77: 1 | N77: UNIT | O77: 5253.98 | P77: 0 | Q77: 0 | R77: =SUM(O77:Q77) -> 5253.98 | S77: 120 | T77: -2889.5085 | U77: -43.78 | V77: =-$R77/$S77 -> -43.783167 | W77: =-$R77/$S77 -> -43.783167 | X77: =-$R77/$S77 -> -43.783167 | Y77: =-$R77/$S77 -> -43.783167 | Z77: =-$R77/$S77 -> -43.783167 | AA77: =-$R77/$S77 -> -43.783167 | AB77: =-$R77/$S77 -> -43.783167 | AC77: =-$R77/$S77 -> -43.783167 | AD77: 0 | AE77: 0 | AF77: 0 | AG77: =SUM(U77:AF77) -> -394.04533 | AH77: 0 | AI77: =T77+AG77+AH77 -> -3283.5538 | AK77: =R77+AI77 -> 1970.4262 | AL77: =O77+T77 -> 2364.4715
A78: 43678 | C78: IR-00072A01-19 | D78: TO SUPPLY LABOUR AND MATERIALS TO INSTALL 2 NOS EXHAUST DUCTING TO ROOFTOP INCLUDING INVERTER CAP, FILTER BOX, 1HP MEDIUM SIROCCO FAN & WIRING WORK AT BLK 4 | F78: SENAI | G78: BAGMAKE | H78: GENERAL | L78: Installation works | M78: 1 | N78: UNIT | O78: 13700 | P78: 0 | Q78: 0 | R78: =SUM(O78:Q78) -> 13700 | S78: 120 | T78: -6621.83 | U78: -114.17 | V78: =-$R78/$S78 -> -114.16667 | W78: =-$R78/$S78 -> -114.16667 | X78: =-$R78/$S78 -> -114.16667 | Y78: =-$R78/$S78 -> -114.16667 | Z78: =-$R78/$S78 -> -114.16667 | AA78: =-$R78/$S78 -> -114.16667 | AB78: =-$R78/$S78 -> -114.16667 | AC78: =-$R78/$S78 -> -114.16667 | AD78: 0 | AE78: 0 | AF78: 0 | AG78: =SUM(U78:AF78) -> -1027.5033 | AH78: 0 | AI78: =T78+AG78+AH78 -> -7649.3333 | AK78: =R78+AI78 -> 6050.6667 | AL78: =O78+T78 -> 7078.17
A79: 43678 | C79: IR-00073A01-19 | D79: TO SUPPLY AND INSTALL WATER TAP AND PIPING SYSTEM INCLUDING NC500 WATER TANK,CONCRETE FOUNDATION FOR WATER TANK, POLY PIPE & PVC PIPE FOR BLK 7 | F79: SENAI | G79: CORPORAT | H79: GENERAL | L79: Installation works | M79: 1 | N79: UNIT | O79: 3500 | P79: 0 | Q79: 0 | R79: =SUM(O79:Q79) -> 3500 | S79: 120 | T79: -1721 | U79: -29.17 | V79: =-$R79/$S79 -> -29.166667 | W79: =-$R79/$S79 -> -29.166667 | X79: =-$R79/$S79 -> -29.166667 | Y79: =-$R79/$S79 -> -29.166667 | Z79: =-$R79/$S79 -> -29.166667 | AA79: =-$R79/$S79 -> -29.166667 | AB79: =-$R79/$S79 -> -29.166667 | AC79: =-$R79/$S79 -> -29.166667 | AD79: 0 | AE79: 0 | AF79: 0 | AG79: =SUM(U79:AF79) -> -262.50333 | AH79: 0 | AI79: =T79+AG79+AH79 -> -1983.5033 | AK79: =R79+AI79 -> 1516.4967 | AL79: =O79+T79 -> 1779
A80: 43770 | C80: IR-00074A01-19 | D80: TO SUPPLY AND INSTALL POLYCABONET PARTITION ROOF FOR BARRIER GATE AT GUARD HOUSE | F80: SENAI | G80: HR | H80: GENERAL | L80: Installation works | M80: 1 | N80: UNIT | O80: 5000 | P80: 0 | Q80: 0 | R80: =SUM(O80:Q80) -> 5000 | S80: 120 | T80: -2333.49 | U80: -41.67 | V80: =-$R80/$S80 -> -41.666667 | W80: =-$R80/$S80 -> -41.666667 | X80: =-$R80/$S80 -> -41.666667 | Y80: =-$R80/$S80 -> -41.666667 | Z80: =-$R80/$S80 -> -41.666667 | AA80: =-$R80/$S80 -> -41.666667 | AB80: =-$R80/$S80 -> -41.666667 | AC80: =-$R80/$S80 -> -41.666667 | AD80: 0 | AE80: 0 | AF80: 0 | AG80: =SUM(U80:AF80) -> -375.00333 | AH80: 0 | AI80: =T80+AG80+AH80 -> -2708.4933 | AK80: =R80+AI80 -> 2291.5067 | AL80: =O80+T80 -> 2666.51
A81: 45485 | C81: IR-24-A0100144 | D81: BLOCK C FUJI NCARGO LIFT | E81: CBE M&E ENGINEERING SDN BHD | F81: TAMPOI | G81: MAINT | H81: GENERAL | I81: 2400101 | J81: DT 1404/ PU54703 | M81: 1 | N81: Unit | O81: 63200 | P81: 94800 | Q81: 0 | R81: =SUM(O81:Q81) -> 158000 | S81: 120 | T81: 0 | U81: =-$R81/$S81 -> -1316.6667 | V81: =-$R81/$S81 -> -1316.6667 | W81: =-$R81/$S81 -> -1316.6667 | X81: =-$R81/$S81 -> -1316.6667 | Y81: =-$R81/$S81 -> -1316.6667 | Z81: =-$R81/$S81 -> -1316.6667 | AA81: =-$R81/$S81 -> -1316.6667 | AB81: =-$R81/$S81 -> -1316.6667 | AC81: =-$R81/$S81 -> -1316.6667 | AD81: 0 | AE81: 0 | AF81: 0 | AG81: =SUM(U81:AF81) -> -11850 | AH81: 0 | AI81: =T81+AG81+AH81 -> -11850 | AK81: =R81+AI81 -> 146150 | AL81: =O81+T81 -> 63200
A83: 45064 | C83: IR-23-A0100108 | D83: CONSTRUCTION OF MOTORCYCLE PARKING AREA | E83: LEGASI KHALIFAH | F83: TAMPOI | G83: MAINT | H83: GENERAL | I83: 2300642 | J83: DT1294/ DT1312 | K83: LKE/DP/0001 | L83: Installation works | M83: 1 | N83: Unit | O83: =19394.38+28605.62 -> 48000 | P83: 0 | Q83: 0 | R83: =SUM(O83:Q83) -> 48000 | S83: 120 | T83: -161.62 | U83: 0 | V83: 0 | W83: 0 | X83: 0 | Y83: 0 | Z83: 0 | AA83: =-T83 -> 161.62 | AB83: 0 | AC83: 0 | AD83: 0 | AE83: 0 | AF83: 0 | AG83: =SUM(U83:AF83) -> 161.62 | AH83: 0 | AI83: =T83+AG83+AH83 -> 0 | AK83: =R83+AI83 -> 48000 | AL83: =O83+T83 -> 47838.38
O85: =SUM(O6:O84) -> 4647319.3 | P85: =SUM(P6:P84) -> 94800 | Q85: =SUM(Q6:Q84) -> 0 | R85: =SUM(R6:R84) -> 4742119.3 | T85: =SUM(T6:T84) -> -771469.39 | U85: =SUM(U6:U84) -> -38469.451 | V85: =SUM(V6:V84) -> -38460.451 | W85: =SUM(W6:W84) -> -38460.451 | X85: =SUM(X6:X84) -> -38460.451 | Y85: =SUM(Y6:Y84) -> -38460.451 | Z85: =SUM(Z6:Z84) -> -38460.451 | AA85: =SUM(AA6:AA84) -> -38298.481 | ... AI85: =SUM(AI6:AI84) -> -1116502.7 | AK85: =SUM(AK6:AK84) -> 3625616.6 | AL85: =SUM(AL6:AL84) -> 3875849.9
AG88: In Balance Sheet as at 31/3/25 | AI88: -1116502.7

Sheet PM
A1: =[33]LAND!A1 -> TOMYPAK FLEXIBLE PACKAGING SDN BHD
A2: =[33]LAND!A2 -> FOR THE YEAR ENDED 30 JUNE 2025 | G2: BASED ON SAP
A3: PLANT AND MACHINERIES | G3: NOT YET PAY/ NOT FULLY PAY
A4: 11101-018 | G4: PV NOT SIGNED | AL4: Closing | AM4: Opening
A5: Acquisition Date | B5: Disposal Date | C5: F/A Code | D5: F/A Description | E5: Suppliers | F5: Cost Ctr. 1 | G5: Cost Ctr. 2 | H5: Cost Ctr. 3 | I5: Purchase Order | J5: NO. | K5: Invoice No. | L5: Remarks | M5: Original Currency | N5: Quantity | O5: UOM | P5: Cost c/f | Q5: Addition | R5: Disposal/ Written off | S5: Cost b/f | T5: Months | U5: Acc Depn b/f | V5: Jul | W5: Aug | X5: Sept | Y5: Oct | Z5: Nov | AA5: Dec | AB5: Jan | AC5: Feb | AD5: Mar | AE5: Apr | AF5: May | AG5: Jun | AH5: Current Year Depn | AI5: Disposal/ Written off | AJ5: Acc Depn c/f | AL5: =FBT!AA5 -> NBV As At 30/06/2025 | AM5: =FBT!AB5 -> NBV As At 30/06/2024
A6: 40755 | C6: PM00-0012/9 | D6: RATING: 15KW | F6: TAMPOI | G6: PROD | H6: General | L6: Installation | N6: 1 | O6: Unit | P6: 10000 | Q6: 0 | R6: 0 | S6: =SUM(P6:R6) -> 10000 | T6: 120 | U6: -10000 | V6: 0 | W6: 0 | X6: 0 | Y6: 0 | Z6: 0 | AA6: 0 | AB6: 0 | AC6: 0 | AD6: 0 | AE6: 0 | AF6: 0 | AG6: 0 | AH6: =SUM(V6:AG6) -> 0 | AI6: 0 | AJ6: =U6+AH6+AI6 -> -10000 | AL6: =S6+AJ6 -> 0 | AM6: =P6+U6 -> 0
A7: 40755 | C7: PM00-0053/33 | D7: 1200MM L - TO DO GRINDING ON IMPRESS R/R NO.1 SCHIAVI | F7: TAMPOI | G7: PROD | H7: General | N7: 1 | O7: Unit | P7: 470 | Q7: 0 | R7: 0 | S7: =SUM(P7:R7) -> 470 | T7: 120 | U7: -470 | V7: 0 | W7: 0 | X7: 0 | Y7: 0 | Z7: 0 | AA7: 0 | AB7: 0 | AC7: 0 | AD7: 0 | AE7: 0 | AF7: 0 | AG7: 0 | AH7: =SUM(V7:AG7) -> 0 | AI7: 0 | AJ7: =U7+AH7+AI7 -> -470 | AL7: =S7+AJ7 -> 0 | AM7: =P7+U7 -> 0
A8: 40755 | C8: PM00-0062/36 | D8: TYPE: UGCMED - 37AA406 FOR D/L,PT 1 &2 & E/L | F8: TAMPOI | G8: PROD | H8: General | N8: 1 | O8: Unit | P8: 10073.7 | Q8: 0 | R8: 0 | S8: =SUM(P8:R8) -> 10073.7 | T8: 120 | U8: -10073.7 | V8: 0 | W8: 0 | X8: 0 | Y8: 0 | Z8: 0 | AA8: 0 | AB8: 0 | AC8: 0 | AD8: 0 | AE8: 0 | AF8: 0 | AG8: 0 | AH8: =SUM(V8:AG8) -> 0 | AI8: 0 | AJ8: =U8+AH8+AI8 -> -10073.7 | AL8: =S8+AJ8 -> 0 | AM8: =P8+U8 -> 0
A9: 40755 | C9: PM00-0064/36 | D9: TYPE: UGCMED - 04AA206 FOR D/L,PT 1 &2 & E/L | F9: TAMPOI | G9: PROD | H9: General | N9: 1 | O9: Unit | P9: 4141.8 | Q9: 0 | R9: 0 | S9: =SUM(P9:R9) -> 4141.8 | T9: 120 | U9: -4141.8 | V9: 0 | W9: 0 | X9: 0 | Y9: 0 | Z9: 0 | AA9: 0 | AB9: 0 | AC9: 0 | AD9: 0 | AE9: 0 | AF9: 0 | AG9: 0 | AH9: =SUM(V9:AG9) -> 0 | AI9: 0 | AJ9: =U9+AH9+AI9 -> -4141.8 | AL9: =S9+AJ9 -> 0 | AM9: =P9+U9 -> 0
A10: 40755 | C10: PM00-0065/36 | D10: @JPY103000/PC LESS DIS. JPY3K ZA-5A 24V DC FOR EL, DL & SL | F10: TAMPOI | G10: PROD | H10: General | N10: 1 | O10: Unit | P10: 7020 | Q10: 0 | R10: 0 | S10: =SUM(P10:R10) -> 7020 | T10: 120 | U10: -7020 | V10: 0 | W10: 0 | X10: 0 | Y10: 0 | Z10: 0 | AA10: 0 | AB10: 0 | AC10: 0 | AD10: 0 | AE10: 0 | AF10: 0 | AG10: 0 | AH10: =SUM(V10:AG10) -> 0 | AI10: 0 | AJ10: =U10+AH10+AI10 -> -7020 | AL10: =S10+AJ10 -> 0 | AM10: =P10+U10 -> 0
A11: 40755 | C11: PM00-0088/49 | D11: COMPRESSOR KST 22.4 FOR FOR NO. 1 & 4 AIR COMPRESSOR | F11: TAMPOI | G11: PROD | H11: General | N11: 1 | O11: Unit | P11: 8738 | Q11: 0 | R11: 0 | S11: =SUM(P11:R11) -> 8738 | T11: 120 | U11: -8738 | V11: 0 | W11: 0 | X11: 0 | Y11: 0 | Z11: 0 | AA11: 0 | AB11: 0 | AC11: 0 | AD11: 0 | AE11: 0 | AF11: 0 | AG11: 0 | AH11: =SUM(V11:AG11) -> 0 | AI11: 0 | AJ11: =U11+AH11+AI11 -> -8738 | AL11: =S11+AJ11 -> 0 | AM11: =P11+U11 -> 0
A12: 40755 | C12: PM00-0172/111 | D12: 1 UNIT CHILLER TANK C/W INSULA INSULATION & BUFFLE PLATE,PIP' 4 NO | F12: TAMPOI | G12: CPP | H12: General | N12: 1 | O12: Unit | P12: 24800 | Q12: 0 | R12: 0 | S12: =SUM(P12:R12) -> 24800 | T12: 120 | U12: -24800 | V12: 0 | W12: 0 | X12: 0 | Y12: 0 | Z12: 0 | AA12: 0 | AB12: 0 | AC12: 0 | AD12: 0 | AE12: 0 | AF12: 0 | AG12: 0 | AH12: =SUM(V12:AG12) -> 0 | AI12: 0 | AJ12: =U12+AH12+AI12 -> -24800 | AL12: =S12+AJ12 -> 0 | AM12: =P12+U12 -> 0
A13: 40755 | C13: PM00-0173/112 | D13: FLOW CAPACITY: 636 CFM @ RM4000/UNIT | F13: TAMPOI | G13: PROD | H13: General | N13: 1 | O13: Unit | P13: 8000 | Q13: 0 | R13: 0 | S13: =SUM(P13:R13) -> 8000 | T13: 120 | U13: -8000 | V13: 0 | W13: 0 | X13: 0 | Y13: 0 | Z13: 0 | AA13: 0 | AB13: 0 | AC13: 0 | AD13: 0 | AE13: 0 | AF13: 0 | AG13: 0 | AH13: =SUM(V13:AG13) -> 0 | AI13: 0 | AJ13: =U13+AH13+AI13 -> -8000 | AL13: =S13+AJ13 -> 0 | AM13: =P13+U13 -> 0
A14: 40755 | C14: PM00-0179/116 | D14: TO WELD & MACHINE ROLLER | F14: TAMPOI | G14: PROD | H14: General | N14: 1 | O14: Unit | P14: 200 | Q14: 0 | R14: 0 | S14: =SUM(P14:R14) -> 200 | T14: 120 | U14: -200 | V14: 0 | W14: 0 | X14: 0 | Y14: 0 | Z14: 0 | AA14: 0 | AB14: 0 | AC14: 0 | AD14: 0 | AE14: 0 | AF14: 0 | AG14: 0 | AH14: =SUM(V14:AG14) -> 0 | AI14: 0 | AJ14: =U14+AH14+AI14 -> -200 | AL14: =S14+AJ14 -> 0 | AM14: =P14+U14 -> 0
A15: 40755 | C15: PM00-0183/120 | D15: FLOW CAPACITY: 424CFM INTER TEMPERATURE: 35 DEG C AMBI | F15: TAMPOI | G15: PROD | H15: General | N15: 1 | O15: Unit | P15: 11200 | Q15: 0 | R15: 0 | S15: =SUM(P15:R15) -> 11200 | T15: 120 | U15: -11200 | V15: 0 | W15: 0 | X15: 0 | Y15: 0 | Z15: 0 | AA15: 0 | AB15: 0 | AC15: 0 | AD15: 0 | AE15: 0 | AF15: 0 | AG15: 0 | AH15: =SUM(V15:AG15) -> 0 | AI15: 0 | AJ15: =U15+AH15+AI15 -> -11200 | AL15: =S15+AJ15 -> 0 | AM15: =P15+U15 -> 0
A16: 40755 | C16: PM00-0202/129 | D16: * 1320MM L - TO DO GRINDING -MATTRING RUBBER ROLLER | F16: TAMPOI | G16: PROD | H16: General | N16: 1 | O16: Unit | P16: 380 | Q16: 0 | R16: 0 | S16: =SUM(P16:R16) -> 380 | T16: 120 | U16: -380 | V16: 0 | W16: 0 | X16: 0 | Y16: 0 | Z16: 0 | AA16: 0 | AB16: 0 | AC16: 0 | AD16: 0 | AE16: 0 | AF16: 0 | AG16: 0 | AH16: =SUM(V16:AG16) -> 0 | AI16: 0 | AJ16: =U16+AH16+AI16 -> -380 | AL16: =S16+AJ16 -> 0 | AM16: =P16+U16 -> 0
A17: 40755 | C17: PM00-0218/136 | D17: RUG JPY60000 & 75 PCS RUG JPY60000 FOR STM - TOSHIN 5,6 & 7 | F17: TAMPOI | G17: PROD | H17: General | N17: 1 | O17: Unit | P17: 4968 | Q17: 0 | R17: 0 | S17: =SUM(P17:R17) -> 4968 | T17: 120 | U17: -4968 | V17: 0 | W17: 0 | X17: 0 | Y17: 0 | Z17: 0 | AA17: 0 | AB17: 0 | AC17: 0 | AD17: 0 | AE17: 0 | AF17: 0 | AG17: 0 | AH17: =SUM(V17:AG17) -> 0 | AI17: 0 | AJ17: =U17+AH17+AI17 -> -4968 | AL17: =S17+AJ17 -> 0 | AM17: =P17+U17 -> 0
A18: 40755 | C18: PM00-0228/145 | D18: 2PC RM100 & 1 PC 203 OD *150ID *100MM HOLLOW PIPE RM68 -MAI | F18: TAMPOI | G18: PROD | H18: General | L18: Installation | N18: 1 | O18: Unit | P18: 168 | Q18: 0 | R18: 0 | S18: =SUM(P18:R18) -> 168 | T18: 120 | U18: -168 | V18: 0 | W18: 0 | X18: 0 | Y18: 0 | Z18: 0 | AA18: 0 | AB18: 0 | AC18: 0 | AD18: 0 | AE18: 0 | AF18: 0 | AG18: 0 | AH18: =SUM(V18:AG18) -> 0 | AI18: 0 | AJ18: =U18+AH18+AI18 -> -168 | AL18: =S18+AJ18 -> 0 | AM18: =P18+U18 -> 0
A19: 40755 | C19: PM00-0240/153 | D19: TYPE UGCMED-04AA206 - MAINTENANCE | F19: TAMPOI | G19: PROD | H19: General | N19: 1 | O19: Unit | P19: 4953.28 | Q19: 0 | R19: 0 | S19: =SUM(P19:R19) -> 4953.28 | T19: 120 | U19: -4953.28 | V19: 0 | W19: 0 | X19: 0 | Y19: 0 | Z19: 0 | AA19: 0 | AB19: 0 | AC19: 0 | AD19: 0 | AE19: 0 | AF19: 0 | AG19: 0 | AH19: =SUM(V19:AG19) -> 0 | AI19: 0 | AJ19: =U19+AH19+AI19 -> -4953.28 | AL19: =S19+AJ19 -> 0 | AM19: =P19+U19 -> 0
A20: 40755 | C20: PM00-0247/159 | D20: & MACHINE HEAD OF EXTRUDER FOR RESIN FILTER FOR CPP | F20: TAMPOI | G20: CPP | H20: General | N20: 1 | O20: Unit | P20: 3200 | Q20: 0 | R20: 0 | S20: =SUM(P20:R20) -> 3200 | T20: 120 | U20: -3200 | V20: 0 | W20: 0 | X20: 0 | Y20: 0 | Z20: 0 | AA20: 0 | AB20: 0 | AC20: 0 | AD20: 0 | AE20: 0 | AF20: 0 | AG20: 0 | AH20: =SUM(V20:AG20) -> 0 | AI20: 0 | AJ20: =U20+AH20+AI20 -> -3200 | AL20: =S20+AJ20 -> 0 | AM20: =P20+U20 -> 0
A21: 41090 | C21: PM-00024A01-12 | D21: 4 SIDE SEAL BAG MAKING MACHINE | F21: TAMPOI | G21: BAGMAKE | H21: General | N21: 1 | O21: Unit | P21: 184207.96 | Q21: 0 | R21: 0 | S21: =SUM(P21:R21) -> 184207.96 | T21: 58 | U21: -184207.96 | V21: 0 | W21: 0 | X21: 0 | Y21: 0 | Z21: 0 | AA21: 0 | AB21: 0 | AC21: 0 | AD21: 0 | AE21: 0 | AF21: 0 | AG21: 0 | AH21: =SUM(V21:AG21) -> 0 | AI21: 0 | AJ21: =U21+AH21+AI21 -> -184207.96 | AL21: =S21+AJ21 -> 0 | AM21: =P21+U21 -> 0
A22: 41090 | C22: PM-00024A01-12/A | D22: 5 SIDE SEAL BAG MAKING MACHINE | F22: TAMPOI | G22: BAGMAKE | H22: General | N22: 1 | O22: Unit | P22: 200083.61 | Q22: 0 | R22: 0 | S22: =SUM(P22:R22) -> 200083.61 | T22: 62 | U22: -200083.61 | V22: 0 | W22: 0 | X22: 0 | Y22: 0 | Z22: 0 | AA22: 0 | AB22: 0 | AC22: 0 | AD22: 0 | AE22: 0 | AF22: 0 | AG22: 0 | AH22: =SUM(V22:AG22) -> 0 | AI22: 0 | AJ22: =U22+AH22+AI22 -> -200083.61 | AL22: =S22+AJ22 -> 0 | AM22: =P22+U22 -> 0
A23: 40990 | C23: PM-00024B01-12 | D23: FD-35V BM2-NEW (SHANGHAI BAG MAKING 2) (BM 2) | F23: TAMPOI | G23: BAGMAKE | H23: General | N23: 1 | O23: Unit | P23: 29165.11 | Q23: 0 | R23: 0 | S23: =SUM(P23:R23) -> 29165.11 | T23: 180 | U23: -23818.394 | V23: -162.03 | W23: =-$S23/$T23 -> -162.02839 | X23: =-$S23/$T23 -> -162.02839 | Y23: =-$S23/$T23 -> -162.02839 | Z23: =-$S23/$T23 -> -162.02839 | AA23: =-$S23/$T23 -> -162.02839 | AB23: =-$S23/$T23 -> -162.02839 | AC23: =-$S23/$T23 -> -162.02839 | AD23: =-$S23/$T23 -> -162.02839 | AE23: 0 | AF23: 0 | AG23: 0 | AH23: =SUM(V23:AG23) -> -1458.2571 | AI23: 0 | AJ23: =U23+AH23+AI23 -> -25276.651 | AL23: =S23+AJ23 -> 3888.459 | AM23: =P23+U23 -> 5346.7161
A24: 41090 | C24: PM-00024B02-12 | D24: SPARE PART FOR BM 2 | F24: TAMPOI | G24: BAGMAKE | H24: General | N24: 1 | O24: Unit | P24: 31608.81 | Q24: 0 | R24: 0 | S24: =SUM(P24:R24) -> 31608.81 | T24: 180 | U24: -25637.835 | V24: -175.6 | W24: =-$S24/$T24 -> -175.6045 | X24: =-$S24/$T24 -> -175.6045 | Y24: =-$S24/$T24 -> -175.6045 | Z24: =-$S24/$T24 -> -175.6045 | AA24: =-$S24/$T24 -> -175.6045 | AB24: =-$S24/$T24 -> -175.6045 | AC24: =-$S24/$T24 -> -175.6045 | AD24: =-$S24/$T24 -> -175.6045 | AE24: 0 | AF24: 0 | AG24: 0 | AH24: =SUM(V24:AG24) -> -1580.436 | AI24: 0 | AJ24: =U24+AH24+AI24 -> -27218.271 | AL24: =S24+AJ24 -> 4390.539 | AM24: =P24+U24 -> 5970.975
A25: 41090 | C25: PM-00024B03-12 | D25: (BM 2) | F25: TAMPOI | G25: BAGMAKE | H25: General | N25: 1 | O25: Unit | P25: 1600.7 | Q25: 0 | R25: 0 | S25: =SUM(P25:R25) -> 1600.7 | T25: 60 | U25: -1600.7 | V25: 0 | W25: 0 | X25: 0 | Y25: 0 | Z25: 0 | AA25: 0 | AB25: 0 | AC25: 0 | AD25: 0 | AE25: 0 | AF25: 0 | AG25: 0 | AH25: =SUM(V25:AG25) -> 0 | AI25: 0 | AJ25: =U25+AH25+AI25 -> -1600.7 | AL25: =S25+AJ25 -> 0 | AM25: =P25+U25 -> 0
A26: 41090 | C26: PM-00024B04-12 | D26: (BM 2) | F26: TAMPOI | G26: BAGMAKE | H26: General | N26: 1 | O26: Unit | P26: 1600.71 | Q26: 0 | R26: 0 | S26: =SUM(P26:R26) -> 1600.71 | T26: 60 | U26: -1600.71 | V26: 0 | W26: 0 | X26: 0 | Y26: 0 | Z26: 0 | AA26: 0 | AB26: 0 | AC26: 0 | AD26: 0 | AE26: 0 | AF26: 0 | AG26: 0 | AH26: =SUM(V26:AG26) -> 0 | AI26: 0 | AJ26: =U26+AH26+AI26 -> -1600.71 | AL26: =S26+AJ26 -> 0 | AM26: =P26+U26 -> 0
A27: 41183 | C27: PM-00024B05-12 | D27: TPO12/1794 | F27: TAMPOI | G27: BAGMAKE | H27: General | N27: 1 | O27: Unit | P27: 1886.54 | Q27: 0 | R27: 0 | S27: =SUM(P27:R27) -> 1886.54 | T27: 60 | U27: -1886.54 | V27: 0 | W27: 0 | X27: 0 | Y27: 0 | Z27: 0 | AA27: 0 | AB27: 0 | AC27: 0 | AD27: 0 | AE27: 0 | AF27: 0 | AG27: 0 | AH27: =SUM(V27:AG27) -> 0 | AI27: 0 | AJ27: =U27+AH27+AI27 -> -1886.54 | AL27: =S27+AJ27 -> 0 | AM27: =P27+U27 -> 0
A28: 41090 | C28: PM-00024B06-12 | D28: FRAMEWORK (FOR ABOVE MITSUHASHI'LPC&ELECTRIC REMOTE CONTROL FUNCTION) (BM 2) | F28: TAMPOI | G28: BAGMAKE | H28: General | N28: 1 | O28: Unit | P28: 17139.28 | Q28: 0 | R28: 0 | S28: =SUM(P28:R28) -> 17139.28 | T28: 60 | U28: -17139.28 | V28: 0 | W28: 0 | X28: 0 | Y28: 0 | Z28: 0 | AA28: 0 | AB28: 0 | AC28: 0 | AD28: 0 | AE28: 0 | AF28: 0 | AG28: 0 | AH28: =SUM(V28:AG28) -> 0 | AI28: 0 | AJ28: =U28+AH28+AI28 -> -17139.28 | AL28: =S28+AJ28 -> 0 | AM28: =P28+U28 -> 0
A29: 40969 | C29: PM-00024C01-12 | D29: CHARGE FOR LORRY CRANE, FORKLIFT & HANDLING FEE (BM 2) | F29: TAMPOI | G29: BAGMAKE | H29: General | L29: Installation | N29: 1 | O29: Unit | P29: 4270.08 | Q29: 0 | R29: 0 | S29: =SUM(P29:R29) -> 4270.08 | T29: 120 | U29: -4270.08 | V29: 0 | W29: 0 | X29: 0 | Y29: 0 | Z29: 0 | AA29: 0 | AB29: 0 | AC29: 0 | AD29: 0 | AE29: 0 | AF29: 0 | AG29: 0 | AH29: =SUM(V29:AG29) -> 0 | AI29: 0 | AJ29: =U29+AH29+AI29 -> -4270.08 | AL29: =S29+AJ29 -> 0 | AM29: =P29+U29 -> 0
A30: 40755 | C30: PM00-0251/162 | D30: GUIDE CONTROL SYSTEM PNEUMATIC CONVERTER TYPE | F30: TAMPOI | G30: PROD | H30: General | N30: 1 | O30: Unit | P30: 12673.53 | Q30: 0 | R30: 0 | S30: =SUM(P30:R30) -> 12673.53 | T30: 120 | U30: -12673.53 | V30: 0 | W30: 0 | X30: 0 | Y30: 0 | Z30: 0 | AA30: 0 | AB30: 0 | AC30: 0 | AD30: 0 | AE30: 0 | AF30: 0 | AG30: 0 | AH30: =SUM(V30:AG30) -> 0 | AI30: 0 | AJ30: =U30+AH30+AI30 -> -12673.53 | AL30: =S30+AJ30 -> 0 | AM30: =P30+U30 -> 0
A31: 40755 | C31: PM00-0271/176 | D31: FOR MTA WATER CHILLER MODE: TAE-M10 P/N # LPWP | F31: TAMPOI | G31: PROD | H31: General | N31: 1 | O31: Unit | P31: 831.44 | Q31: 0 | R31: 0 | S31: =SUM(P31:R31) -> 831.44 | T31: 120 | U31: -831.44 | V31: 0 | W31: 0 | X31: 0 | Y31: 0 | Z31: 0 | AA31: 0 | AB31: 0 | AC31: 0 | AD31: 0 | AE31: 0 | AF31: 0 | AG31: 0 | AH31: =SUM(V31:AG31) -> 0 | AI31: 0 | AJ31: =U31+AH31+AI31 -> -831.44 | AL31: =S31+AJ31 -> 0 | AM31: =P31+U31 -> 0
A32: 40755 | C32: PM00-0280/185 | D32: 709 SHAFT DIA. 75 X 225MM (W/O NO. MSW250700-4325) | F32: TAMPOI | G32: PROD | H32: General | N32: 1 | O32: Unit | P32: 430 | Q32: 0 | R32: 0 | S32: =SUM(P32:R32) -> 430 | T32: 120 | U32: -430 | V32: 0 | W32: 0 | X32: 0 | Y32: 0 | Z32: 0 | AA32: 0 | AB32: 0 | AC32: 0 | AD32: 0 | AE32: 0 | AF32: 0 | AG32: 0 | AH32: =SUM(V32:AG32) -> 0 | AI32: 0 | AJ32: =U32+AH32+AI32 -> -430 | AL32: =S32+AJ32 -> 0 | AM32: =P32+U32 -> 0
A33: 40755 | C33: PM00-0281/186 | D33: DIA.60 X 210MM | F33: TAMPOI | G33: PROD | H33: General | N33: 1 | O33: Unit | P33: 270 | Q33: 0 | R33: 0 | S33: =SUM(P33:R33) -> 270 | T33: 120 | U33: -270 | V33: 0 | W33: 0 | X33: 0 | Y33: 0 | Z33: 0 | AA33: 0 | AB33: 0 | AC33: 0 | AD33: 0 | AE33: 0 | AF33: 0 | AG33: 0 | AH33: =SUM(V33:AG33) -> 0 | AI33: 0 | AJ33: =U33+AH33+AI33 -> -270 | AL33: =S33+AJ33 -> 0 | AM33: =P33+U33 -> 0
A34: 40755 | C34: PM00-0290/193 | D34: FOR RELINDER MACHINE | F34: TAMPOI | G34: PROD | H34: General | N34: 1 | O34: Unit | P34: 1790 | Q34: 0 | R34: 0 | S34: =SUM(P34:R34) -> 1790 | T34: 120 | U34: -1790 | V34: 0 | W34: 0 | X34: 0 | Y34: 0 | Z34: 0 | AA34: 0 | AB34: 0 | AC34: 0 | AD34: 0 | AE34: 0 | AF34: 0 | AG34: 0 | AH34: =SUM(V34:AG34) -> 0 | AI34: 0 | AJ34: =U34+AH34+AI34 -> -1790 | AL34: =S34+AJ34 -> 0 | AM34: =P34+U34 -> 0
A35: 40755 | C35: PM00-0292/195 | D35: DIA.45 X 135MM W/O NO. M280700-4355 | F35: TAMPOI | G35: PROD | H35: General | N35: 1 | O35: Unit | P35: 650 | Q35: 0 | R35: 0 | S35: =SUM(P35:R35) -> 650 | T35: 120 | U35: -650 | V35: 0 | W35: 0 | X35: 0 | Y35: 0 | Z35: 0 | AA35: 0 | AB35: 0 | AC35: 0 | AD35: 0 | AE35: 0 | AF35: 0 | AG35: 0 | AH35: =SUM(V35:AG35) -> 0 | AI35: 0 | AJ35: =U35+AH35+AI35 -> -650 | AL35: =S35+AJ35 -> 0 | AM35: =P35+U35 -> 0
A36: 40755 | C36: PM00-0293/196 | D36: ELECTRO PNEUMATIC REGULAT | F36: TAMPOI | G36: CPP | H36: General | N36: 1 | O36: Unit | P36: 1321.67 | Q36: 0 | R36: 0 | S36: =SUM(P36:R36) -> 1321.67 | T36: 120 | U36: -1321.67 | V36: 0 | W36: 0 | X36: 0 | Y36: 0 | Z36: 0 | AA36: 0 | AB36: 0 | AC36: 0 | AD36: 0 | AE36: 0 | AF36: 0 | AG36: 0 | AH36: =SUM(V36:AG36) -> 0 | AI36: 0 | AJ36: =U36+AH36+AI36 -> -1321.67 | AL36: =S36+AJ36 -> 0 | AM36: =P36+U36 -> 0
A37: 40755 | C37: PM00-0294/197 | D37: ELECTRO PNEUMATIC SYSTEM | F37: TAMPOI | G37: CPP | H37: General | N37: 1 | O37: Unit | P37: 650 | Q37: 0 | R37: 0 | S37: =SUM(P37:R37) -> 650 | T37: 120 | U37: -650 | V37: 0 | W37: 0 | X37: 0 | Y37: 0 | Z37: 0 | AA37: 0 | AB37: 0 | AC37: 0 | AD37: 0 | AE37: 0 | AF37: 0 | AG37: 0 | AH37: =SUM(V37:AG37) -> 0 | AI37: 0 | AJ37: =U37+AH37+AI37 -> -650 | AL37: =S37+AJ37 -> 0 | AM37: =P37+U37 -> 0
A38: 40755 | C38: PM00-0321/218 | D38: TYPE:PCS-1.5 MAX. 300VA 50/60HZ INPU | F38: TAMPOI | G38: PROD | H38: General | N38: 1 | O38: Unit | P38: 1061.78 | Q38: 0 | R38: 0 | S38: =SUM(P38:R38) -> 1061.78 | T38: 120 | U38: -1061.78 | V38: 0 | W38: 0 | X38: 0 | Y38: 0 | Z38: 0 | AA38: 0 | AB38: 0 | AC38: 0 | AD38: 0 | AE38: 0 | AF38: 0 | AG38: 0 | AH38: =SUM(V38:AG38) -> 0 | AI38: 0 | AJ38: =U38+AH38+AI38 -> -1061.78 | AL38: =S38+AJ38 -> 0 | AM38: =P38+U38 -> 0
A39: 40755 | C39: PM00-0358/240 | D39: K28/500T | F39: TAMPOI | G39: PROD | H39: General | N39: 1 | O39: Unit | P39: 1450 | Q39: 0 | R39: 0 | S39: =SUM(P39:R39) -> 1450 | T39: 120 | U39: -1450 | V39: 0 | W39: 0 | X39: 0 | Y39: 0 | Z39: 0 | AA39: 0 | AB39: 0 | AC39: 0 | AD39: 0 | AE39: 0 | AF39: 0 | AG39: 0 | AH39: =SUM(V39:AG39) -> 0 | AI39: 0 | AJ39: =U39+AH39+AI39 -> -1450 | AL39: =S39+AJ39 -> 0 | AM39: =P39+U39 -> 0
A40: 40755 | C40: PM00-0390/268 | D40: GRIND SILICONE ROLLERS | F40: TAMPOI | G40: PROD | H40: General | N40: 1 | O40: Unit | P40: 2580 | Q40: 0 | R40: 0 | S40: =SUM(P40:R40) -> 2580 | T40: 120 | U40: -2580 | V40: 0 | W40: 0 | X40: 0 | Y40: 0 | Z40: 0 | AA40: 0 | AB40: 0 | AC40: 0 | AD40: 0 | AE40: 0 | AF40: 0 | AG40: 0 | AH40: =SUM(V40:AG40) -> 0 | AI40: 0 | AJ40: =U40+AH40+AI40 -> -2580 | AL40: =S40+AJ40 -> 0 | AM40: =P40+U40 -> 0
A41: 40755 | C41: PM00-0391A/269 | D41: MODEL: UC30JYE | F41: TAMPOI | G41: PROD | H41: General | N41: 1 | O41: Unit | P41: 10260 | Q41: 0 | R41: 0 | S41: =SUM(P41:R41) -> 10260 | T41: 120 | U41: -10260 | V41: 0 | W41: 0 | X41: 0 | Y41: 0 | Z41: 0 | AA41: 0 | AB41: 0 | AC41: 0 | AD41: 0 | AE41: 0 | AF41: 0 | AG41: 0 | AH41: =SUM(V41:AG41) -> 0 | AI41: 0 | AJ41: =U41+AH41+AI41 -> -10260 | AL41: =S41+AJ41 -> 0 | AM41: =P41+U41 -> 0
... A53: 41402 | C53: PM-00056A01-13 | D53: MACHINE, RPB-05 | F53: TAMPOI | G53: STORE | H53: General | N53: 1 | O53: Unit | P53: 8500 | Q53: 0 | R53: 0 | S53: =SUM(P53:R53) -> 8500 | T53: 60 | U53: -8500 | V53: 0 | W53: 0 | X53: 0 | Y53: 0 | Z53: 0 | AA53: 0 | AB53: 0 | AC53: 0 | AD53: 0 | AE53: 0 | AF53: 0 | AG53: 0 | AH53: =SUM(V53:AG53) -> 0 | AI53: 0 | AJ53: =U53+AH53+AI53 -> -8500 | AL53: =S53+AJ53 -> 0 | AM53: =P53+U53 -> 0
A54: 42104 | C54: PM-00085B02-15 | D54: EUROTHERM BOAT CONTROLLER UNIT | F54: TAMPOI | G54: METZ | H54: General | N54: 1 | O54: Unit | P54: 77714 | Q54: 0 | R54: 0 | S54: =SUM(P54:R54) -> 77714 | T54: 120 | U54: -72533.41 | V54: -647.62 | W54: =-$S54/$T54 -> -647.61667 | X54: =-$S54/$T54 -> -647.61667 | Y54: =-$S54/$T54 -> -647.61667 | Z54: =-$S54/$T54 -> -647.61667 | AA54: =-$S54/$T54 -> -647.61667 | AB54: =-$S54/$T54 -> -647.61667 | AC54: -647.27 | AD54: 0 | AE54: 0 | AF54: 0 | AG54: 0 | AH54: =SUM(V54:AG54) -> -5180.59 | AI54: 0 | AJ54: =U54+AH54+AI54 -> -77714 | AL54: =S54+AJ54 -> 0 | AM54: =P54+U54 -> 5180.59
A55: 42430 | C55: PM-00110A01-16 | D55: VACUUM WEB COATER C/W ACCESSORIES; BRAND: BOBST; MODEL: K4000-1250 | F55: TAMPOI | G55: METZ | H55: METZ 1 | N55: 1 | O55: Unit | P55: 5476896.8 | Q55: 0 | R55: 0 | S55: =SUM(P55:R55) -> 5476896.8 | T55: 180 | U55: -3073147.2 | V55: -30427.2 | W55: =-$S55/$T55 -> -30427.204 | X55: =-$S55/$T55 -> -30427.204 | Y55: =-$S55/$T55 -> -30427.204 | Z55: =-$S55/$T55 -> -30427.204 | AA55: =-$S55/$T55 -> -30427.204 | AB55: =-$S55/$T55 -> -30427.204 | AC55: =-$S55/$T55 -> -30427.204 | AD55: =-$S55/$T55 -> -30427.204 | AE55: 0 | AF55: 0 | AG55: 0 | AH55: =SUM(V55:AG55) -> -273844.84 | AI55: 0 | AJ55: =U55+AH55+AI55 -> -3346992.1 | AL55: =S55+AJ55 -> 2129904.7 | AM55: =P55+U55 -> 2403749.6
A56: 42429 | C56: PM-00110B02-16 | D56: CABLE FROM MSB TO NEW 1000A SSB, 1000A COMPARTMENT, 1000A TPN SSB, | F56: TAMPOI | G56: METZ | H56: General | N56: 1 | O56: Unit | P56: 194000 | Q56: 0 | R56: 0 | S56: =SUM(P56:R56) -> 194000 | T56: 180 | U56: -107777.98 | V56: -1077.78 | W56: =-$S56/$T56 -> -1077.7778 | X56: =-$S56/$T56 -> -1077.7778 | Y56: =-$S56/$T56 -> -1077.7778 | Z56: =-$S56/$T56 -> -1077.7778 | AA56: =-$S56/$T56 -> -1077.7778 | AB56: =-$S56/$T56 -> -1077.7778 | AC56: =-$S56/$T56 -> -1077.7778 | AD56: =-$S56/$T56 -> -1077.7778 | AE56: 0 | AF56: 0 | AG56: 0 | AH56: =SUM(V56:AG56) -> -9700.0022 | AI56: 0 | AJ56: =U56+AH56+AI56 -> -117477.98 | AL56: =S56+AJ56 -> 76522.018 | AM56: =P56+U56 -> 86222.02
A57: 42430 | C57: PM-00110B03-16 | D57: (CAPACITY (SWL): 1TON, MONORAIL BEAM: 10MTR, HOOK PATH: 4.5MTR (MAX: 5MTR) | F57: TAMPOI | G57: METZ | H57: General | N57: 1 | O57: Unit | P57: 13600 | Q57: 0 | R57: 0 | S57: =SUM(P57:R57) -> 13600 | T57: 120 | U57: -11446.36 | V57: -113.33 | W57: =-$S57/$T57 -> -113.33333 | X57: =-$S57/$T57 -> -113.33333 | Y57: =-$S57/$T57 -> -113.33333 | Z57: =-$S57/$T57 -> -113.33333 | AA57: =-$S57/$T57 -> -113.33333 | AB57: =-$S57/$T57 -> -113.33333 | AC57: =-$S57/$T57 -> -113.33333 | AD57: =-$S57/$T57 -> -113.33333 | AE57: 0 | AF57: 0 | AG57: 0 | AH57: =SUM(V57:AG57) -> -1019.9967 | AI57: 0 | AJ57: =U57+AH57+AI57 -> -12466.357 | AL57: =S57+AJ57 -> 1133.6433 | AM57: =P57+U57 -> 2153.64
A58: 42430 | C58: PM-00110B04-16 | D58: CAPACITY 125HRT; BRAND: LIANG CHI; MODEL: LRC-H-125 | F58: TAMPOI | G58: METZ | H58: General | N58: 1 | O58: Unit | P58: 35855 | Q58: 0 | R58: 0 | S58: =SUM(P58:R58) -> 35855 | T58: 120 | U58: -30177.805 | V58: -298.79 | W58: =-$S58/$T58 -> -298.79167 | X58: =-$S58/$T58 -> -298.79167 | Y58: =-$S58/$T58 -> -298.79167 | Z58: =-$S58/$T58 -> -298.79167 | AA58: =-$S58/$T58 -> -298.79167 | AB58: =-$S58/$T58 -> -298.79167 | AC58: =-$S58/$T58 -> -298.79167 | AD58: =-$S58/$T58 -> -298.79167 | AE58: 0 | AF58: 0 | AG58: 0 | AH58: =SUM(V58:AG58) -> -2689.1233 | AI58: 0 | AJ58: =U58+AH58+AI58 -> -32866.928 | AL58: =S58+AJ58 -> 2988.0717 | AM58: =P58+U58 -> 5677.195
A59: 42430 | C59: PM-00110B05-16 | D59: MODEL: EU 50/16; BRAND: EUROFLO; POWER: 15HP 2POLE 415V; CAPACITY: 1000LIT/MIN@35M | F59: TAMPOI | G59: METZ | H59: General | N59: 1 | O59: Unit | P59: 7896 | Q59: 0 | R59: 0 | S59: =SUM(P59:R59) -> 7896 | T59: 120 | U59: -6580 | V59: -65.8 | W59: =-$S59/$T59 -> -65.8 | X59: =-$S59/$T59 -> -65.8 | Y59: =-$S59/$T59 -> -65.8 | Z59: =-$S59/$T59 -> -65.8 | AA59: =-$S59/$T59 -> -65.8 | AB59: =-$S59/$T59 -> -65.8 | AC59: =-$S59/$T59 -> -65.8 | AD59: =-$S59/$T59 -> -65.8 | AE59: 0 | AF59: 0 | AG59: 0 | AH59: =SUM(V59:AG59) -> -592.2 | AI59: 0 | AJ59: =U59+AH59+AI59 -> -7172.2 | AL59: =S59+AJ59 -> 723.8 | AM59: =P59+U59 -> 1316 | AN59: =-(R59+AI59) -> 0
A60: 42430 | C60: PM-00110B06-16 | D60: MODEL: EU 50/16; BRAND: EUROFLO; POWER: 15HP 2POLE 415V; CAPACITY: 1000LIT/MIN@35M | F60: TAMPOI | G60: METZ | H60: General | N60: 1 | O60: Unit | P60: 7896 | Q60: 0 | R60: 0 | S60: =SUM(P60:R60) -> 7896 | T60: 120 | U60: -6580 | V60: -65.8 | W60: =-$S60/$T60 -> -65.8 | X60: =-$S60/$T60 -> -65.8 | Y60: =-$S60/$T60 -> -65.8 | Z60: =-$S60/$T60 -> -65.8 | AA60: =-$S60/$T60 -> -65.8 | AB60: =-$S60/$T60 -> -65.8 | AC60: =-$S60/$T60 -> -65.8 | AD60: =-$S60/$T60 -> -65.8 | AE60: 0 | AF60: 0 | AG60: 0 | AH60: =SUM(V60:AG60) -> -592.2 | AI60: 0 | AJ60: =U60+AH60+AI60 -> -7172.2 | AL60: =S60+AJ60 -> 723.8 | AM60: =P60+U60 -> 1316 | AN60: =-(R60+AI60) -> 0
A61: 42430 | C61: PM-00110B07-16 | D61: AREA INTO PLANT CONNECTION & CHILLER UNIT | F61: TAMPOI | G61: METZ | H61: General | N61: 1 | O61: Unit | P61: 22096 | Q61: 0 | R61: 0 | S61: =SUM(P61:R61) -> 22096 | T61: 120 | U61: -18413.027 | V61: -184.13 | W61: =-$S61/$T61 -> -184.13333 | X61: =-$S61/$T61 -> -184.13333 | Y61: =-$S61/$T61 -> -184.13333 | Z61: =-$S61/$T61 -> -184.13333 | AA61: =-$S61/$T61 -> -184.13333 | AB61: =-$S61/$T61 -> -184.13333 | AC61: =-$S61/$T61 -> -184.13333 | AD61: =-$S61/$T61 -> -184.13333 | AE61: 0 | AF61: 0 | AG61: 0 | AH61: =SUM(V61:AG61) -> -1657.1967 | AI61: 0 | AJ61: =U61+AH61+AI61 -> -20070.223 | AL61: =S61+AJ61 -> 2025.7767 | AM61: =P61+U61 -> 3682.9733 | AN61: =-(R61+AI61) -> 0
A62: 42430 | C62: PM-00110B08-16 | D62: MODEL: EU 25/16; BRAND: EUROFLO; POWER: 10HP 4POLE 415V; CAPACITY: 800LIT/MIN@20M | F62: TAMPOI | G62: METZ | H62: General | N62: 1 | O62: Unit | P62: 11619 | Q62: 0 | R62: 0 | S62: =SUM(P62:R62) -> 11619 | T62: 120 | U62: -9682.91 | V62: -96.83 | W62: =-$S62/$T62 -> -96.825 | X62: =-$S62/$T62 -> -96.825 | Y62: =-$S62/$T62 -> -96.825 | Z62: =-$S62/$T62 -> -96.825 | AA62: =-$S62/$T62 -> -96.825 | AB62: =-$S62/$T62 -> -96.825 | AC62: =-$S62/$T62 -> -96.825 | AD62: =-$S62/$T62 -> -96.825 | AE62: 0 | AF62: 0 | AG62: 0 | AH62: =SUM(V62:AG62) -> -871.43 | AI62: 0 | AJ62: =U62+AH62+AI62 -> -10554.34 | AL62: =S62+AJ62 -> 1064.66 | AM62: =P62+U62 -> 1936.09 | AN62: =-(R62+AI62) -> 0
A63: 42430 | C63: PM-00110B09-16 | D63: MODEL: EU 25/16; BRAND: EUROFLO; POWER: 10HP 4POLE 415V; CAPACITY: 800LIT/MIN@20M | F63: TAMPOI | G63: METZ | H63: General | N63: 1 | O63: Unit | P63: 11619 | Q63: 0 | R63: 0 | S63: =SUM(P63:R63) -> 11619 | T63: 120 | U63: -9586.08 | V63: -96.83 | W63: =-$S63/$T63 -> -96.825 | X63: =-$S63/$T63 -> -96.825 | Y63: =-$S63/$T63 -> -96.825 | Z63: =-$S63/$T63 -> -96.825 | AA63: =-$S63/$T63 -> -96.825 | AB63: =-$S63/$T63 -> -96.825 | AC63: =-$S63/$T63 -> -96.825 | AD63: =-$S63/$T63 -> -96.825 | AE63: 0 | AF63: 0 | AG63: 0 | AH63: =SUM(V63:AG63) -> -871.43 | AI63: 0 | AJ63: =U63+AH63+AI63 -> -10457.51 | AL63: =S63+AJ63 -> 1161.49 | AM63: =P63+U63 -> 2032.92 | AN63: =-(R63+AI63) -> 0
A64: 42430 | C64: PM-00110B10-16 | D64: MODEL: EU 50/20; BRAND: EUROFLO; POWER: 15HP 2POLE 415V; CAPACITY: 500LIT/MIN@60M | F64: TAMPOI | G64: METZ | H64: General | N64: 1 | O64: Unit | P64: 11122 | Q64: 0 | R64: 0 | S64: =SUM(P64:R64) -> 11122 | T64: 120 | U64: -9268.0267 | V64: -92.68 | W64: =-$S64/$T64 -> -92.683333 | X64: =-$S64/$T64 -> -92.683333 | Y64: =-$S64/$T64 -> -92.683333 | Z64: =-$S64/$T64 -> -92.683333 | AA64: =-$S64/$T64 -> -92.683333 | AB64: =-$S64/$T64 -> -92.683333 | AC64: =-$S64/$T64 -> -92.683333 | AD64: =-$S64/$T64 -> -92.683333 | AE64: 0 | AF64: 0 | AG64: 0 | AH64: =SUM(V64:AG64) -> -834.14667 | AI64: 0 | AJ64: =U64+AH64+AI64 -> -10102.173 | AL64: =S64+AJ64 -> 1019.8267 | AM64: =P64+U64 -> 1853.9733 | AN64: =-(R64+AI64) -> 0
A65: 42430 | C65: PM-00110B11-16 | D65: MODEL: EU 50/20; BRAND: EUROFLO; POWER: 15HP 2POLE 415V; CAPACITY: 500LIT/MIN@60M | F65: TAMPOI | G65: METZ | H65: General | N65: 1 | O65: Unit | P65: 11122 | Q65: 0 | R65: 0 | S65: =SUM(P65:R65) -> 11122 | T65: 120 | U65: -9268.0267 | V65: -92.68 | W65: =-$S65/$T65 -> -92.683333 | X65: =-$S65/$T65 -> -92.683333 | Y65: =-$S65/$T65 -> -92.683333 | Z65: =-$S65/$T65 -> -92.683333 | AA65: =-$S65/$T65 -> -92.683333 | AB65: =-$S65/$T65 -> -92.683333 | AC65: =-$S65/$T65 -> -92.683333 | AD65: =-$S65/$T65 -> -92.683333 | AE65: 0 | AF65: 0 | AG65: 0 | AH65: =SUM(V65:AG65) -> -834.14667 | AI65: 0 | AJ65: =U65+AH65+AI65 -> -10102.173 | AL65: =S65+AJ65 -> 1019.8267 | AM65: =P65+U65 -> 1853.9733 | AN65: =-(R65+AI65) -> 0
A66: 42430 | C66: PM-00110B12-16 | D66: & WATER PUMP (PM-00110B04-16, PM-00110B05-16 & PM-00110B06-16) | F66: TAMPOI | G66: METZ | H66: General | N66: 1 | O66: Unit | P66: 2394 | Q66: 0 | R66: 0 | S66: =SUM(P66:R66) -> 2394 | T66: 120 | U66: -1995 | V66: -19.95 | W66: =-$S66/$T66 -> -19.95 | X66: =-$S66/$T66 -> -19.95 | Y66: =-$S66/$T66 -> -19.95 | Z66: =-$S66/$T66 -> -19.95 | AA66: =-$S66/$T66 -> -19.95 | AB66: =-$S66/$T66 -> -19.95 | AC66: =-$S66/$T66 -> -19.95 | AD66: =-$S66/$T66 -> -19.95 | AE66: 0 | AF66: 0 | AG66: 0 | AH66: =SUM(V66:AG66) -> -179.55 | AI66: 0 | AJ66: =U66+AH66+AI66 -> -2174.55 | AL66: =S66+AJ66 -> 219.45 | AM66: =P66+U66 -> 399 | AN66: =-(R66+AI66) -> 0
A67: 42628 | C67: PM-00110B13-16 | D67: SOURCE C/W ACCESSORIES, 1 SET OF INSULATORS | F67: ` | G67: METZ | H67: General | N67: 1 | O67: Unit | P67: 356266.96 | Q67: 0 | R67: 0 | S67: =SUM(P67:R67) -> 356266.96 | T67: 180 | U67: -184071.19 | V67: -1979.26 | W67: =-$S67/$T67 -> -1979.2609 | X67: =-$S67/$T67 -> -1979.2609 | Y67: =-$S67/$T67 -> -1979.2609 | Z67: =-$S67/$T67 -> -1979.2609 | AA67: =-$S67/$T67 -> -1979.2609 | AB67: =-$S67/$T67 -> -1979.2609 | AC67: =-$S67/$T67 -> -1979.2609 | AD67: =-$S67/$T67 -> -1979.2609 | AE67: 0 | AF67: 0 | AG67: 0 | AH67: =SUM(V67:AG67) -> -17813.347 | AI67: 0 | AJ67: =U67+AH67+AI67 -> -201884.53 | AL67: =S67+AJ67 -> 154382.43 | AM67: =P67+U67 -> 172195.77 | AN67: =-(R67+AI67) -> 0
A68: 42430 | C68: PM-00110C15-16 | D68: AND MONKEY LADDER | F68: TAMPOI | G68: METZ | H68: General | N68: 1 | O68: Unit | P68: 2500 | Q68: 0 | R68: 0 | S68: =SUM(P68:R68) -> 2500 | T68: 180 | U68: -1402.88 | V68: -13.89 | W68: =-$S68/$T68 -> -13.888889 | X68: =-$S68/$T68 -> -13.888889 | Y68: =-$S68/$T68 -> -13.888889 | Z68: =-$S68/$T68 -> -13.888889 | AA68: =-$S68/$T68 -> -13.888889 | AB68: =-$S68/$T68 -> -13.888889 | AC68: =-$S68/$T68 -> -13.888889 | AD68: =-$S68/$T68 -> -13.888889 | AE68: 0 | AF68: 0 | AG68: 0 | AH68: =SUM(V68:AG68) -> -125.00111 | AI68: 0 | AJ68: =U68+AH68+AI68 -> -1527.8811 | AL68: =S68+AJ68 -> 972.11889 | AM68: =P68+U68 -> 1097.12
A69: 42674 | C69: PM-00110C16-16 | D69: CAMPLUS 3 PLASMA TREATER | F69: TAMPOI | G69: METZ | H69: General | N69: 1 | O69: Unit | P69: 3231 | Q69: 0 | R69: 0 | S69: =SUM(P69:R69) -> 3231 | T69: 180 | U69: -1669.35 | V69: -17.95 | W69: =-$S69/$T69 -> -17.95 | X69: =-$S69/$T69 -> -17.95 | Y69: =-$S69/$T69 -> -17.95 | Z69: =-$S69/$T69 -> -17.95 | AA69: =-$S69/$T69 -> -17.95 | AB69: =-$S69/$T69 -> -17.95 | AC69: =-$S69/$T69 -> -17.95 | AD69: =-$S69/$T69 -> -17.95 | AE69: 0 | AF69: 0 | AG69: 0 | AH69: =SUM(V69:AG69) -> -161.55 | AI69: 0 | AJ69: =U69+AH69+AI69 -> -1830.9 | AL69: =S69+AJ69 -> 1400.1 | AM69: =P69+U69 -> 1561.65
A70: 43132 | C70: PM-00110C17-18 | D70: SINGLE GIRDER MONORAIL CRANE (CAPACITY (SWL): 1TON, MONORAIL BEAM: 10MTR, HOOK PATH: 4.5MTR (MAX: 5MTR) | F70: TAMPOI | G70: METZ | H70: METZ 1 | N70: 1 | O70: UNIT | P70: 3400 | Q70: 0 | R70: 0 | S70: =SUM(P70:R70) -> 3400 | T70: 107 | U70: -2447.0213 | V70: -31.78 | W70: =-$S70/$T70 -> -31.775701 | X70: =-$S70/$T70 -> -31.775701 | Y70: =-$S70/$T70 -> -31.775701 | Z70: =-$S70/$T70 -> -31.775701 | AA70: =-$S70/$T70 -> -31.775701 | AB70: =-$S70/$T70 -> -31.775701 | AC70: =-$S70/$T70 -> -31.775701 | AD70: =-$S70/$T70 -> -31.775701 | AE70: 0 | AF70: 0 | AG70: 0 | AH70: =SUM(V70:AG70) -> -285.98561 | AI70: 0 | AJ70: =U70+AH70+AI70 -> -2733.0069 | AL70: =S70+AJ70 -> 666.99308 | AM70: =P70+U70 -> 952.97869
A71: 42304 | C71: PM-00111A01-15 | D71: (TWO LINES), FLAT BOTTOM POUCH WITH ZIPPER (TWO LINE) POUCH MAKING MACHINE | F71: TAMPOI | G71: BAGMAKE | H71: General | N71: 1 | O71: Unit | P71: 2083056 | Q71: 0 | R71: 0 | S71: =SUM(P71:R71) -> 2083056 | T71: 180 | U71: -1215115.7 | V71: -11572.53 | W71: =-$S71/$T71 -> -11572.533 | X71: =-$S71/$T71 -> -11572.533 | Y71: =-$S71/$T71 -> -11572.533 | Z71: =-$S71/$T71 -> -11572.533 | AA71: =-$S71/$T71 -> -11572.533 | AB71: =-$S71/$T71 -> -11572.533 | AC71: =-$S71/$T71 -> -11572.533 | AD71: =-$S71/$T71 -> -11572.533 | AE71: 0 | AF71: 0 | AG71: 0 | AH71: =SUM(V71:AG71) -> -104152.8 | AI71: 0 | AJ71: =U71+AH71+AI71 -> -1319268.5 | AL71: =S71+AJ71 -> 763787.52 | AM71: =P71+U71 -> 867940.32
A72: 42291 | C72: PM-00111B02-15 | D72: MODEL: PC 2AC, BRAND: VIP | F72: TAMPOI | G72: BAGMAKE | H72: General | N72: 1 | O72: Unit | P72: 9000 | Q72: 0 | R72: 0 | S72: =SUM(P72:R72) -> 9000 | T72: 60 | U72: -9000 | V72: 0 | W72: 0 | X72: 0 | Y72: 0 | Z72: 0 | AA72: 0 | AB72: 0 | AC72: 0 | AD72: 0 | AE72: 0 | AF72: 0 | AG72: 0 | AH72: =SUM(V72:AG72) -> 0 | AI72: 0 | AJ72: =U72+AH72+AI72 -> -9000 | AL72: =S72+AJ72 -> 0 | AM72: =P72+U72 -> 0
A73: 42345 | C73: PM-00111B03-15 | D73: MODEL: JD-300-30 | F73: TAMPOI | G73: BAGMAKE | H73: General | N73: 1 | O73: Unit | P73: 14350 | Q73: 0 | R73: 0 | S73: =SUM(P73:R73) -> 14350 | T73: 60 | U73: -14350 | V73: 0 | W73: 0 | X73: 0 | Y73: 0 | Z73: 0 | AA73: 0 | AB73: 0 | AC73: 0 | AD73: 0 | AE73: 0 | AF73: 0 | AG73: 0 | AH73: =SUM(V73:AG73) -> 0 | AI73: 0 | AJ73: =U73+AH73+AI73 -> -14350 | AL73: =S73+AJ73 -> 0 | AM73: =P73+U73 -> 0
A74: 42948 | C74: PM-00111B04-17 | D74: "VIP" BRAND INDUSTRIAL AIR COOL CHILLER | F74: TAMPOI | G74: BAGMAKE | H74: BM 9 | N74: 1 | O74: UNIT | P74: 11800 | Q74: 0 | R74: 0 | S74: =SUM(P74:R74) -> 11800 | T74: 60 | U74: -11800 | V74: -196.47 | W74: 196.47 | X74: 0 | Y74: 0 | Z74: 0 | AA74: 0 | AB74: 0 | AC74: 0 | AD74: 0 | AE74: 0 | AF74: 0 | AG74: 0 | AH74: =SUM(V74:AG74) -> 0 | AI74: 0 | AJ74: =U74+AH74+AI74 -> -11800 | AL74: =S74+AJ74 -> 0 | AM74: =P74+U74 -> 0
A75: 42308 | C75: PM-00111C01-15 | D75: OFF EXISTING BRICKWALL C/W SITE CLEARING, TO SUPPLY AND INSTALL 12MM THK PARTITION & BRICKWALL, | F75: TAMPOI | G75: BAGMAKE | H75: General | L75: Installation | N75: 1 | O75: Unit | P75: 6000 | Q75: 0 | R75: 0 | S75: =SUM(P75:R75) -> 6000 | T75: 180 | U75: -3499.68 | V75: -33.33 | W75: =-$S75/$T75 -> -33.333333 | X75: =-$S75/$T75 -> -33.333333 | Y75: =-$S75/$T75 -> -33.333333 | Z75: =-$S75/$T75 -> -33.333333 | AA75: =-$S75/$T75 -> -33.333333 | AB75: =-$S75/$T75 -> -33.333333 | AC75: =-$S75/$T75 -> -33.333333 | AD75: =-$S75/$T75 -> -33.333333 | AE75: 0 | AF75: 0 | AG75: 0 | AH75: =SUM(V75:AG75) -> -299.99667 | AI75: 0 | AJ75: =U75+AH75+AI75 -> -3799.6767 | AL75: =S75+AJ75 -> 2200.3233 | AM75: =P75+U75 -> 2500.32
A76: 42303 | C76: PM-00111C02-15 | D76: TRANSPORT CHARGES | F76: TAMPOI | G76: BAGMAKE | H76: General | N76: 2 | O76: Unit | P76: 3948.3 | Q76: 0 | R76: 0 | S76: =SUM(P76:R76) -> 3948.3 | T76: 180 | U76: -2303.585 | V76: -21.94 | W76: =-$S76/$T76 -> -21.935 | X76: =-$S76/$T76 -> -21.935 | Y76: =-$S76/$T76 -> -21.935 | Z76: =-$S76/$T76 -> -21.935 | AA76: =-$S76/$T76 -> -21.935 | AB76: =-$S76/$T76 -> -21.935 | AC76: =-$S76/$T76 -> -21.935 | AD76: =-$S76/$T76 -> -21.935 | AE76: 0 | AF76: 0 | AG76: 0 | AH76: =SUM(V76:AG76) -> -197.42 | AI76: 0 | AJ76: =U76+AH76+AI76 -> -2501.005 | AL76: =S76+AJ76 -> 1447.295 | AM76: =P76+U76 -> 1644.715
A77: 42311 | C77: PM-00111C03-15 | D77: INSURANCE - ERECTION ALL RISKS | F77: TAMPOI | G77: BAGMAKE | H77: General | N77: 2 | O77: Unit | P77: 2081.21 | Q77: 0 | R77: 0 | S77: =SUM(P77:R77) -> 2081.21 | T77: 180 | U77: -1202.2605 | V77: -11.56 | W77: =-$S77/$T77 -> -11.562278 | X77: =-$S77/$T77 -> -11.562278 | Y77: =-$S77/$T77 -> -11.562278 | Z77: =-$S77/$T77 -> -11.562278 | AA77: =-$S77/$T77 -> -11.562278 | AB77: =-$S77/$T77 -> -11.562278 | AC77: =-$S77/$T77 -> -11.562278 | AD77: =-$S77/$T77 -> -11.562278 | AE77: 0 | AF77: 0 | AG77: 0 | AH77: =SUM(V77:AG77) -> -104.05822 | AI77: 0 | AJ77: =U77+AH77+AI77 -> -1306.3187 | AL77: =S77+AJ77 -> 774.89128 | AM77: =P77+U77 -> 878.9495
A78: 42312 | C78: PM-00111C04-15 | D78: RENTAL OF EQUIPMENT | F78: TAMPOI | G78: BAGMAKE | H78: General | N78: 1 | O78: Unit | P78: 8900 | Q78: 0 | R78: 0 | S78: =SUM(P78:R78) -> 8900 | T78: 180 | U78: -5191.24 | V78: -49.44 | W78: =-$S78/$T78 -> -49.444444 | X78: =-$S78/$T78 -> -49.444444 | Y78: =-$S78/$T78 -> -49.444444 | Z78: =-$S78/$T78 -> -49.444444 | AA78: =-$S78/$T78 -> -49.444444 | AB78: =-$S78/$T78 -> -49.444444 | AC78: =-$S78/$T78 -> -49.444444 | AD78: =-$S78/$T78 -> -49.444444 | AE78: 0 | AF78: 0 | AG78: 0 | AH78: =SUM(V78:AG78) -> -444.99556 | AI78: 0 | AJ78: =U78+AH78+AI78 -> -5636.2356 | AL78: =S78+AJ78 -> 3263.7644 | AM78: =P78+U78 -> 3708.76
A79: 42312 | C79: PM-00111C05-15 | D79: PVC CABLE + E IN TRUNKING C/W TERMINATION. (20 MTR L) & DISMANTLE AND MODIFY 4 X 1/2 G.I PIPING | F79: TAMPOI | G79: BAGMAKE | H79: General | N79: 1 | O79: Unit | P79: 1200 | Q79: 0 | R79: 0 | S79: =SUM(P79:R79) -> 1200 | T79: 180 | U79: -700.32 | V79: -6.67 | W79: =-$S79/$T79 -> -6.6666667 | X79: =-$S79/$T79 -> -6.6666667 | Y79: =-$S79/$T79 -> -6.6666667 | Z79: =-$S79/$T79 -> -6.6666667 | AA79: =-$S79/$T79 -> -6.6666667 | AB79: =-$S79/$T79 -> -6.6666667 | AC79: =-$S79/$T79 -> -6.6666667 | AD79: =-$S79/$T79 -> -6.6666667 | AE79: 0 | AF79: 0 | AG79: 0 | AH79: =SUM(V79:AG79) -> -60.003333 | AI79: 0 | AJ79: =U79+AH79+AI79 -> -760.32333 | AL79: =S79+AJ79 -> 439.67667 | AM79: =P79+U79 -> 499.68
A80: 42334 | C80: PM-00111C06-15 | D80: PVC CABLE + E IN TRUNKING C/W TERMINATION. (20 MTR L), 10 X 10 METAL BOX, | F80: TAMPOI | G80: BAGMAKE | H80: General | N80: 1 | O80: Unit | P80: 1700 | Q80: 0 | R80: 0 | S80: =SUM(P80:R80) -> 1700 | T80: 180 | U80: -991.24 | V80: -9.44 | W80: =-$S80/$T80 -> -9.4444444 | X80: =-$S80/$T80 -> -9.4444444 | Y80: =-$S80/$T80 -> -9.4444444 | Z80: =-$S80/$T80 -> -9.4444444 | AA80: =-$S80/$T80 -> -9.4444444 | AB80: =-$S80/$T80 -> -9.4444444 | AC80: =-$S80/$T80 -> -9.4444444 | AD80: =-$S80/$T80 -> -9.4444444 | AE80: 0 | AF80: 0 | AG80: 0 | AH80: =SUM(V80:AG80) -> -84.995556 | AI80: 0 | AJ80: =U80+AH80+AI80 -> -1076.2356 | AL80: =S80+AJ80 -> 623.76444 | AM80: =P80+U80 -> 708.76
A81: 42347 | C81: PM-00111C07-15 | D81: FOR COM AUTOMATIC TAPING MACHINE (PM-00111B03-15) | F81: TAMPOI | G81: BAGMAKE | H81: General | N81: 1 | O81: Unit | P81: 3230.73 | Q81: 0 | R81: 0 | S81: =SUM(P81:R81) -> 3230.73 | T81: 60 | U81: -3230.73 | V81: 0 | W81: 0 | X81: 0 | Y81: 0 | Z81: 0 | AA81: 0 | AB81: 0 | AC81: 0 | AD81: 0 | AE81: 0 | AF81: 0 | AG81: 0 | AH81: =SUM(V81:AG81) -> 0 | AI81: 0 | AJ81: =U81+AH81+AI81 -> -3230.73 | AL81: =S81+AJ81 -> 0 | AM81: =P81+U81 -> 0
A82: 42515 | C82: PM-00117A01-16 | D82: REGISTERED PRINT POUCH MAKING MACHINE (HEAVY DUTY & HIGH SPEED) | F82: TAMPOI | G82: BAGMAKE | H82: BM 7 | N82: 1 | O82: Unit | P82: 610425 | Q82: 0 | R82: 0 | S82: =SUM(P82:R82) -> 610425 | T82: 120 | U82: -498514.16 | V82: -5086.88 | W82: =-$S82/$T82 -> -5086.875 | X82: =-$S82/$T82 -> -5086.875 | Y82: =-$S82/$T82 -> -5086.875 | Z82: =-$S82/$T82 -> -5086.875 | AA82: =-$S82/$T82 -> -5086.875 | AB82: =-$S82/$T82 -> -5086.875 | AC82: =-$S82/$T82 -> -5086.875 | AD82: =-$S82/$T82 -> -5086.875 | AE82: 0 | AF82: 0 | AG82: 0 | AH82: =SUM(V82:AG82) -> -45781.88 | AI82: 0 | AJ82: =U82+AH82+AI82 -> -544296.04 | AL82: =S82+AJ82 -> 66128.955 | AM82: =P82+U82 -> 111910.84
A83: 42457 | C83: PM-00117B01-16 | D83: COMPRESSOR: 2HP; MODEL: PC 2AC; BRAND: VIP | F83: TAMPOI | G83: BAGMAKE | H83: General | N83: 1 | O83: Unit | P83: 10080 | Q83: 0 | R83: 0 | S83: =SUM(P83:R83) -> 10080 | T83: 120 | U83: -8232 | V83: -84 | W83: =-$S83/$T83 -> -84 | X83: =-$S83/$T83 -> -84 | Y83: =-$S83/$T83 -> -84 | Z83: =-$S83/$T83 -> -84 | AA83: =-$S83/$T83 -> -84 | AB83: =-$S83/$T83 -> -84 | AC83: =-$S83/$T83 -> -84 | AD83: =-$S83/$T83 -> -84 | AE83: 0 | AF83: 0 | AG83: 0 | AH83: =SUM(V83:AG83) -> -756 | AI83: 0 | AJ83: =U83+AH83+AI83 -> -8988 | AL83: =S83+AJ83 -> 1092 | AM83: =P83+U83 -> 1848
A84: 42540 | C84: PM-00117B02-16 | D84: MODEL : JD-300-30mm, 240 VOLT, 50Hz | F84: TAMPOI | G84: BAGMAKE | H84: General | N84: 1 | O84: Unit | P84: 15498 | Q84: 0 | R84: 0 | S84: =SUM(P84:R84) -> 15498 | T84: 60 | U84: -15498 | V84: 0 | W84: 0 | X84: 0 | Y84: 0 | Z84: 0 | AA84: 0 | AB84: 0 | AC84: 0 | AD84: 0 | AE84: 0 | AF84: 0 | AG84: 0 | AH84: =SUM(V84:AG84) -> 0 | AI84: 0 | AJ84: =U84+AH84+AI84 -> -15498 | AL84: =S84+AJ84 -> 0 | AM84: =P84+U84 -> 0
A85: 42536 | C85: PM-00117B03-16 | D85: GC C/W PLATFORM, CAP : 150kg x 10g | F85: TAMPOI | G85: BAGMAKE | H85: General | N85: 1 | O85: Unit | P85: 1980 | Q85: 0 | R85: 0 | S85: =SUM(P85:R85) -> 1980 | T85: 36 | U85: -1980 | V85: 0 | W85: 0 | X85: 0 | Y85: 0 | Z85: 0 | AA85: 0 | AB85: 0 | AC85: 0 | AD85: 0 | AE85: 0 | AF85: 0 | AG85: 0 | AH85: =SUM(V85:AG85) -> 0 | AI85: 0 | AJ85: =U85+AH85+AI85 -> -1980 | AL85: =S85+AJ85 -> 0 | AM85: =P85+U85 -> 0
A86: 42549 | C86: PM-00117C01-16 | D86: BM 7 | F86: TAMPOI | G86: BAGMAKE | H86: General | N86: 2 | O86: Unit | P86: 2399.7 | Q86: 0 | R86: 0 | S86: =SUM(P86:R86) -> 2399.7 | T86: 120 | U86: -1959.9775 | V86: -20 | W86: =-$S86/$T86 -> -19.9975 | X86: =-$S86/$T86 -> -19.9975 | Y86: =-$S86/$T86 -> -19.9975 | Z86: =-$S86/$T86 -> -19.9975 | AA86: =-$S86/$T86 -> -19.9975 | AB86: =-$S86/$T86 -> -19.9975 | AC86: =-$S86/$T86 -> -19.9975 | AD86: =-$S86/$T86 -> -19.9975 | AE86: 0 | AF86: 0 | AG86: 0 | AH86: =SUM(V86:AG86) -> -179.98 | AI86: 0 | AJ86: =U86+AH86+AI86 -> -2139.9575 | AL86: =S86+AJ86 -> 259.7425 | AM86: =P86+U86 -> 439.7225
A87: 42522 | C87: PM-00117C02-16 | D87: TO SUPPLY MANPOWER, TOOLS, FORKLIFT, LORRY CRANE AND MOBILE CRANE | F87: TAMPOI | G87: BAGMAKE | H87: General | L87: Installation | N87: 2 | O87: Unit | P87: 6900 | Q87: 0 | R87: 0 | S87: =SUM(P87:R87) -> 6900 | T87: 120 | U87: -5635 | V87: -57.5 | W87: =-$S87/$T87 -> -57.5 | X87: =-$S87/$T87 -> -57.5 | Y87: =-$S87/$T87 -> -57.5 | Z87: =-$S87/$T87 -> -57.5 | AA87: =-$S87/$T87 -> -57.5 | AB87: =-$S87/$T87 -> -57.5 | AC87: =-$S87/$T87 -> -57.5 | AD87: =-$S87/$T87 -> -57.5 | AE87: 0 | AF87: 0 | AG87: 0 | AH87: =SUM(V87:AG87) -> -517.5 | AI87: 0 | AJ87: =U87+AH87+AI87 -> -6152.5 | AL87: =S87+AJ87 -> 747.5 | AM87: =P87+U87 -> 1265
A88: 42543 | C88: PM-00117C03-16 | D88: SEIKI TAPPING MACHINE | F88: TAMPOI | G88: BAGMAKE | H88: General | N88: 1 | O88: Unit | P88: 448.11 | Q88: 0 | R88: 0 | S88: =SUM(P88:R88) -> 448.11 | T88: 60 | U88: -448.11 | V88: 0 | W88: 0 | X88: 0 | Y88: 0 | Z88: 0 | AA88: 0 | AB88: 0 | AC88: 0 | AD88: 0 | AE88: 0 | AF88: 0 | AG88: 0 | AH88: =SUM(V88:AG88) -> 0 | AI88: 0 | AJ88: =U88+AH88+AI88 -> -448.11 | AL88: =S88+AJ88 -> 0 | AM88: =P88+U88 -> 0
A89: 42515 | C89: PM-00124A01-16 | D89: (TWO LINES), FLAT BOTTOM POUCH WITH ZIPPER (TWO LINE) POUCH MAKING MACHINE | F89: TAMPOI | G89: BAGMAKE | H89: BM 6 | N89: 1 | O89: Unit | P89: 1953360 | Q89: 0 | R89: 0 | S89: =SUM(P89:R89) -> 1953360 | T89: 120 | U89: -1578966 | V89: -16278 | W89: =-$S89/$T89 -> -16278 | X89: =-$S89/$T89 -> -16278 | Y89: =-$S89/$T89 -> -16278 | Z89: =-$S89/$T89 -> -16278 | AA89: =-$S89/$T89 -> -16278 | AB89: =-$S89/$T89 -> -16278 | AC89: =-$S89/$T89 -> -16278 | AD89: =-$S89/$T89 -> -16278 | AE89: 0 | AF89: 0 | AG89: 0 | AH89: =SUM(V89:AG89) -> -146502 | AI89: 0 | AJ89: =U89+AH89+AI89 -> -1725468 | AL89: =S89+AJ89 -> 227892 | AM89: =P89+U89 -> 374394
A90: 42473 | C90: PM-00124B01-16 | D90: MODEL : JD-300-30 | F90: TAMPOI | G90: BAGMAKE | H90: General | N90: 1 | O90: Unit | P90: 14555 | Q90: 0 | R90: 0 | S90: =SUM(P90:R90) -> 14555 | T90: 60 | U90: -14555 | V90: 0 | W90: 0 | X90: 0 | Y90: 0 | Z90: 0 | AA90: 0 | AB90: 0 | AC90: 0 | AD90: 0 | AE90: 0 | AF90: 0 | AG90: 0 | AH90: =SUM(V90:AG90) -> 0 | AI90: 0 | AJ90: =U90+AH90+AI90 -> -14555 | AL90: =S90+AJ90 -> 0 | AM90: =P90+U90 -> 0
A91: 42530 | C91: PM-00124B02-16 | D91: MODEL : PC 2AC, COMPRESSOR : 2HP | F91: TAMPOI | G91: BAGMAKE | H91: General | N91: 1 | O91: Unit | P91: 10080 | Q91: 0 | R91: 0 | S91: =SUM(P91:R91) -> 10080 | T91: 120 | U91: -8232 | V91: -84 | W91: =-$S91/$T91 -> -84 | X91: =-$S91/$T91 -> -84 | Y91: =-$S91/$T91 -> -84 | Z91: =-$S91/$T91 -> -84 | AA91: =-$S91/$T91 -> -84 | AB91: =-$S91/$T91 -> -84 | AC91: =-$S91/$T91 -> -84 | AD91: =-$S91/$T91 -> -84 | AE91: 0 | AF91: 0 | AG91: 0 | AH91: =SUM(V91:AG91) -> -756 | AI91: 0 | AJ91: =U91+AH91+AI91 -> -8988 | AL91: =S91+AJ91 -> 1092 | AM91: =P91+U91 -> 1848
A92: 42545 | C92: PM-00124B03-16 | D92: C/W PLATFORM, CAP : 150KG x 10G FOR BM 6 | F92: TAMPOI | G92: BAGMAKE | H92: General | N92: 1 | O92: Unit | P92: 1980 | Q92: 0 | R92: 0 | S92: =SUM(P92:R92) -> 1980 | T92: 36 | U92: -1980 | V92: 0 | W92: 0 | X92: 0 | Y92: 0 | Z92: 0 | AA92: 0 | AB92: 0 | AC92: 0 | AD92: 0 | AE92: 0 | AF92: 0 | AG92: 0 | AH92: =SUM(V92:AG92) -> 0 | AI92: 0 | AJ92: =U92+AH92+AI92 -> -1980 | AL92: =S92+AJ92 -> 0 | AM92: =P92+U92 -> 0
A93: 42549 | C93: PM-00124C01-16 | D93: BM 6 | F93: TAMPOI | G93: BAGMAKE | H93: General | N93: 1 | O93: Unit | P93: 2399.7 | Q93: 0 | R93: 0 | S93: =SUM(P93:R93) -> 2399.7 | T93: 120 | U93: -1959.9775 | V93: -20 | W93: =-$S93/$T93 -> -19.9975 | X93: =-$S93/$T93 -> -19.9975 | Y93: =-$S93/$T93 -> -19.9975 | Z93: =-$S93/$T93 -> -19.9975 | AA93: =-$S93/$T93 -> -19.9975 | AB93: =-$S93/$T93 -> -19.9975 | AC93: =-$S93/$T93 -> -19.9975 | AD93: =-$S93/$T93 -> -19.9975 | AE93: 0 | AF93: 0 | AG93: 0 | AH93: =SUM(V93:AG93) -> -179.98 | AI93: 0 | AJ93: =U93+AH93+AI93 -> -2139.9575 | AL93: =S93+AJ93 -> 259.7425 | AM93: =P93+U93 -> 439.7225
A94: 42522 | C94: PM-00124C02-16 | D94: TO SUPPLY MANPOWER, TOOLS, FORKLIFT, LORRY CRANE AND MOBILE CRANE | F94: TAMPOI | G94: BAGMAKE | H94: General | L94: Installation | N94: 1 | O94: Unit | P94: 6900 | Q94: 0 | R94: 0 | S94: =SUM(P94:R94) -> 6900 | T94: 120 | U94: -5635 | V94: -57.5 | W94: =-$S94/$T94 -> -57.5 | X94: =-$S94/$T94 -> -57.5 | Y94: =-$S94/$T94 -> -57.5 | Z94: =-$S94/$T94 -> -57.5 | AA94: =-$S94/$T94 -> -57.5 | AB94: =-$S94/$T94 -> -57.5 | AC94: =-$S94/$T94 -> -57.5 | AD94: =-$S94/$T94 -> -57.5 | AE94: 0 | AF94: 0 | AG94: 0 | AH94: =SUM(V94:AG94) -> -517.5 | AI94: 0 | AJ94: =U94+AH94+AI94 -> -6152.5 | AL94: =S94+AJ94 -> 747.5 | AM94: =P94+U94 -> 1265
A95: 42856 | C95: PM-00151A01-17 | D95: THREE SIDE SEAL, STAND UP POUCH ZIPPER SEAL POUCH | F95: TAMPOI | G95: BAGMAKE | H95: BM 8 | N95: 1 | O95: UNIT | P95: 699184 | Q95: 0 | R95: 0 | S95: =SUM(P95:R95) -> 699184 | T95: 120 | U95: -489428.55 | V95: -5826.53 | W95: =-$S95/$T95 -> -5826.5333 | X95: =-$S95/$T95 -> -5826.5333 | Y95: =-$S95/$T95 -> -5826.5333 | Z95: =-$S95/$T95 -> -5826.5333 | AA95: =-$S95/$T95 -> -5826.5333 | AB95: =-$S95/$T95 -> -5826.5333 | AC95: =-$S95/$T95 -> -5826.5333 | AD95: =-$S95/$T95 -> -5826.5333 | AE95: 0 | AF95: 0 | AG95: 0 | AH95: =SUM(V95:AG95) -> -52438.797 | AI95: 0 | AJ95: =U95+AH95+AI95 -> -541867.35 | AL95: =S95+AJ95 -> 157316.65 | AM95: =P95+U95 -> 209755.45
A96: 42948 | C96: PM-00151B01-17 | D96: "VIP" BRAND INDUSTRIAL AIR COOL CHILLER FOR COOLING IN SEALING PROCESS | F96: TAMPOI | G96: BAGMAKE | H96: BM 8 | N96: 1 | O96: UNIT | P96: 11800 | Q96: 0 | R96: 0 | S96: =SUM(P96:R96) -> 11800 | T96: 60 | U96: -11800 | V96: 0 | W96: 0 | X96: 0 | Y96: 0 | Z96: 0 | AA96: 0 | AB96: 0 | AC96: 0 | AD96: 0 | AE96: 0 | AF96: 0 | AG96: 0 | AH96: =SUM(V96:AG96) -> 0 | AI96: 0 | AJ96: =U96+AH96+AI96 -> -11800 | AL96: =S96+AJ96 -> 0 | AM96: =P96+U96 -> 0
A97: 42948 | C97: PM-00151B02-17 | D97: GSC COUNTING PLATFORM SCALE | F97: TAMPOI | G97: BAGMAKE | H97: BM 8 | N97: 1 | O97: UNIT | P97: 1900 | Q97: 0 | R97: 0 | S97: =SUM(P97:R97) -> 1900 | T97: 24 | U97: -1900 | V97: 0 | W97: 0 | X97: 0 | Y97: 0 | Z97: 0 | AA97: 0 | AB97: 0 | AC97: 0 | AD97: 0 | AE97: 0 | AF97: 0 | AG97: 0 | AH97: =SUM(V97:AG97) -> 0 | AI97: 0 | AJ97: =U97+AH97+AI97 -> -1900 | AL97: =S97+AJ97 -> 0 | AM97: =P97+U97 -> 0
A98: 42948 | C98: PM-00151B03-17 | D98: SKY COUNTING SCALE | F98: TAMPOI | G98: BAGMAKE | H98: BM 8 | N98: 1 | O98: UNIT | P98: 750 | Q98: 0 | R98: 0 | S98: =SUM(P98:R98) -> 750 | T98: 24 | U98: -750 | V98: 0 | W98: 0 | X98: 0 | Y98: 0 | Z98: 0 | AA98: 0 | AB98: 0 | AC98: 0 | AD98: 0 | AE98: 0 | AF98: 0 | AG98: 0 | AH98: =SUM(V98:AG98) -> 0 | AI98: 0 | AJ98: =U98+AH98+AI98 -> -750 | AL98: =S98+AJ98 -> 0 | AM98: =P98+U98 -> 0
A99: 42856 | C99: PM-00151C01-17 | D99: TRANSPORT CHARGES FOR THREE SIDE SEAL, STAND UP POUCH ZIPPER SEAL POUCH | F99: TAMPOI | G99: BAGMAKE | H99: BM 8 | N99: 1 | O99: UNIT | P99: 2573 | Q99: 0 | R99: 0 | S99: =SUM(P99:R99) -> 2573 | T99: 120 | U99: -1800.975 | V99: -21.44 | W99: =-$S99/$T99 -> -21.441667 | X99: =-$S99/$T99 -> -21.441667 | Y99: =-$S99/$T99 -> -21.441667 | Z99: =-$S99/$T99 -> -21.441667 | AA99: =-$S99/$T99 -> -21.441667 | AB99: =-$S99/$T99 -> -21.441667 | AC99: =-$S99/$T99 -> -21.441667 | AD99: =-$S99/$T99 -> -21.441667 | AE99: 0 | AF99: 0 | AG99: 0 | AH99: =SUM(V99:AG99) -> -192.97333 | AI99: 0 | AJ99: =U99+AH99+AI99 -> -1993.9483 | AL99: =S99+AJ99 -> 579.05167 | AM99: =P99+U99 -> 772.025
A100: 42948 | C100: PM-00151C02-17 | D100: CALIBRATION CERT FOR GSC COUNTING PLATFORM SCALE | F100: TAMPOI | G100: BAGMAKE | H100: BM 8 | N100: 1 | O100: UNIT | P100: 80 | Q100: 0 | R100: 0 | S100: =SUM(P100:R100) -> 80 | T100: 24 | U100: -80 | V100: 0 | W100: 0 | X100: 0 | Y100: 0 | Z100: 0 | AA100: 0 | AB100: 0 | AC100: 0 | AD100: 0 | AE100: 0 | AF100: 0 | AG100: 0 | AH100: =SUM(V100:AG100) -> 0 | AI100: 0 | AJ100: =U100+AH100+AI100 -> -80 | AL100: =S100+AJ100 -> 0 | AM100: =P100+U100 -> 0
A101: 42948 | C101: PM-00151C03-17 | D101: CALIBRATION CERT FOR SKY COUNTING SCALE | F101: TAMPOI | G101: BAGMAKE | H101: BM 8 | N101: 1 | O101: UNIT | P101: 80 | Q101: 0 | R101: 0 | S101: =SUM(P101:R101) -> 80 | T101: 24 | U101: -80 | V101: 0 | W101: 0 | X101: 0 | Y101: 0 | Z101: 0 | AA101: 0 | AB101: 0 | AC101: 0 | AD101: 0 | AE101: 0 | AF101: 0 | AG101: 0 | AH101: =SUM(V101:AG101) -> 0 | AI101: 0 | AJ101: =U101+AH101+AI101 -> -80 | AL101: =S101+AJ101 -> 0 | AM101: =P101+U101 -> 0
A102: 43221 | C102: PM-00151C04-18 | D102: INCOMING POWER SUPPLY FOR BAG MAKING MACHINE | F102: TAMPOI | G102: BAGMAKE | H102: BM 8 | N102: 1 | O102: UNIT | P102: 26173 | Q102: 0 | R102: 0 | S102: =SUM(P102:R102) -> 26173 | T102: 111 | U102: -17448.485 | V102: -235.79 | W102: =-$S102/$T102 -> -235.79279 | X102: =-$S102/$T102 -> -235.79279 | Y102: =-$S102/$T102 -> -235.79279 | Z102: =-$S102/$T102 -> -235.79279 | AA102: =-$S102/$T102 -> -235.79279 | AB102: =-$S102/$T102 -> -235.79279 | AC102: =-$S102/$T102 -> -235.79279 | AD102: =-$S102/$T102 -> -235.79279 | AE102: 0 | AF102: 0 | AG102: 0 | AH102: =SUM(V102:AG102) -> -2122.1323 | AI102: 0 | AJ102: =U102+AH102+AI102 -> -19570.617 | AL102: =S102+AJ102 -> 6602.3825 | AM102: =P102+U102 -> 8724.5149
A103: 43252 | C103: PM-00178A01-18 | D103: THREE SIDE SEAL, STAND UP POUCH, SINGLE-WEB STANDING POUCH, ZIPPER SEAL, FOUR SIDE SEAL BAG MAKING MACHINE (BM 9) | F103: TAMPOI | G103: BAGMAKE | H103: BM 9 | N103: 1 | O103: UNIT | P103: 641184 | Q103: 0 | R103: 0 | S103: =SUM(P103:R103) -> 641184 | T103: 120 | U103: -384710.4 | V103: -5343.2 | W103: =-$S103/$T103 -> -5343.2 | X103: =-$S103/$T103 -> -5343.2 | Y103: =-$S103/$T103 -> -5343.2 | Z103: =-$S103/$T103 -> -5343.2 | AA103: =-$S103/$T103 -> -5343.2 | AB103: =-$S103/$T103 -> -5343.2 | AC103: =-$S103/$T103 -> -5343.2 | AD103: =-$S103/$T103 -> -5343.2 | AE103: 0 | AF103: 0 | AG103: 0 | AH103: =SUM(V103:AG103) -> -48088.8 | AI103: 0 | AJ103: =U103+AH103+AI103 -> -432799.2 | AL103: =S103+AJ103 -> 208384.8 | AM103: =P103+U103 -> 256473.6
A104: 43252 | C104: PM-00178C01-18 | D104: HAULAGE CHARGES AND HANDLING CHARGES FOR BAG MAKING MACHINE (BM 9) | F104: TAMPOI | G104: BAGMAKE | H104: BM 9 | N104: 1 | O104: UNIT | P104: 1747.57 | Q104: 0 | R104: 0 | S104: =SUM(P104:R104) -> 1747.57 | T104: 120 | U104: -1048.3477 | V104: -14.56 | W104: =-$S104/$T104 -> -14.563083 | X104: =-$S104/$T104 -> -14.563083 | Y104: =-$S104/$T104 -> -14.563083 | Z104: =-$S104/$T104 -> -14.563083 | AA104: =-$S104/$T104 -> -14.563083 | AB104: =-$S104/$T104 -> -14.563083 | AC104: =-$S104/$T104 -> -14.563083 | AD104: =-$S104/$T104 -> -14.563083 | AE104: 0 | AF104: 0 | AG104: 0 | AH104: =SUM(V104:AG104) -> -131.06467 | AI104: 0 | AJ104: =U104+AH104+AI104 -> -1179.4124 | AL104: =S104+AJ104 -> 568.15758 | AM104: =P104+U104 -> 699.22225
A105: 43252 | C105: PM-00178C02-18 | D105: RENTAL CHARGES FOR MOBILE CRANE, LORRY CRANE, FORKLIFT, AND LABOURS AND TOOLS WITH EQUIPMENT FOR BAG MAKING MACHINE (BM 9) | F105: TAMPOI | G105: BAGMAKE | H105: BM 9 | L105: Installation | N105: 1 | O105: UNIT | P105: 9000 | Q105: 0 | R105: 0 | S105: =SUM(P105:R105) -> 9000 | T105: 120 | U105: -5400 | V105: -75 | W105: =-$S105/$T105 -> -75 | X105: =-$S105/$T105 -> -75 | Y105: =-$S105/$T105 -> -75 | Z105: =-$S105/$T105 -> -75 | AA105: =-$S105/$T105 -> -75 | AB105: =-$S105/$T105 -> -75 | AC105: =-$S105/$T105 -> -75 | AD105: =-$S105/$T105 -> -75 | AE105: 0 | AF105: 0 | AG105: 0 | AH105: =SUM(V105:AG105) -> -675 | AI105: 0 | AJ105: =U105+AH105+AI105 -> -6075 | AL105: =S105+AJ105 -> 2925 | AM105: =P105+U105 -> 3600
A106: 43252 | C106: PM-00179A01-18 | D106: HIGH SPEED THREE SIDE SEAL, INSERTED BOTTOM GUSSET STAND-UP WITH OPTIONAL ZIPPER POUCH MAKING MACHINE (BM 10) | F106: TAMPOI | G106: BAGMAKE | H106: BM 10 | N106: 1 | O106: UNIT | P106: 480888 | Q106: 0 | R106: 0 | S106: =SUM(P106:R106) -> 480888 | T106: 120 | U106: -288532.8 | V106: -4007.4 | W106: =-$S106/$T106 -> -4007.4 | X106: =-$S106/$T106 -> -4007.4 | Y106: =-$S106/$T106 -> -4007.4 | Z106: =-$S106/$T106 -> -4007.4 | AA106: =-$S106/$T106 -> -4007.4 | AB106: =-$S106/$T106 -> -4007.4 | AC106: =-$S106/$T106 -> -4007.4 | AD106: =-$S106/$T106 -> -4007.4 | AE106: 0 | AF106: 0 | AG106: 0 | AH106: =SUM(V106:AG106) -> -36066.6 | AI106: 0 | AJ106: =U106+AH106+AI106 -> -324599.4 | AL106: =S106+AJ106 -> 156288.6 | AM106: =P106+U106 -> 192355.2
A107: 43252 | C107: PM-00179C01-18 | D107: HAULAGE CHARGES AND HANDLING CHARGES FOR BAG MAKING MACHINE (BM 10) | F107: TAMPOI | G107: BAGMAKE | H107: BM 10 | N107: 1 | O107: UNIT | P107: 1747.57 | Q107: 0 | R107: 0 | S107: =SUM(P107:R107) -> 1747.57 | T107: 120 | U107: -1048.3477 | V107: -14.56 | W107: =-$S107/$T107 -> -14.563083 | X107: =-$S107/$T107 -> -14.563083 | Y107: =-$S107/$T107 -> -14.563083 | Z107: =-$S107/$T107 -> -14.563083 | AA107: =-$S107/$T107 -> -14.563083 | AB107: =-$S107/$T107 -> -14.563083 | AC107: =-$S107/$T107 -> -14.563083 | AD107: =-$S107/$T107 -> -14.563083 | AE107: 0 | AF107: 0 | AG107: 0 | AH107: =SUM(V107:AG107) -> -131.06467 | AI107: 0 | AJ107: =U107+AH107+AI107 -> -1179.4124 | AL107: =S107+AJ107 -> 568.15758 | AM107: =P107+U107 -> 699.22225
A108: 43252 | C108: PM-00179C02-18 | D108: RENTAL CHARGES FOR MOBILE CRANE, LORRY CRANE, FORKLIFT, AND LABOURS AND TOOLS WITH EQUIPMENT FOR BAG MAKING MACHINE (BM 10) | F108: TAMPOI | G108: BAGMAKE | H108: BM 10 | L108: Installation | N108: 1 | O108: UNIT | P108: 9000 | Q108: 0 | R108: 0 | S108: =SUM(P108:R108) -> 9000 | T108: 120 | U108: -5400 | V108: -75 | W108: =-$S108/$T108 -> -75 | X108: =-$S108/$T108 -> -75 | Y108: =-$S108/$T108 -> -75 | Z108: =-$S108/$T108 -> -75 | AA108: =-$S108/$T108 -> -75 | AB108: =-$S108/$T108 -> -75 | AC108: =-$S108/$T108 -> -75 | AD108: =-$S108/$T108 -> -75 | AE108: 0 | AF108: 0 | AG108: 0 | AH108: =SUM(V108:AG108) -> -675 | AI108: 0 | AJ108: =U108+AH108+AI108 -> -6075 | AL108: =S108+AJ108 -> 2925 | AM108: =P108+U108 -> 3600
A109: 43282 | C109: PM-00183A01-18 | D109: 60HP SCREW WATER COOLED CHILLER FOR METZ 1&3 | F109: TAMPOI | G109: METZ | H109: GENERAL | N109: 1 | O109: UNIT | P109: 30000 | Q109: 0 | R109: 0 | S109: =SUM(P109:R109) -> 30000 | T109: 24 | U109: -30000 | V109: 0 | W109: 0 | X109: 0 | Y109: 0 | Z109: 0 | AA109: 0 | AB109: 0 | AC109: 0 | AD109: 0 | AE109: 0 | AF109: 0 | AG109: 0 | AH109: =SUM(V109:AG109) -> 0 | AI109: 0 | AJ109: =U109+AH109+AI109 -> -30000 | AL109: =S109+AJ109 -> 0 | AM109: =P109+U109 -> 0
A110: 44348 | C110: PM-00183C03-21 | D110: TO SUPPLY AND INSTALL STACK COPPER TUBINGS FOR METZ 1 CHILLER | F110: TAMPOI | G110: METZ | H110: METZ 1 | L110: Installation | N110: 1 | O110: UNIT | P110: 40000 | Q110: 0 | R110: 0 | S110: =SUM(P110:R110) -> 40000 | T110: 120 | U110: -12109.917 | V110: -333.33 | W110: =-$S110/$T110 -> -333.33333 | X110: =-$S110/$T110 -> -333.33333 | Y110: =-$S110/$T110 -> -333.33333 | Z110: =-$S110/$T110 -> -333.33333 | AA110: =-$S110/$T110 -> -333.33333 | AB110: =-$S110/$T110 -> -333.33333 | AC110: =-$S110/$T110 -> -333.33333 | AD110: =-$S110/$T110 -> -333.33333 | AE110: 0 | AF110: 0 | AG110: 0 | AH110: =SUM(V110:AG110) -> -2999.9967 | AI110: 0 | AJ110: =U110+AH110+AI110 -> -15109.913 | AL110: =S110+AJ110 -> 24890.087 | AM110: =P110+U110 -> 27890.083 | AN110: =-(R110+AI110) -> 0
A111: 43344 | C111: PM-00185B01-18 | D111: SCANNING THICKNESS GAUGE FOR TAMPOI CPP 1 PM92-002 | F111: TAMPOI | G111: CPP | H111: CPP 1 | N111: 1 | O111: UNIT | P111: 349435.5 | Q111: 0 | R111: 0 | S111: =SUM(P111:R111) -> 349435.5 | T111: 120 | U111: -116478.42 | V111: -2911.96 | W111: =-$S111/$T111 -> -2911.9625 | X111: =-$S111/$T111 -> -2911.9625 | Y111: =-$S111/$T111 -> -2911.9625 | Z111: =-$S111/$T111 -> -2911.9625 | AA111: =-$S111/$T111 -> -2911.9625 | AB111: =-$S111/$T111 -> -2911.9625 | AC111: =-$S111/$T111 -> -2911.9625 | AD111: =-$S111/$T111 -> -2911.9625 | AE111: 0 | AF111: 0 | AG111: 0 | AH111: =SUM(V111:AG111) -> -26207.66 | AI111: 0 | AJ111: =U111+AH111+AI111 -> -142686.08 | AL111: =S111+AJ111 -> 206749.42 | AM111: =P111+U111 -> 232957.08
...

Sheet EF
A1: =[33]LAND!A1 -> TOMYPAK FLEXIBLE PACKAGING SDN BHD
A2: =[33]LAND!A2 -> FOR THE YEAR ENDED 30 JUNE 2025 | F2: BASED ON SAP
A3: ELECTRICAL FITTINGS | F3: NOT YET PAY/ NOT FULLY PAY
A4: 11101-008 | B4: 45473 | F4: PV NOT SIGNED | AL4: Closing | AM4: Opening
A5: Acquisition Date | B5: Disposal Date | C5: F/A Code | D5: F/A Description | E5: Suppliers | F5: Cost Ctr. 1 | G5: Cost Ctr. 2 | H5: Cost Ctr. 3 | I5: Purchase Order | J5: NO. | K5: Invoice No. | L5: Remarks | M5: Quantity | O5: Cost c/f | P5: Addition | Q5: Disposal/ Written off | R5: Cost b/f | T5: Months | U5: Acc Depn b/f | V5: Jul | W5: Aug | X5: Sept | Y5: Oct | Z5: Nov | AA5: Dec | AB5: Jan | AC5: Feb | AD5: Mar | AE5: Apr | AF5: May | AG5: Jun | AH5: Current Year Depn | AI5: Disposal/ Written off | AJ5: Acc Depn c/f | AL5: =FBT!AA5 -> NBV As At 30/06/2025 | AM5: =FBT!AB5 -> NBV As At 30/06/2024
A6: 42795 | C6: EF-00006A01-17 | D6: REPLACE CAPACITOR BANK | F6: TAMPOI | G6: CORPORAT | H6: General | M6: 1 | N6: UNIT | O6: 86130 | P6: 0 | Q6: 0 | R6: =SUM(O6:Q6) -> 86130 | T6: 60 | U6: -86130 | V6: 0 | W6: 0 | X6: 0 | Y6: 0 | Z6: 0 | AA6: 0 | AB6: 0 | AC6: 0 | AD6: 0 | AE6: 0 | AF6: 0 | AG6: 0 | AH6: =SUM(V6:AG6) -> 0 | AI6: 0 | AJ6: =U6+AH6+AI6 -> -86130 | AL6: =R6+AJ6 -> 0 | AM6: =O6+U6 -> 0
A7: 42856 | C7: EF-00008A01-17 | D7: 8" 18W LED LIGHTING (GUARDHOUSE) | F7: SENAI | G7: HR | H7: General | L7: Installation | M7: 1 | N7: UNIT | O7: 1320 | P7: 0 | Q7: 0 | R7: =SUM(O7:Q7) -> 1320 | T7: 60 | U7: -1320 | V7: 0 | W7: 0 | X7: 0 | Y7: 0 | Z7: 0 | AA7: 0 | AB7: 0 | AC7: 0 | AD7: 0 | AE7: 0 | AF7: 0 | AG7: 0 | AH7: =SUM(V7:AG7) -> 0 | AI7: 0 | AJ7: =U7+AH7+AI7 -> -1320 | AL7: =R7+AJ7 -> 0 | AM7: =O7+U7 -> 0
A8: 43466 | C8: EF-00021A01-19 | D8: ELECTICAL WORK AT BLK 4 FOR 2 UNITS OF NEW LIMAX BAG MAKING MACHINE INCLUDING PVC CABLE, TRUNKING C/W SUPPLY BRACKET, C/W TERMINATION 60A 3P ISOLATOR AND PVC CABLE IN GI CONDUIT FOR WATER PUMP RECYCLING C/W TERMINATION | F8: SENAI | G8: BAGMAKE | H8: SBM01 | L8: Installation | M8: 1 | N8: UNIT | O8: 12469.21 | P8: 0 | Q8: 0 | R8: =SUM(O8:Q8) -> 12469.21 | T8: 120 | U8: -6858.0607 | V8: -103.91 | W8: =-$R8/$T$12 -> -103.91008 | X8: =-$R8/$T$12 -> -103.91008 | Y8: =-$R8/$T$12 -> -103.91008 | Z8: =-$R8/$T$12 -> -103.91008 | AA8: =-$R8/$T$12 -> -103.91008 | AB8: =-$R8/$T$12 -> -103.91008 | AC8: =-$R8/$T$12 -> -103.91008 | AD8: =-$R8/$T$12 -> -103.91008 | AE8: 0 | AF8: 0 | AG8: 0 | AH8: =SUM(V8:AG8) -> -935.19067 | AI8: 0 | AJ8: =U8+AH8+AI8 -> -7793.2514 | AL8: =R8+AJ8 -> 4675.9586 | AM8: =O8+U8 -> 5611.1492
A9: 43466 | C9: EF-00022A01-19 | D9: ELECTICAL WORK AT BLK 4 FOR 2 UNITS OF EXISTING BAGMAKING MACHINE INCLUDING LABOUR, TOOLS AND EQUIPMENT TO DISMATLE EXISTING CABLE, INSTALL NEW CABLE AND GI TRUNKING SUPPORT BRACKET, STUD ROD, COUPLING PLATES, SS NUT & BOLT, WASHERS | F9: SENAI | G9: BAGMAKE | H9: GENERAL | L9: Installation | M9: 1 | N9: UNIT | O9: 5030.79 | P9: 0 | Q9: 0 | R9: =SUM(O9:Q9) -> 5030.79 | T9: 120 | U9: -2766.7492 | V9: -41.92 | W9: =-$R9/$T$12 -> -41.92325 | X9: =-$R9/$T$12 -> -41.92325 | Y9: =-$R9/$T$12 -> -41.92325 | Z9: =-$R9/$T$12 -> -41.92325 | AA9: =-$R9/$T$12 -> -41.92325 | AB9: =-$R9/$T$12 -> -41.92325 | AC9: =-$R9/$T$12 -> -41.92325 | AD9: =-$R9/$T$12 -> -41.92325 | AE9: 0 | AF9: 0 | AG9: 0 | AH9: =SUM(V9:AG9) -> -377.306 | AI9: 0 | AJ9: =U9+AH9+AI9 -> -3144.0552 | AL9: =R9+AJ9 -> 1886.7348 | AM9: =O9+U9 -> 2264.0408
A10: 43678 | C10: EF-00029A01-19 | D10: ELECTRICAL WORK AT BLOK 4 FOR WIRE BENDING MACHINE | F10: SENAI | G10: BAGMAKE | H10: GENERAL | L10: Installation | M10: 1 | N10: UNIT | O10: 1950 | P10: 0 | Q10: 0 | R10: =SUM(O10:Q10) -> 1950 | T10: 120 | U10: -958.75 | V10: -16.25 | W10: =-$R10/$T$12 -> -16.25 | X10: =-$R10/$T$12 -> -16.25 | Y10: =-$R10/$T$12 -> -16.25 | Z10: =-$R10/$T$12 -> -16.25 | AA10: =-$R10/$T$12 -> -16.25 | AB10: =-$R10/$T$12 -> -16.25 | AC10: =-$R10/$T$12 -> -16.25 | AD10: =-$R10/$T$12 -> -16.25 | AE10: 0 | AF10: 0 | AG10: 0 | AH10: =SUM(V10:AG10) -> -146.25 | AI10: 0 | AJ10: =U10+AH10+AI10 -> -1105 | AL10: =R10+AJ10 -> 845 | AM10: =O10+U10 -> 991.25
P11: 0 | Q11: 0 | AI11: 0
A12: 44978 | C12: EF-23-A0100049 | D12: ELECTRICAL WORK FOR NEW QC LAB | E12: S.K.L.A. ENGINEERING SDN. BHD. | F12: TAMPOI | G12: MAINT | H12: GENERAL | I12: 2300110 | J12: DT1246/ DT1299 | K12: INV 23020004/ INV23050002 | L12: Installation | M12: 1 | N12: Unit | O12: 35000 | P12: 0 | Q12: 0 | R12: =SUM(O12:Q12) -> 35000 | T12: 120 | U12: -4958.35 | V12: =-$R12/$T$12 -> -291.66667 | W12: =-$R12/$T$12 -> -291.66667 | X12: =-$R12/$T$12 -> -291.66667 | Y12: =-$R12/$T$12 -> -291.66667 | Z12: =-$R12/$T$12 -> -291.66667 | AA12: =-$R12/$T$12 -> -291.66667 | AB12: =-$R12/$T$12 -> -291.66667 | AC12: =-$R12/$T$12 -> -291.66667 | AD12: =-$R12/$T$12 -> -291.66667 | AE12: 0 | AF12: 0 | AG12: 0 | AH12: =SUM(V12:AG12) -> -2625 | AI12: 0 | AJ12: =U12+AH12+AI12 -> -7583.35 | AL12: =R12+AJ12 -> 27416.65 | AM12: =O12+U12 -> 30041.65
A13: 44988 | C13: EF-23-A0200067 | D13: FOR EXTRUSION LAMINATING TO SUPPLY AND INSTALL FOR EL4 TO SUPPLY AND INSTALL POWER POINT USING 1CX4X4MM + E PVC CABLE IN G.I CONDUIT FOR HOIST C/W | E13: S.K.L.A ENGINEERING SDN BHD | F13: TAMPOI | G13: MAINT | H13: GENERAL | I13: 2201794 | J13: PU49093 | K13: INV.23030005 | L13: Installation | M13: 1 | N13: Unit | O13: 32900 | P13: 0 | Q13: 0 | R13: =SUM(O13:Q13) -> 32900 | T13: 120 | U13: -4386.68 | V13: =-$R13/$T13 -> -274.16667 | W13: =-$R13/$T$12 -> -274.16667 | X13: =-$R13/$T$12 -> -274.16667 | Y13: =-$R13/$T$12 -> -274.16667 | Z13: =-$R13/$T$12 -> -274.16667 | AA13: =-$R13/$T$12 -> -274.16667 | AB13: =-$R13/$T$12 -> -274.16667 | AC13: =-$R13/$T$12 -> -274.16667 | AD13: =-$R13/$T$12 -> -274.16667 | AE13: 0 | AF13: 0 | AG13: 0 | AH13: =SUM(V13:AG13) -> -2467.5 | AI13: 0 | AJ13: =U13+AH13+AI13 -> -6854.18 | AL13: =R13+AJ13 -> 26045.82 | AM13: =O13+U13 -> 28513.32
A14: 45015 | C14: EF-23-A0100050 | D14: ELECTRICAL WORK AT TOMYPAK TAMPOI BLK A | E14: S.K.L.A. ENGINEERING SDN. BHD. | F14: TAMPOI | G14: MAINT | H14: GENERAL | I14: 2201654 | J14: DT1192/ DT1269 | K14: INV22110004/ INV 23030020 | L14: Installation | M14: 1 | N14: Unit | O14: 60000 | P14: 0 | Q14: 0 | R14: =SUM(O14:Q14) -> 60000 | T14: 120 | U14: -8000 | V14: =-$R14/$T14 -> -500 | W14: =-$R14/$T$12 -> -500 | X14: =-$R14/$T$12 -> -500 | Y14: =-$R14/$T$12 -> -500 | Z14: =-$R14/$T$12 -> -500 | AA14: =-$R14/$T$12 -> -500 | AB14: =-$R14/$T$12 -> -500 | AC14: =-$R14/$T$12 -> -500 | AD14: =-$R14/$T$12 -> -500 | AE14: 0 | AF14: 0 | AG14: 0 | AH14: =SUM(V14:AG14) -> -4500 | AI14: 0 | AJ14: =U14+AH14+AI14 -> -12500 | AL14: =R14+AJ14 -> 47500 | AM14: =O14+U14 -> 52000
A15: 45015 | C15: EF-23-A0100051 | D15: ELECTRICAL WORK (TAMPOI) LIGHTNING AND POWER POINT AT BLOCK A | E15: S.K.L.A. ENGINEERING SDN. BHD. | F15: TAMPOI | G15: MAINT | H15: GENERAL | I15: 2201525 | J15: DT1197/ DT1270 | K15: INV22110007/ INV23030017 | L15: Installation | M15: 1 | N15: Unit | O15: 125000 | P15: 0 | Q15: 0 | R15: =SUM(O15:Q15) -> 125000 | T15: 120 | U15: -16666.68 | V15: =-$R15/$T15 -> -1041.6667 | W15: =-$R15/$T$12 -> -1041.6667 | X15: =-$R15/$T$12 -> -1041.6667 | Y15: =-$R15/$T$12 -> -1041.6667 | Z15: =-$R15/$T$12 -> -1041.6667 | AA15: =-$R15/$T$12 -> -1041.6667 | AB15: =-$R15/$T$12 -> -1041.6667 | AC15: =-$R15/$T$12 -> -1041.6667 | AD15: =-$R15/$T$12 -> -1041.6667 | AE15: 0 | AF15: 0 | AG15: 0 | AH15: =SUM(V15:AG15) -> -9375 | AI15: 0 | AJ15: =U15+AH15+AI15 -> -26041.68 | AL15: =R15+AJ15 -> 98958.32 | AM15: =O15+U15 -> 108333.32
A16: 45051 | C16: EF-23-A0100052 | D16: TO SUPPLY AND INSTALL C/W DISMANTLE EXISTING TO SUPPLY AND INSTALL C/W DISMANTLE EXISTING HIGH BAY 100W BLOCK C 1ST FLOOR TO SUPPLY AND INSTALL C/W DISMANTLE EXISTING KELUAR SIGN TO SUPPLY AND INSTALL C/W DISMANTLE EXISTING EL LIGHT TO SUPPLY AND INSTALL C/W DISMANTLE EXISTING 1X18W BARE CHANNEL TO SUPPLY & INSTALL HIGH BAY POINT USING 2X2.5MM+E PVC CABLE IN G.I CONDUIT/TRUNKING C/W METAL SWITCH TO SUPPLY LABOUR TO PAINTING ALL TRUNKING AND G.I CONDUIT C/W MAKE GOOD | E16: S.K.L.A ENGINEERING SDN BHD | F16: TAMPOI | G16: MAINT | H16: GENERAL | I16: 2300327 | J16: PU49830 | K16: INV.23050004 | L16: Installation | M16: 1 | N16: Unit | O16: 38000 | P16: 0 | Q16: 0 | R16: =SUM(O16:Q16) -> 38000 | T16: 120 | U16: -4433.34 | V16: =-$R16/$T16 -> -316.66667 | W16: =-$R16/$T$12 -> -316.66667 | X16: =-$R16/$T$12 -> -316.66667 | Y16: =-$R16/$T$12 -> -316.66667 | Z16: =-$R16/$T$12 -> -316.66667 | AA16: =-$R16/$T$12 -> -316.66667 | AB16: =-$R16/$T$12 -> -316.66667 | AC16: =-$R16/$T$12 -> -316.66667 | AD16: =-$R16/$T$12 -> -316.66667 | AE16: 0 | AF16: 0 | AG16: 0 | AH16: =SUM(V16:AG16) -> -2850 | AI16: 0 | AJ16: =U16+AH16+AI16 -> -7283.34 | AL16: =R16+AJ16 -> 30716.66 | AM16: =O16+U16 -> 33566.66
A17: 45051 | C17: EF-23-A0100053 | D17: TO SUPPLY AND INSTALL POWER POINT USING 1CX4X4MM+E PVC CABLE IN G.I CONDUIT FOR HOIST C/W | E17: S.K.L.A. ENGINEERING SDN. BHD. | F17: TAMPOI | G17: MAINT | H17: GENERAL | I17: 2300269 | J17: DT1244/ DT1302 | K17: INV 23020005/ INV23050005 | L17: Installation | M17: 1 | N17: Unit | O17: 25000 | P17: 0 | Q17: 0 | R17: =SUM(O17:Q17) -> 25000 | T17: 120 | U17: -2916.66 | V17: =-$R17/$T17 -> -208.33333 | W17: =-$R17/$T$12 -> -208.33333 | X17: =-$R17/$T$12 -> -208.33333 | Y17: =-$R17/$T$12 -> -208.33333 | Z17: =-$R17/$T$12 -> -208.33333 | AA17: =-$R17/$T$12 -> -208.33333 | AB17: =-$R17/$T$12 -> -208.33333 | AC17: =-$R17/$T$12 -> -208.33333 | AD17: =-$R17/$T$12 -> -208.33333 | AE17: 0 | AF17: 0 | AG17: 0 | AH17: =SUM(V17:AG17) -> -1875 | AI17: 0 | AJ17: =U17+AH17+AI17 -> -4791.66 | AL17: =R17+AJ17 -> 20208.34 | AM17: =O17+U17 -> 22083.34
A18: 45090 | C18: EF-23-A0100054 | D18: PERMOHONAN BEKALAN ELEKTRIK TAMBAHAN KE KILANG SEDIADA TO SUPPLY & LAY FOR HORIZONTAL DIRECT DRILLING (HDD) WORKS FOR 1 NOS 150MM DIA HDPE PN10 PIPE TO FOLLOW TNB SPECIFICATIONS C/W END LAUNCHING,RECEIVING PIT,MAKING GOOD TO EXISTING PREMIX/GRASS ROADS MOBILLSATION & DEMOBILLSATION C/W CLEARING HOUSEKEEPING OF ALL THE WORKS SPACES AND TRAFFIC MANAGEMENT DURING THE HDD WORKS PROJECT INSURANCE 3RD PARTY DAMAGE AND ETC TO PREPARE DOCUMENTS TO TNB SUCH AS VENDOR CERTIFICATE,KAD KELAYAKAN TEKNIKAL (KKT) & ALL RELATED DOCUMENTS TO OBTAIN ARAHAN MULA KERJA (AMK) INCLUSIVE TO DO LIVE TRACING WITH TNB STAFF To LIAISE ALL AUTHORITIES INVOLVED ON THE ROUTE/ARRANGEMENT/APPROVAL/PERMIT ISSUANCE SUCH AS KUI,JKR,MAJLIS,TELEKOM MALAYSIA & ETC ALSO TO GET BACK SECURITY DEPOSIT FROM AUTHORTIES AFTER COMPLETION WO | E18: BIO BRILLIANT SDN BHD | F18: TAMPOI | G18: MAINT | H18: GENERAL | I18: 2201536 | J18: PU50258 | K18: BBSB/INV-23/06/06 | L18: Installation | M18: 1 | N18: Unit | O18: 290000 | P18: 0 | Q18: 0 | R18: =SUM(O18:Q18) -> 290000 | T18: 120 | U18: -31416.67 | V18: =-$R18/$T18 -> -2416.6667 | W18: =-$R18/$T$12 -> -2416.6667 | X18: =-$R18/$T$12 -> -2416.6667 | Y18: =-$R18/$T$12 -> -2416.6667 | Z18: =-$R18/$T$12 -> -2416.6667 | AA18: =-$R18/$T$12 -> -2416.6667 | AB18: =-$R18/$T$12 -> -2416.6667 | AC18: =-$R18/$T$12 -> -2416.6667 | AD18: =-$R18/$T$12 -> -2416.6667 | AE18: 0 | AF18: 0 | AG18: 0 | AH18: =SUM(V18:AG18) -> -21750 | AI18: 0 | AJ18: =U18+AH18+AI18 -> -53166.67 | AL18: =R18+AJ18 -> 236833.33 | AM18: =O18+U18 -> 258583.33
A19: 45092 | C19: EF-23-A0100056 | D19: ELECTRICAL WORK AT TAMPOI BLOCK C | E19: S.K.L.A. ENGINEERING SDN. BHD. | F19: TAMPOI | G19: MAINT | H19: GENERAL | I19: 2300645 | J19: DT1316/ DT1334 | K19: INV 23060017/ INV 23060019 | L19: Installation | M19: 1 | N19: Unit | O19: 40000 | P19: 0 | Q19: 0 | R19: =SUM(O19:Q19) -> 40000 | T19: 120 | U19: -4333.3267 | V19: =-333.33*3 -> -999.99 | W19: =-$R19/$T$12 -> -333.33333 | X19: =-$R19/$T$12 -> -333.33333 | Y19: =-$R19/$T$12 -> -333.33333 | Z19: =-$R19/$T$12 -> -333.33333 | AA19: =-$R19/$T$12 -> -333.33333 | AB19: =-$R19/$T$12 -> -333.33333 | AC19: =-$R19/$T$12 -> -333.33333 | AD19: =-$R19/$T$12 -> -333.33333 | AE19: 0 | AF19: 0 | AG19: 0 | AH19: =SUM(V19:AG19) -> -3666.6567 | AI19: 0 | AJ19: =U19+AH19+AI19 -> -7999.9833 | AL19: =R19+AJ19 -> 32000.017 | AM19: =O19+U19 -> 35666.673
P20: 0 | Q20: 0 | AI20: 0
A21: 45113 | C21: EF-23-A0100057 | D21: ELECTRICAL WORK (TAMPOI) - CABLING TO MACHINE PANEL | E21: S.K.L.A. ENGINEERING SDN. BHD. | F21: TAMPOI | G21: MAINT | H21: GENERAL | I21: 2201336 | J21: DT1126/ DT1207/ DT1260/ PU50846 | K21: INV 22090002 | L21: Installation | M21: 1 | N21: Unit | O21: 1120000 | P21: 0 | Q21: 0 | R21: =SUM(O21:Q21) -> 1120000 | T21: 120 | U21: -112000 | V21: =-$R21/$T21 -> -9333.3333 | W21: =-$R21/$T$12 -> -9333.3333 | X21: =-$R21/$T$12 -> -9333.3333 | Y21: =-$R21/$T$12 -> -9333.3333 | Z21: =-$R21/$T$12 -> -9333.3333 | AA21: =-$R21/$T$12 -> -9333.3333 | AB21: =-$R21/$T$12 -> -9333.3333 | AC21: =-$R21/$T$12 -> -9333.3333 | AD21: =-$R21/$T$12 -> -9333.3333 | AE21: 0 | AF21: 0 | AG21: 0 | AH21: =SUM(V21:AG21) -> -84000 | AI21: 0 | AJ21: =U21+AH21+AI21 -> -196000 | AL21: =R21+AJ21 -> 924000 | AM21: =O21+U21 -> 1008000
A22: 45113 | C22: EF-23-A0300068 | D22: CABLE DUCTING NEW HSM TANDEM EL3 | E22: S.K.L.A. ENGINEERING SDN. BHD. | F22: TAMPOI | G22: MAINT | H22: GENERAL | I22: 2300362 | J22: DT1261/ PU51241 | K22: INV23030013/ (PO)23070006 | L22: Installation | M22: 1 | N22: Unit | O22: 33800 | P22: 0 | Q22: 0 | R22: =SUM(O22:Q22) -> 33800 | T22: 120 | U22: -3380 | V22: =-$R22/$T22 -> -281.66667 | W22: =-$R22/$T$12 -> -281.66667 | X22: =-$R22/$T$12 -> -281.66667 | Y22: =-$R22/$T$12 -> -281.66667 | Z22: =-$R22/$T$12 -> -281.66667 | AA22: =-$R22/$T$12 -> -281.66667 | AB22: =-$R22/$T$12 -> -281.66667 | AC22: =-$R22/$T$12 -> -281.66667 | AD22: =-$R22/$T$12 -> -281.66667 | AE22: 0 | AF22: 0 | AG22: 0 | AH22: =SUM(V22:AG22) -> -2535 | AI22: 0 | AJ22: =U22+AH22+AI22 -> -5915 | AL22: =R22+AJ22 -> 27885 | AM22: =O22+U22 -> 30420
A23: 45118 | C23: EF-23-A0100058 | D23: TO UPGRADE TNB INCOMING POWER SUPPLY FROM 3239KW TO 4100KW | E23: KAC PROJECTS SDN BHD | F23: TAMPOI | G23: MAINT | H23: GENERAL | I23: 2201337 | J23: PU50738 | K23: S2858 | L23: Installation | M23: 1 | N23: Unit | O23: 38316.94 | P23: 0 | Q23: 0 | R23: =SUM(O23:Q23) -> 38316.94 | T23: 120 | U23: -3831.694 | V23: =-$R23/$T$12 -> -319.30783 | W23: =-$R23/$T$12 -> -319.30783 | X23: =-$R23/$T$12 -> -319.30783 | Y23: =-$R23/$T$12 -> -319.30783 | Z23: =-$R23/$T$12 -> -319.30783 | AA23: =-$R23/$T$12 -> -319.30783 | AB23: =-$R23/$T$12 -> -319.30783 | AC23: =-$R23/$T$12 -> -319.30783 | AD23: =-$R23/$T$12 -> -319.30783 | AE23: 0 | AF23: 0 | AG23: 0 | AH23: =SUM(V23:AG23) -> -2873.7705 | AI23: 0 | AJ23: =U23+AH23+AI23 -> -6705.4645 | AL23: =R23+AJ23 -> 31611.476 | AM23: =O23+U23 -> 34485.246
A24: 45131 | C24: EF-23-A0100059 | D24: COMPOUND LIGHTING | E24: S.K.L.A ENGINEERING SDN BHD | F24: TAMPOI | G24: MAINT | H24: GENERAL | I24: 2301073 | J24: PU50648 | K24: 23070017 | L24: Installation | M24: 1 | N24: Unit | O24: 31970 | P24: 0 | Q24: 0 | R24: =SUM(O24:Q24) -> 31970 | T24: 120 | U24: -3197 | V24: =-$R24/$T$12 -> -266.41667 | W24: =-$R24/$T$12 -> -266.41667 | X24: =-$R24/$T$12 -> -266.41667 | Y24: =-$R24/$T$12 -> -266.41667 | Z24: =-$R24/$T$12 -> -266.41667 | AA24: =-$R24/$T$12 -> -266.41667 | AB24: =-$R24/$T$12 -> -266.41667 | AC24: =-$R24/$T$12 -> -266.41667 | AD24: =-$R24/$T$12 -> -266.41667 | AE24: 0 | AF24: 0 | AG24: 0 | AH24: =SUM(V24:AG24) -> -2397.75 | AI24: 0 | AJ24: =U24+AH24+AI24 -> -5594.75 | AL24: =R24+AJ24 -> 26375.25 | AM24: =O24+U24 -> 28773
A25: 45189 | C25: EF-23-A0100060 | D25: ESSENTIAL SYSTEM FOR SMOKE FILL FAN AND BLOWER FAN | E25: S.K.L.A. ENGINEERING SDN. BHD. | F25: TAMPOI | G25: MAINT | H25: GENERAL | I25: 2201888 | J25: DT1214/ PU51422 | K25: INV 23010001/ (PO)I-23060317 | L25: Installation | M25: 1 | N25: Unit | O25: 400000 | P25: 0 | Q25: 0 | R25: =SUM(O25:Q25) -> 400000 | T25: 120 | U25: -33333.333 | V25: =-$R25/$T$12 -> -3333.3333 | W25: =-$R25/$T$12 -> -3333.3333 | X25: =-$R25/$T$12 -> -3333.3333 | Y25: =-$R25/$T$12 -> -3333.3333 | Z25: =-$R25/$T$12 -> -3333.3333 | AA25: =-$R25/$T$12 -> -3333.3333 | AB25: =-$R25/$T$12 -> -3333.3333 | AC25: =-$R25/$T$12 -> -3333.3333 | AD25: =-$R25/$T$12 -> -3333.3333 | AE25: 0 | AF25: 0 | AG25: 0 | AH25: =SUM(V25:AG25) -> -30000 | AI25: 0 | AJ25: =U25+AH25+AI25 -> -63333.333 | AL25: =R25+AJ25 -> 336666.67 | AM25: =O25+U25 -> 366666.67
A26: 45189 | C26: EF-23-A0100061 | D26: TO SUPPLY AND INSTALL LIGHTING FITTING FOR BLOCK C GROUND FLOOR SLITTING MACHINE FOR LIGHTING & POWER POINT | E26: S.K.L.A ENGINEERING SDN BHD | F26: TAMPOI | G26: MAINT | H26: GENERAL | I26: 2301072 | J26: PU51604 | K26: 23090011 | L26: Installation | M26: 1 | N26: Unit | O26: 30000 | P26: 0 | Q26: 0 | R26: =SUM(O26:Q26) -> 30000 | T26: 120 | U26: -2500 | V26: =-$R26/$T$12 -> -250 | W26: =-$R26/$T$12 -> -250 | X26: =-$R26/$T$12 -> -250 | Y26: =-$R26/$T$12 -> -250 | Z26: =-$R26/$T$12 -> -250 | AA26: =-$R26/$T$12 -> -250 | AB26: =-$R26/$T$12 -> -250 | AC26: =-$R26/$T$12 -> -250 | AD26: =-$R26/$T$12 -> -250 | AE26: 0 | AF26: 0 | AG26: 0 | AH26: =SUM(V26:AG26) -> -2250 | AI26: 0 | AJ26: =U26+AH26+AI26 -> -4750 | AL26: =R26+AJ26 -> 25250 | AM26: =O26+U26 -> 27500
A27: 45247 | C27: EF-23-A0100062 | D27: ELECTRICAL WORK AT TAMPOI FOR BLOCK C BASEMENT FLOOR | E27: S.K.L.A ENGINEERING SDN BHD | F27: TAMPOI | G27: MAINT | H27: GENERAL | I27: 2301721 | J27: PU52077 | K27: 23110013 | L27: Installation | M27: 1 | N27: Unit | O27: 29500 | P27: 0 | Q27: 0 | R27: =SUM(O27:Q27) -> 29500 | T27: 120 | U27: -1966.6667 | V27: =-$R27/$T$12 -> -245.83333 | W27: =-$R27/$T$12 -> -245.83333 | X27: =-$R27/$T$12 -> -245.83333 | Y27: =-$R27/$T$12 -> -245.83333 | Z27: =-$R27/$T$12 -> -245.83333 | AA27: =-$R27/$T$12 -> -245.83333 | AB27: =-$R27/$T$12 -> -245.83333 | AC27: =-$R27/$T$12 -> -245.83333 | AD27: =-$R27/$T$12 -> -245.83333 | AE27: 0 | AF27: 0 | AG27: 0 | AH27: =SUM(V27:AG27) -> -2212.5 | AI27: 0 | AJ27: =U27+AH27+AI27 -> -4179.1667 | AL27: =R27+AJ27 -> 25320.833 | AM27: =O27+U27 -> 27533.333
A28: 45252 | C28: EF-23-A0100063 | D28: ADDITIONAL LIGHTNING COUNTER AT BLOCK A & C | E28: CBE M&E ENGINEERING SDN BHD | F28: TAMPOI | G28: MAINT | H28: GENERAL | I28: 2301811 | J28: PU52062 | K28: INV2762 | M28: 1 | N28: Unit | O28: 5400 | P28: 0 | Q28: 0 | R28: =SUM(O28:Q28) -> 5400 | T28: 120 | U28: -360 | V28: =-$R28/$T$12 -> -45 | W28: =-$R28/$T$12 -> -45 | X28: =-$R28/$T$12 -> -45 | Y28: =-$R28/$T$12 -> -45 | Z28: =-$R28/$T$12 -> -45 | AA28: =-$R28/$T$12 -> -45 | AB28: =-$R28/$T$12 -> -45 | AC28: =-$R28/$T$12 -> -45 | AD28: =-$R28/$T$12 -> -45 | AE28: 0 | AF28: 0 | AG28: 0 | AH28: =SUM(V28:AG28) -> -405 | AI28: 0 | AJ28: =U28+AH28+AI28 -> -765 | AL28: =R28+AJ28 -> 4635 | AM28: =O28+U28 -> 5040
A29: 45301 | C29: EF-24-A0100065 | D29: TNB SUB-STATION | E29: F-I ENGINEERING SDN BHD | F29: TAMPOI | G29: MAINT | H29: GENERAL | I29: 2301961 | J29: PI52619 | K29: 8003 | M29: 1 | N29: Unit | O29: 15800 | P29: 0 | Q29: 0 | R29: =SUM(O29:Q29) -> 15800 | T29: 120 | U29: -790 | V29: =-$R29/$T$12 -> -131.66667 | W29: =-$R29/$T$12 -> -131.66667 | X29: =-$R29/$T$12 -> -131.66667 | Y29: =-$R29/$T$12 -> -131.66667 | Z29: =-$R29/$T$12 -> -131.66667 | AA29: =-$R29/$T$12 -> -131.66667 | AB29: =-$R29/$T$12 -> -131.66667 | AC29: =-$R29/$T$12 -> -131.66667 | AD29: =-$R29/$T$12 -> -131.66667 | AE29: 0 | AF29: 0 | AG29: 0 | AH29: =SUM(V29:AG29) -> -1185 | AI29: 0 | AJ29: =U29+AH29+AI29 -> -1975 | AL29: =R29+AJ29 -> 13825 | AM29: =O29+U29 -> 15010
A30: 45370 | C30: EF-24-A0100066 | D30: TO SUPPLY AND INSTALL SUB-MAIN CABLE FOR COMPRESSOR USING 4X1C 35MM2 PVC CABLE IN METAL TRUNKING AS FOLLOWING | E30: S.K.L.A ENGINEERING SDN BHD | F30: TAMPOI | G30: MAINT | H30: GENERAL | I30: 2400366 | J30: PU 53377 | K30: 24030002 | L30: Installation | M30: 1 | N30: Unit | O30: 11750 | P30: 0 | Q30: 0 | R30: =SUM(O30:Q30) -> 11750 | T30: 120 | U30: -391.66667 | V30: =-$R30/$T$12 -> -97.916667 | W30: =-$R30/$T$12 -> -97.916667 | X30: =-$R30/$T$12 -> -97.916667 | Y30: =-$R30/$T$12 -> -97.916667 | Z30: =-$R30/$T$12 -> -97.916667 | AA30: =-$R30/$T$12 -> -97.916667 | AB30: =-$R30/$T$12 -> -97.916667 | AC30: =-$R30/$T$12 -> -97.916667 | AD30: =-$R30/$T$12 -> -97.916667 | AE30: 0 | AF30: 0 | AG30: 0 | AH30: =SUM(V30:AG30) -> -881.25 | AI30: 0 | AJ30: =U30+AH30+AI30 -> -1272.9167 | AL30: =R30+AJ30 -> 10477.083 | AM30: =O30+U30 -> 11358.333
A31: 45267 | C31: EF-23-A0100064 | D31: ELECTRICAL WORK AT TAMPOI GROUND FLOOR SLITTING | E31: S.K.L.A. ENGINEERING SDN. BHD. | F31: TAMPOI | G31: MAINT | H31: GENERAL | I31: 2301074 | J31: DT1339/DT1371/DT1396 | K31: INV 23120004 | L31: Installation | M31: 1 | N31: Unit | O31: 320000 | P31: 0 | Q31: 0 | R31: =SUM(O31:Q31) -> 320000 | T31: 120 | U31: 0 | V31: =-$R31/$T$12 -> -2666.6667 | W31: =-$R31/$T$12 -> -2666.6667 | X31: =-$R31/$T$12 -> -2666.6667 | Y31: =-$R31/$T$12 -> -2666.6667 | Z31: =-$R31/$T$12 -> -2666.6667 | AA31: =-$R31/$T$12 -> -2666.6667 | AB31: =-$R31/$T$12 -> -2666.6667 | AC31: =-$R31/$T$12 -> -2666.6667 | AD31: =-$R31/$T$12 -> -2666.6667 | AE31: 0 | AF31: 0 | AG31: 0 | AH31: =SUM(V31:AG31) -> -24000 | AI31: 0 | AJ31: =U31+AH31+AI31 -> -24000 | AL31: =R31+AJ31 -> 296000 | AM31: =O31+U31 -> 320000
A32: 45091 | C32: EF-23-A0100055 | D32: ELECTRICAL WORK AT TAMPOI BLOCK A OUTSIDE ROOF | E32: S.K.L.A. ENGINEERING SDN. BHD. | F32: TAMPOI | G32: MAINT | H32: GENERAL | I32: 2300655 | J32: DT1317/ DT1365 | K32: INV 23060018/ 23080014 | L32: Installation | M32: 1 | N32: Unit | O32: =8400+19600 -> 28000 | P32: 0 | Q32: 0 | R32: =SUM(O32:Q32) -> 28000 | T32: 120 | U32: 0 | V32: =-$R32/$T$12 -> -233.33333 | W32: =-$R32/$T$12 -> -233.33333 | X32: =-$R32/$T$12 -> -233.33333 | Y32: =-$R32/$T$12 -> -233.33333 | Z32: =-$R32/$T$12 -> -233.33333 | AA32: =-$R32/$T$12 -> -233.33333 | AB32: =-$R32/$T$12 -> -233.33333 | AC32: =-$R32/$T$12 -> -233.33333 | AD32: =-$R32/$T$12 -> -233.33333 | AE32: 0 | AF32: 0 | AG32: 0 | AH32: =SUM(V32:AG32) -> -2100 | AI32: 0 | AJ32: =U32+AH32+AI32 -> -2100 | AL32: =R32+AJ32 -> 25900 | AM32: =O32+U32 -> 28000 | AN32: 2300655 | AO32: 28000 | AP32: =O32/AO32 -> 1
O34: =SUM(O6:O33) -> 2817336.9 | P34: =SUM(P6:P33) -> 0 | Q34: =SUM(Q6:Q33) -> 0 | R34: =SUM(R6:R33) -> 2817336.9 | U34: =SUM(U6:U33) -> -336895.63 | V34: =SUM(V6:V33) -> -23415.711 | W34: =SUM(W6:W33) -> -22749.058 | X34: =SUM(X6:X33) -> -22749.058 | Y34: =SUM(Y6:Y33) -> -22749.058 | Z34: =SUM(Z6:Z33) -> -22749.058 | AA34: =SUM(AA6:AA33) -> -22749.058 | AB34: =SUM(AB6:AB33) -> -22749.058 | ... AJ34: =SUM(AJ6:AJ33) -> -542303.8 | AL34: =SUM(AL6:AL33) -> 2275033.1 | AM34: =SUM(AM6:AM33) -> 2480441.3
AH36: In Balance Sheet as at 31/3/25 | AJ36: -542303.8
AJ38: =AJ34-AJ36 -> -0.0011666666
F67: `

Sheet CB
A1: =[32]LAND!A1 -> TOMYPAK FLEXIBLE PACKAGING SDN BHD
A2: =[32]LAND!A2 -> FOR THE YEAR ENDED 30 JUNE 2024 | D2: 45717 | AS2: 51204-003 | AT2: 51206-002
A3: CYLINDER BLOCKS LISTING | AS3: CONSUMABLE MATERIALS | AT3: DEPN - CYLINDER BLOCKS
A4: 11101-007 | AO4: Closing | AP4: Opening
A5: Acquisition Date | B5: Disposal Date | C5: Asset Number | D5: Ref | E5: CB ID. | F5: MATCH DISPOSAL | J5: Location | K5: No. of Col. | L5: PO No. | M5: PU No. | N5: FA Descriptions | O5: Inv No. | P5: Supplier | Q5: Remarks | R5: Cost c/f | S5: Addition | T5: Disposal/ Written off | U5: Cost b/f | W5: Months | X5: Acc Depn b/f | Y5: Jul | Z5: Aug | AA5: Sept | AB5: Oct | AC5: Nov | AD5: Dec | AE5: Jan | AF5: Feb | AG5: Mar | AH5: Apr | AI5: May | AJ5: Jun | AK5: Current Year Depn | AL5: Disposal/ Written off | AM5: =[32]FBT!Y5 -> Acc Depn c/f | AO5: =[33]FBS!AE5 -> NBV As At 30/06/2025 | AP5: =[33]FBS!AF5 -> NBV As At 30/06/2024 | AQ5: Mths | AR5: Capitalise | AS5: Expense off | AT5: Current yr Depreciation
A6: 44593 | C6: 22-0001 | D6: TP/CYL/22/0012 | E6: AJI21/179 | F6: =VLOOKUP(E6,#REF!,2,FALSE) -> #REF! | G6: =VLOOKUP(E6,#REF!,9,FALSE) -> #REF! | H6: =VLOOKUP(E6,#REF!,10,FALSE) -> #REF! | I6: =G6-U6 -> #REF! | J6: AROPAK | K6: 1 | N6: MSG 100G (MANILA) | O6: LSO/MTM/9351 | P6: LIAN SENG | R6: 1355.12 | S6: 0 | T6: 0 | U6: =SUM(R6:T6) -> 1355.12 | W6: 24 | X6: -1355.1233 | Y6: 0 | Z6: 0 | AA6: 0 | AB6: 0 | AC6: 0 | AD6: 0 | AE6: 0 | AF6: 0 | AG6: 0 | AH6: 0 | AI6: 0 | AJ6: 0 | AK6: =SUM(Y6:AJ6) -> 0 | AL6: 0 | AM6: =X6+AK6+AL6 -> -1355.1233 | AO6: =U6+AM6 -> -0.0033333333 | AP6: =R6+X6 -> -0.0033333333
A7: 44593 | C7: 22-0002 | D7: TP/CYL/22/0055 | E7: AJI21/169 | F7: =VLOOKUP(E7,#REF!,2,FALSE) -> #REF! | G7: =VLOOKUP(E7,#REF!,9,FALSE) -> #REF! | H7: =VLOOKUP(E7,#REF!,10,FALSE) -> #REF! | I7: =G7-U7 -> #REF! | J7: AROPAK | K7: 1 | N7: MSG 100G (CEBU) | O7: LSO/MTM/9351 | P7: LIAN SENG | R7: 1355.12 | S7: 0 | T7: 0 | U7: =SUM(R7:T7) -> 1355.12 | W7: 24 | X7: -1355.1233 | Y7: 0 | Z7: 0 | AA7: 0 | AB7: 0 | AC7: 0 | AD7: 0 | AE7: 0 | AF7: 0 | AG7: 0 | AH7: 0 | AI7: 0 | AJ7: 0 | AK7: =SUM(Y7:AJ7) -> 0 | AL7: 0 | AM7: =X7+AK7+AL7 -> -1355.1233 | AO7: =U7+AM7 -> -0.0033333333 | AP7: =R7+X7 -> -0.0033333333
A8: 44593 | C8: 22-0003 | D8: TP/CYL/22/0091 | E8: AJI18/111 | F8: =VLOOKUP(E8,#REF!,2,FALSE) -> #REF! | G8: =VLOOKUP(E8,#REF!,9,FALSE) -> #REF! | H8: =VLOOKUP(E8,#REF!,10,FALSE) -> #REF! | I8: =G8-U8 -> #REF! | J8: AROPAK | K8: 2 | N8: CRISPY FRY 62GM ORIGINAL | O8: LSO/MTM/9355 | P8: LIAN SENG | R8: 3752.69 | S8: 0 | T8: 0 | U8: =SUM(R8:T8) -> 3752.69 | W8: 24 | X8: -3752.6908 | Y8: 0 | Z8: 0 | AA8: 0 | AB8: 0 | AC8: 0 | AD8: 0 | AE8: 0 | AF8: 0 | AG8: 0 | AH8: 0 | AI8: 0 | AJ8: 0 | AK8: =SUM(Y8:AJ8) -> 0 | AL8: 0 | AM8: =X8+AK8+AL8 -> -3752.6908 | AO8: =U8+AM8 -> -0.00083333333 | AP8: =R8+X8 -> -0.00083333333
A9: 44593 | C9: 22-0004 | D9: TP/CYL/22/0114 | E9: AJI18/111 | F9: =VLOOKUP(E9,#REF!,2,FALSE) -> #REF! | G9: =VLOOKUP(E9,#REF!,9,FALSE) -> #REF! | H9: =VLOOKUP(E9,#REF!,10,FALSE) -> #REF! | I9: =G9-U9 -> #REF! | J9: AROPAK | K9: 6 | N9: CRISPY FRY 62GM ORIGINAL | O9: LSO/MTM/9355 | P9: LIAN SENG | R9: 10977.46 | S9: 0 | T9: 0 | U9: =SUM(R9:T9) -> 10977.46 | W9: 24 | X9: -10977.462 | Y9: 0 | Z9: 0 | AA9: 0 | AB9: 0 | AC9: 0 | AD9: 0 | AE9: 0 | AF9: 0 | AG9: 0 | AH9: 0 | AI9: 0 | AJ9: 0 | AK9: =SUM(Y9:AJ9) -> 0 | AL9: 0 | AM9: =X9+AK9+AL9 -> -10977.462 | AO9: =U9+AM9 -> -0.0016666667 | AP9: =R9+X9 -> -0.0016666667
A10: 44593 | C10: 22-0005 | D10: TP/CYL/22/0116 | E10: AJI15/070 | F10: =VLOOKUP(E10,#REF!,2,FALSE) -> #REF! | G10: =VLOOKUP(E10,#REF!,9,FALSE) -> #REF! | H10: =VLOOKUP(E10,#REF!,10,FALSE) -> #REF! | I10: =G10-U10 -> #REF! | J10: AROPAK | K10: 7 | N10: CRISPY FRY 62GM ORIGINAL AGB | O10: LSO/MTM/9355 | P10: LIAN SENG | R10: 10836.74 | S10: 0 | T10: 0 | U10: =SUM(R10:T10) -> 10836.74 | W10: 24 | X10: -10836.738 | Y10: 0 | Z10: 0 | AA10: 0 | AB10: 0 | AC10: 0 | AD10: 0 | AE10: 0 | AF10: 0 | AG10: 0 | AH10: 0 | AI10: 0 | AJ10: 0 | AK10: =SUM(Y10:AJ10) -> 0 | AL10: 0 | AM10: =X10+AK10+AL10 -> -10836.738 | AO10: =U10+AM10 -> 0.0016666667 | AP10: =R10+X10 -> 0.0016666667
A11: 44593 | C11: 22-0006 | D11: TP/CYL/22/0117 | E11: AJI21/173 | F11: =VLOOKUP(E11,#REF!,2,FALSE) -> #REF! | G11: =VLOOKUP(E11,#REF!,9,FALSE) -> #REF! | H11: =VLOOKUP(E11,#REF!,10,FALSE) -> #REF! | I11: =G11-U11 -> #REF! | J11: AROPAK | K11: 7 | N11: SARSAYA 30G - OYSTER SAUCE | O11: LSO/MTM/9355 | P11: LIAN SENG | R11: 10640.52 | S11: 0 | T11: 0 | U11: =SUM(R11:T11) -> 10640.52 | W11: 24 | X11: -10640.52 | Y11: 0 | Z11: 0 | AA11: 0 | AB11: 0 | AC11: 0 | AD11: 0 | AE11: 0 | AF11: 0 | AG11: 0 | AH11: 0 | AI11: 0 | AJ11: 0 | AK11: =SUM(Y11:AJ11) -> 0 | AL11: 0 | AM11: =X11+AK11+AL11 -> -10640.52 | AO11: =U11+AM11 -> 0 | AP11: =R11+X11 -> 0
A12: 44593 | C12: 22-0007 | D12: TP/CYL/22/0094 | E12: AJI21/173 | F12: =VLOOKUP(E12,#REF!,2,FALSE) -> #REF! | G12: =VLOOKUP(E12,#REF!,9,FALSE) -> #REF! | H12: =VLOOKUP(E12,#REF!,10,FALSE) -> #REF! | I12: =G12-U12 -> #REF! | J12: AROPAK | K12: 1 | N12: SARSAYA 30G - OYSTER SAUCE | O12: LSO/MTM/9355 | P12: LIAN SENG | R12: 1613.61 | S12: 0 | T12: 0 | U12: =SUM(R12:T12) -> 1613.61 | W12: 24 | X12: -1613.6075 | Y12: 0 | Z12: 0 | AA12: 0 | AB12: 0 | AC12: 0 | AD12: 0 | AE12: 0 | AF12: 0 | AG12: 0 | AH12: 0 | AI12: 0 | AJ12: 0 | AK12: =SUM(Y12:AJ12) -> 0 | AL12: 0 | AM12: =X12+AK12+AL12 -> -1613.6075 | AO12: =U12+AM12 -> 0.0025 | AP12: =R12+X12 -> 0.0025
A13: 44593 | C13: 22-0008 | D13: TP/CYL/22/0113 | E13: AJI13/039 | F13: =VLOOKUP(E13,#REF!,2,FALSE) -> #REF! | G13: =VLOOKUP(E13,#REF!,9,FALSE) -> #REF! | H13: =VLOOKUP(E13,#REF!,10,FALSE) -> #REF! | I13: =G13-U13 -> #REF! | J13: AROPAK | K13: 7 | N13: CRISPY FRY 30GM-ORIGINAL AGB | O13: LSO/MTM/9354 | P13: LIAN SENG | R13: 11100.19 | S13: 0 | T13: 0 | U13: =SUM(R13:T13) -> 11100.19 | W13: 24 | X13: -11100.189 | Y13: 0 | Z13: 0 | AA13: 0 | AB13: 0 | AC13: 0 | AD13: 0 | AE13: 0 | AF13: 0 | AG13: 0 | AH13: 0 | AI13: 0 | AJ13: 0 | AK13: =SUM(Y13:AJ13) -> 0 | AL13: 0 | AM13: =X13+AK13+AL13 -> -11100.189 | AO13: =U13+AM13 -> 0.00083333333 | AP13: =R13+X13 -> 0.00083333333
A14: 44593 | C14: 22-0009 | D14: TP/CYL/22/0115 | E14: AJI19/123 | F14: =VLOOKUP(E14,#REF!,2,FALSE) -> #REF! | G14: =VLOOKUP(E14,#REF!,9,FALSE) -> #REF! | H14: =VLOOKUP(E14,#REF!,10,FALSE) -> #REF! | I14: =G14-U14 -> #REF! | J14: AROPAK | K14: 7 | N14: CRISPY FRY ORIGINAL 238GM AGB | O14: LSO/MTM/9354 | P14: LIAN SENG | R14: 12081.08 | S14: 0 | T14: 0 | U14: =SUM(R14:T14) -> 12081.08 | W14: 24 | X14: -12081.083 | Y14: 0 | Z14: 0 | AA14: 0 | AB14: 0 | AC14: 0 | AD14: 0 | AE14: 0 | AF14: 0 | AG14: 0 | AH14: 0 | AI14: 0 | AJ14: 0 | AK14: =SUM(Y14:AJ14) -> 0 | AL14: 0 | AM14: =X14+AK14+AL14 -> -12081.083 | AO14: =U14+AM14 -> -0.0033333333 | AP14: =R14+X14 -> -0.0033333333
A15: 44593 | C15: 22-0010 | D15: TP/CYL/22/0090 | E15: AJI13/039 | F15: =VLOOKUP(E15,#REF!,2,FALSE) -> #REF! | G15: =VLOOKUP(E15,#REF!,9,FALSE) -> #REF! | H15: =VLOOKUP(E15,#REF!,10,FALSE) -> #REF! | I15: =G15-U15 -> #REF! | J15: AROPAK | K15: 1 | N15: CRISPY FRY 30GM-ORIGINAL AGB | O15: LSO/MTM/9354 | P15: LIAN SENG | R15: 1679.28 | S15: 0 | T15: 0 | U15: =SUM(R15:T15) -> 1679.28 | W15: 24 | X15: -1679.28 | Y15: 0 | Z15: 0 | AA15: 0 | AB15: 0 | AC15: 0 | AD15: 0 | AE15: 0 | AF15: 0 | AG15: 0 | AH15: 0 | AI15: 0 | AJ15: 0 | AK15: =SUM(Y15:AJ15) -> 0 | AL15: 0 | AM15: =X15+AK15+AL15 -> -1679.28 | AO15: =U15+AM15 -> 0 | AP15: =R15+X15 -> 0
A16: 44593 | C16: 22-0011 | D16: TP/CYL/22/0092 | E16: AJI19/123 | F16: =VLOOKUP(E16,#REF!,2,FALSE) -> #REF! | G16: =VLOOKUP(E16,#REF!,9,FALSE) -> #REF! | H16: =VLOOKUP(E16,#REF!,10,FALSE) -> #REF! | I16: =G16-U16 -> #REF! | J16: AROPAK | K16: 1 | N16: CRISPY FRY ORIGINAL 238GM AGB | O16: LSO/MTM/9354 | P16: LIAN SENG | R16: 1819.41 | S16: 0 | T16: 0 | U16: =SUM(R16:T16) -> 1819.41 | W16: 24 | X16: -1819.4075 | Y16: 0 | Z16: 0 | AA16: 0 | AB16: 0 | AC16: 0 | AD16: 0 | AE16: 0 | AF16: 0 | AG16: 0 | AH16: 0 | AI16: 0 | AJ16: 0 | AK16: =SUM(Y16:AJ16) -> 0 | AL16: 0 | AM16: =X16+AK16+AL16 -> -1819.4075 | AO16: =U16+AM16 -> 0.0025 | AP16: =R16+X16 -> 0.0025
A17: 44593 | C17: 22-0012 | D17: TP/CYL/22/0093 | E17: AJI15/070 | F17: =VLOOKUP(E17,#REF!,2,FALSE) -> #REF! | G17: =VLOOKUP(E17,#REF!,9,FALSE) -> #REF! | H17: =VLOOKUP(E17,#REF!,10,FALSE) -> #REF! | I17: =G17-U17 -> #REF! | J17: AROPAK | K17: 1 | N17: CRISPY FRY 62GM ORIGINAL AGB | O17: LSO/MTM/9354 | P17: LIAN SENG | R17: 1641.65 | S17: 0 | T17: 0 | U17: =SUM(R17:T17) -> 1641.65 | W17: 24 | X17: -1641.6508 | Y17: 0 | Z17: 0 | AA17: 0 | AB17: 0 | AC17: 0 | AD17: 0 | AE17: 0 | AF17: 0 | AG17: 0 | AH17: 0 | AI17: 0 | AJ17: 0 | AK17: =SUM(Y17:AJ17) -> 0 | AL17: 0 | AM17: =X17+AK17+AL17 -> -1641.6508 | AO17: =U17+AM17 -> -0.00083333333 | AP17: =R17+X17 -> -0.00083333333
... A26: 44637 | C26: 22-0023 | D26: TP/CYL/22/0084 | E26: PCO14/063 | F26: =VLOOKUP(E26,#REF!,2,FALSE) -> #REF! | G26: =VLOOKUP(E26,#REF!,9,FALSE) -> #REF! | H26: =VLOOKUP(E26,#REF!,10,FALSE) -> #REF! | I26: =G26-U26 -> #REF! | J26: SEMI CONVERTOR | K26: 6 | N26: PICO STIX CHICKEN F/V 60G -SCI | O26: SINV22-00204 | P26: FUJI ROTO | R26: 4758 | S26: 0 | T26: 0 | U26: =SUM(R26:T26) -> 4758 | W26: 24 | X26: -4758 | Y26: 0 | Z26: 0 | AA26: 0 | AB26: 0 | AC26: 0 | AD26: 0 | AE26: 0 | AF26: 0 | AG26: 0 | AH26: 0 | AI26: 0 | AJ26: 0 | AK26: =SUM(Y26:AJ26) -> 0 | AL26: 0 | AM26: =X26+AK26+AL26 -> -4758 | AO26: =U26+AM26 -> 0 | AP26: =R26+X26 -> 0
A27: 44637 | C27: 22-0024 | D27: TP/CYL/22/0016 | E27: CF12/047 | F27: =VLOOKUP(E27,#REF!,2,FALSE) -> #REF! | G27: =VLOOKUP(E27,#REF!,9,FALSE) -> #REF! | H27: =VLOOKUP(E27,#REF!,10,FALSE) -> #REF! | I27: =G27-U27 -> #REF! | J27: AROPAK | K27: 6 | N27: HARI-HARI SAYANGKU PRAWN | O27: 2202079 | P27: WELL EQUIPPED | R27: 4536 | S27: 0 | T27: 0 | U27: =SUM(R27:T27) -> 4536 | W27: 24 | X27: -4536 | Y27: 0 | Z27: 0 | AA27: 0 | AB27: 0 | AC27: 0 | AD27: 0 | AE27: 0 | AF27: 0 | AG27: 0 | AH27: 0 | AI27: 0 | AJ27: 0 | AK27: =SUM(Y27:AJ27) -> 0 | AL27: 0 | AM27: =X27+AK27+AL27 -> -4536 | AO27: =U27+AM27 -> 0 | AP27: =R27+X27 -> 0
A28: 44637 | C28: 22-0025 | D28: TP/CYL/22/0017 | E28: YNF21/009 | F28: =VLOOKUP(E28,#REF!,2,FALSE) -> #REF! | G28: =VLOOKUP(E28,#REF!,9,FALSE) -> #REF! | H28: =VLOOKUP(E28,#REF!,10,FALSE) -> #REF! | I28: =G28-U28 -> #REF! | J28: AROPAK | K28: 2 | N28: ROLL FOAM - STOK SUP STIMBOT 28G - 1006646 MY | O28: SINV22-00112 | P28: FUJI ROTO | R28: 1344 | S28: 0 | T28: 0 | U28: =SUM(R28:T28) -> 1344 | W28: 24 | X28: -1344 | Y28: 0 | Z28: 0 | AA28: 0 | AB28: 0 | AC28: 0 | AD28: 0 | AE28: 0 | AF28: 0 | AG28: 0 | AH28: 0 | AI28: 0 | AJ28: 0 | AK28: =SUM(Y28:AJ28) -> 0 | AL28: 0 | AM28: =X28+AK28+AL28 -> -1344 | AO28: =U28+AM28 -> 0 | AP28: =R28+X28 -> 0
A29: 44638 | C29: 22-0027 | D29: TP/CYL/22/0082 | E29: PCO06/018 | F29: =VLOOKUP(E29,#REF!,2,FALSE) -> #REF! | G29: =VLOOKUP(E29,#REF!,9,FALSE) -> #REF! | H29: =VLOOKUP(E29,#REF!,10,FALSE) -> #REF! | I29: =G29-U29 -> #REF! | J29: SEMI CONVERTOR | K29: 6 | N29: KOKO SNEK AYAM 60G (NO DATE) - SCI | O29: SINV22-00205 | P29: FUJI ROTO | R29: 4758 | S29: 0 | T29: 0 | U29: =SUM(R29:T29) -> 4758 | W29: 24 | X29: -4758 | Y29: 0 | Z29: 0 | AA29: 0 | AB29: 0 | AC29: 0 | AD29: 0 | AE29: 0 | AF29: 0 | AG29: 0 | AH29: 0 | AI29: 0 | AJ29: 0 | AK29: =SUM(Y29:AJ29) -> 0 | AL29: 0 | AM29: =X29+AK29+AL29 -> -4758 | AO29: =U29+AM29 -> 0 | AP29: =R29+X29 -> 0
A30: 44638 | C30: 22-0028 | D30: TP/CYL/22/0138 | E30: FES16/264 | F30: =VLOOKUP(E30,#REF!,2,FALSE) -> #REF! | G30: =VLOOKUP(E30,#REF!,9,FALSE) -> #REF! | H30: =VLOOKUP(E30,#REF!,10,FALSE) -> #REF! | I30: =G30-U30 -> #REF! | J30: SCIENTEX | K30: 7 | N30: KLASSNO 3IN1 PREMIUM 25G SACHET | O30: SINV22-00350 | P30: FUJI ROTO | R30: 6013.6 | S30: 0 | T30: 0 | U30: =SUM(R30:T30) -> 6013.6 | W30: 24 | X30: -6013.5967 | Y30: 0 | Z30: 0 | AA30: 0 | AB30: 0 | AC30: 0 | AD30: 0 | AE30: 0 | AF30: 0 | AG30: 0 | AH30: 0 | AI30: 0 | AJ30: 0 | AK30: =SUM(Y30:AJ30) -> 0 | AL30: 0 | AM30: =X30+AK30+AL30 -> -6013.5967 | AO30: =U30+AM30 -> 0.0033333333 | AP30: =R30+X30 -> 0.0033333333
A31: 44638 | C31: 22-0029 | D31: TP/CYL/22/0088 | E31: FES18/277 | F31: =VLOOKUP(E31,#REF!,2,FALSE) -> #REF! | G31: =VLOOKUP(E31,#REF!,9,FALSE) -> #REF! | H31: =VLOOKUP(E31,#REF!,10,FALSE) -> #REF! | I31: =G31-U31 -> #REF! | J31: SCIENTEX | K31: 8 | N31: KLASSNO GOLD FREEZE DRIED 3IN1 ORIGINAL 18G SACHET | O31: SINV22-00351 | P31: FUJI ROTO | R31: 7492 | S31: 0 | T31: 0 | U31: =SUM(R31:T31) -> 7492 | W31: 24 | X31: -7491.9967 | Y31: 0 | Z31: 0 | AA31: 0 | AB31: 0 | AC31: 0 | AD31: 0 | AE31: 0 | AF31: 0 | AG31: 0 | AH31: 0 | AI31: 0 | AJ31: 0 | AK31: =SUM(Y31:AJ31) -> 0 | AL31: 0 | AM31: =X31+AK31+AL31 -> -7491.9967 | AO31: =U31+AM31 -> 0.0033333333 | AP31: =R31+X31 -> 0.0033333333
A32: 44638 | C32: 22-0030 | D32: TP/CYL/22/0087 | E32: FES18/279 | F32: =VLOOKUP(E32,#REF!,2,FALSE) -> #REF! | G32: =VLOOKUP(E32,#REF!,9,FALSE) -> #REF! | H32: =VLOOKUP(E32,#REF!,10,FALSE) -> #REF! | I32: =G32-U32 -> #REF! | J32: SCIENTEX | K32: 7 | N32: KLASSNO 3IN1 ORIGINAL 20G SAC | O32: SINV22-00349 | P32: FUJI ROTO | R32: 7450 | S32: 0 | T32: 0 | U32: =SUM(R32:T32) -> 7450 | W32: 24 | X32: -7449.9967 | Y32: 0 | Z32: 0 | AA32: 0 | AB32: 0 | AC32: 0 | AD32: 0 | AE32: 0 | AF32: 0 | AG32: 0 | AH32: 0 | AI32: 0 | AJ32: 0 | AK32: =SUM(Y32:AJ32) -> 0 | AL32: 0 | AM32: =X32+AK32+AL32 -> -7449.9967 | AO32: =U32+AM32 -> 0.0033333333 | AP32: =R32+X32 -> 0.0033333333
A33: 44638 | C33: 22-0031 | D33: TP/CYL/22/0085 | E33: PCO06/006 | F33: =VLOOKUP(E33,#REF!,2,FALSE) -> #REF! | G33: =VLOOKUP(E33,#REF!,9,FALSE) -> #REF! | H33: =VLOOKUP(E33,#REF!,10,FALSE) -> #REF! | I33: =G33-U33 -> #REF! | J33: SEMI CONVERTOR | K33: 6 | N33: PICO P&P PRAWN CRACKERS 60GM - SCI | O33: SINV22-00214 | P33: FUJI ROTO | R33: 4758 | S33: 0 | T33: 0 | U33: =SUM(R33:T33) -> 4758 | W33: 24 | X33: -4758 | Y33: 0 | Z33: 0 | AA33: 0 | AB33: 0 | AC33: 0 | AD33: 0 | AE33: 0 | AF33: 0 | AG33: 0 | AH33: 0 | AI33: 0 | AJ33: 0 | AK33: =SUM(Y33:AJ33) -> 0 | AL33: 0 | AM33: =X33+AK33+AL33 -> -4758 | AO33: =U33+AM33 -> 0 | AP33: =R33+X33 -> 0
A34: 44638 | C34: 22-0032 | D34: TP/CYL/22/0060 | E34: SLG18/019 | F34: =VLOOKUP(E34,#REF!,2,FALSE) -> #REF! | G34: =VLOOKUP(E34,#REF!,9,FALSE) -> #REF! | H34: =VLOOKUP(E34,#REF!,10,FALSE) -> #REF! | I34: =G34-U34 -> #REF! | J34: AROPAK | K34: 9 | N34: KANGAROO GOJI BERRY NUT MIX 30G X 7'S POUCH (AMD#02-21) | O34: SINV22-00333 | P34: FUJI ROTO | R34: 5904 | S34: 0 | T34: 0 | U34: =SUM(R34:T34) -> 5904 | W34: 24 | X34: -5904 | Y34: 0 | Z34: 0 | AA34: 0 | AB34: 0 | AC34: 0 | AD34: 0 | AE34: 0 | AF34: 0 | AG34: 0 | AH34: 0 | AI34: 0 | AJ34: 0 | AK34: =SUM(Y34:AJ34) -> 0 | AL34: 0 | AM34: =X34+AK34+AL34 -> -5904 | AO34: =U34+AM34 -> 0 | AP34: =R34+X34 -> 0
A35: 44638 | C35: 22-0033 | D35: TP/CYL/22/0059 | E35: AK19/001 | F35: =VLOOKUP(E35,#REF!,2,FALSE) -> #REF! | G35: =VLOOKUP(E35,#REF!,9,FALSE) -> #REF! | H35: =VLOOKUP(E35,#REF!,10,FALSE) -> #REF! | I35: =G35-U35 -> #REF! | J35: AROPAK | K35: 7 | N35: AK FISH BALL (AMD#01-21) | O35: SINV22-00273 | P35: FUJI ROTO | R35: 6048 | S35: 0 | T35: 0 | U35: =SUM(R35:T35) -> 6048 | W35: 24 | X35: -6048 | Y35: 0 | Z35: 0 | AA35: 0 | AB35: 0 | AC35: 0 | AD35: 0 | AE35: 0 | AF35: 0 | AG35: 0 | AH35: 0 | AI35: 0 | AJ35: 0 | AK35: =SUM(Y35:AJ35) -> 0 | AL35: 0 | AM35: =X35+AK35+AL35 -> -6048 | AO35: =U35+AM35 -> 0 | AP35: =R35+X35 -> 0
A36: 44638 | C36: 22-0034 | D36: TP/CYL/22/0083 | E36: PCO06/009 | F36: =VLOOKUP(E36,#REF!,2,FALSE) -> #REF! | G36: =VLOOKUP(E36,#REF!,9,FALSE) -> #REF! | H36: =VLOOKUP(E36,#REF!,10,FALSE) -> #REF! | I36: =G36-U36 -> #REF! | J36: SEMI CONVERTOR | K36: 6 | N36: PICO O & O CHEESE RINGS 60G - SCI | O36: SINV22-00213 | P36: FUJI ROTO | R36: 4758 | S36: 0 | T36: 0 | U36: =SUM(R36:T36) -> 4758 | W36: 24 | X36: -4758 | Y36: 0 | Z36: 0 | AA36: 0 | AB36: 0 | AC36: 0 | AD36: 0 | AE36: 0 | AF36: 0 | AG36: 0 | AH36: 0 | AI36: 0 | AJ36: 0 | AK36: =SUM(Y36:AJ36) -> 0 | AL36: 0 | AM36: =X36+AK36+AL36 -> -4758 | AO36: =U36+AM36 -> 0 | AP36: =R36+X36 -> 0
A37: 44651 | C37: 22-0035 | D37: TP/CYL/22/0051 | E37: AJI22/182 | F37: =VLOOKUP(E37,#REF!,2,FALSE) -> #REF! | G37: =VLOOKUP(E37,#REF!,9,FALSE) -> #REF! | H37: =VLOOKUP(E37,#REF!,10,FALSE) -> #REF! | I37: =G37-U37 -> #REF! | J37: HEXACHASE | K37: 6 | N37: FINGER PRINT | O37: LSO/MTM/9345 | P37: LIAN SENG | R37: 9220.37 | S37: 0 | T37: 0 | U37: =SUM(R37:T37) -> 9220.37 | W37: 24 | X37: -9220.3687 | Y37: 0 | Z37: 0 | AA37: 0 | AB37: 0 | AC37: 0 | AD37: 0 | AE37: 0 | AF37: 0 | AG37: 0 | AH37: 0 | AI37: 0 | AJ37: 0 | AK37: =SUM(Y37:AJ37) -> 0 | AL37: 0 | AM37: =X37+AK37+AL37 -> -9220.3687 | AO37: =U37+AM37 -> 0.00125 | AP37: =R37+X37 -> 0.00125
A38: 44651 | C38: 22-0036 | D38: TP/CYL/22/0015 | E38: C&F21/053 | F38: =VLOOKUP(E38,#REF!,2,FALSE) -> #REF! | G38: =VLOOKUP(E38,#REF!,9,FALSE) -> #REF! | H38: =VLOOKUP(E38,#REF!,10,FALSE) -> #REF! | I38: =G38-U38 -> #REF! | J38: AROPAK | K38: 6 | N38: HARI HARI KOKO MORE (NO DATE) | O38: SINV22-00141 | P38: FUJI ROTO | R38: 4838.4 | S38: 0 | T38: 0 | U38: =SUM(R38:T38) -> 4838.4 | W38: 24 | X38: -4838.4 | Y38: 0 | Z38: 0 | AA38: 0 | AB38: 0 | AC38: 0 | AD38: 0 | AE38: 0 | AF38: 0 | AG38: 0 | AH38: 0 | AI38: 0 | AJ38: 0 | AK38: =SUM(Y38:AJ38) -> 0 | AL38: 0 | AM38: =X38+AK38+AL38 -> -4838.4 | AO38: =U38+AM38 -> 0 | AP38: =R38+X38 -> 0
A39: 44651 | C39: 22-0037 | D39: TP/CYL/22/0122 | E39: DCH22/020 | F39: =VLOOKUP(E39,#REF!,2,FALSE) -> #REF! | G39: =VLOOKUP(E39,#REF!,9,FALSE) -> #REF! | H39: =VLOOKUP(E39,#REF!,10,FALSE) -> #REF! | I39: =G39-U39 -> #REF! | J39: AROPAK | K39: 8 | N39: HORLICKS 3IN1 ORIGINAL 10 X 28G HK (AMD#1-21) | O39: 122300359 | P39: JANOSCHKA | R39: 5760 | S39: 0 | T39: 0 | U39: =SUM(R39:T39) -> 5760 | W39: 24 | X39: -5760 | Y39: 0 | Z39: 0 | AA39: 0 | AB39: 0 | AC39: 0 | AD39: 0 | AE39: 0 | AF39: 0 | AG39: 0 | AH39: 0 | AI39: 0 | AJ39: 0 | AK39: =SUM(Y39:AJ39) -> 0 | AL39: 0 | AM39: =X39+AK39+AL39 -> -5760 | AO39: =U39+AM39 -> 0 | AP39: =R39+X39 -> 0
A40: 44651 | C40: 22-0038 | D40: TP/CYL/22/0121 | E40: DCH21/004 | F40: =VLOOKUP(E40,#REF!,2,FALSE) -> #REF! | G40: =VLOOKUP(E40,#REF!,9,FALSE) -> #REF! | H40: =VLOOKUP(E40,#REF!,10,FALSE) -> #REF! | I40: =G40-U40 -> #REF! | J40: AROPAK | K40: 8 | N40: HORLICKS 3IN1 ORIGINAL 28G HK (AMD#1-21) | O40: 122300386 | P40: JANOSCHKA | R40: 5760 | S40: 0 | T40: 0 | U40: =SUM(R40:T40) -> 5760 | W40: 24 | X40: -5760 | Y40: 0 | Z40: 0 | AA40: 0 | AB40: 0 | AC40: 0 | AD40: 0 | AE40: 0 | AF40: 0 | AG40: 0 | AH40: 0 | AI40: 0 | AJ40: 0 | AK40: =SUM(Y40:AJ40) -> 0 | AL40: 0 | AM40: =X40+AK40+AL40 -> -5760 | AO40: =U40+AM40 -> 0 | AP40: =R40+X40 -> 0
A41: 44651 | C41: 22-0039 | D41: TP/CYL/22/0119 | E41: DCH22/021 | F41: =VLOOKUP(E41,#REF!,2,FALSE) -> #REF! | G41: =VLOOKUP(E41,#REF!,9,FALSE) -> #REF! | H41: =VLOOKUP(E41,#REF!,10,FALSE) -> #REF! | I41: =G41-U41 -> #REF! | J41: AROPAK | K41: 7 | N41: HORLICKS 3IN1 ORIGINAL 10 X 28G MY/SG (AMD#1-21) | O41: 122300360 | P41: JANOSCHKA | R41: 5449.5 | S41: 0 | T41: 0 | U41: =SUM(R41:T41) -> 5449.5 | W41: 24 | X41: -5449.5025 | Y41: 0 | Z41: 0 | AA41: 0 | AB41: 0 | AC41: 0 | AD41: 0 | AE41: 0 | AF41: 0 | AG41: 0 | AH41: 0 | AI41: 0 | AJ41: 0 | AK41: =SUM(Y41:AJ41) -> 0 | AL41: 0 | AM41: =X41+AK41+AL41 -> -5449.5025 | AO41: =U41+AM41 -> -0.0025 | AP41: =R41+X41 -> -0.0025
A42: 44651 | C42: 22-0040 | D42: TP/CYL/22/0118 | E42: DCH21/007 | F42: =VLOOKUP(E42,#REF!,2,FALSE) -> #REF! | G42: =VLOOKUP(E42,#REF!,9,FALSE) -> #REF! | H42: =VLOOKUP(E42,#REF!,10,FALSE) -> #REF! | I42: =G42-U42 -> #REF! | J42: AROPAK | K42: 7 | N42: HORLICKS 3IN1 ORIGINAL 28G MY/SG (AMD#1-21) | O42: 122300385 | P42: JANOSCHKA | R42: 5449.5 | S42: 0 | T42: 0 | U42: =SUM(R42:T42) -> 5449.5 | W42: 24 | X42: -5449.5025 | Y42: 0 | Z42: 0 | AA42: 0 | AB42: 0 | AC42: 0 | AD42: 0 | AE42: 0 | AF42: 0 | AG42: 0 | AH42: 0 | AI42: 0 | AJ42: 0 | AK42: =SUM(Y42:AJ42) -> 0 | AL42: 0 | AM42: =X42+AK42+AL42 -> -5449.5025 | AO42: =U42+AM42 -> -0.0025 | AP42: =R42+X42 -> -0.0025
A43: 44651 | C43: 22-0041 | D43: TP/CYL/22/0123 | E43: DCH21/008 | F43: =VLOOKUP(E43,#REF!,2,FALSE) -> #REF! | G43: =VLOOKUP(E43,#REF!,9,FALSE) -> #REF! | H43: =VLOOKUP(E43,#REF!,10,FALSE) -> #REF! | I43: =G43-U43 -> #REF! | J43: AROPAK | K43: 8 | N43: HORLICKS 3IN1 LITE 10 X 28G MY/SG (AMD#1-21) | O43: 122300412 | P43: JANOSCHKA | R43: 5760 | S43: 0 | T43: 0 | U43: =SUM(R43:T43) -> 5760 | W43: 24 | X43: -5760 | Y43: 0 | Z43: 0 | AA43: 0 | AB43: 0 | AC43: 0 | AD43: 0 | AE43: 0 | AF43: 0 | AG43: 0 | AH43: 0 | AI43: 0 | AJ43: 0 | AK43: =SUM(Y43:AJ43) -> 0 | AL43: 0 | AM43: =X43+AK43+AL43 -> -5760 | AO43: =U43+AM43 -> 0 | AP43: =R43+X43 -> 0
A44: 44651 | C44: 22-0042 | D44: TP/CYL/22/0124 | E44: DCH21/005 | F44: =VLOOKUP(E44,#REF!,2,FALSE) -> #REF! | G44: =VLOOKUP(E44,#REF!,9,FALSE) -> #REF! | H44: =VLOOKUP(E44,#REF!,10,FALSE) -> #REF! | I44: =G44-U44 -> #REF! | J44: AROPAK | K44: 8 | N44: HORLICKS 3IN1 CEREAL 10 X 32G MY/SG (AMD#1-21) | O44: 122300381 | P44: JANOSCHKA | R44: 6120 | S44: 0 | T44: 0 | U44: =SUM(R44:T44) -> 6120 | W44: 24 | X44: -6120 | Y44: 0 | Z44: 0 | AA44: 0 | AB44: 0 | AC44: 0 | AD44: 0 | AE44: 0 | AF44: 0 | AG44: 0 | AH44: 0 | AI44: 0 | AJ44: 0 | AK44: =SUM(Y44:AJ44) -> 0 | AL44: 0 | AM44: =X44+AK44+AL44 -> -6120 | AO44: =U44+AM44 -> 0 | AP44: =R44+X44 -> 0
A45: 44651 | C45: 22-0043 | D45: TP/CYL/22/0058 | E45: ZHL15/082 | F45: =VLOOKUP(E45,#REF!,2,FALSE) -> #REF! | G45: =VLOOKUP(E45,#REF!,9,FALSE) -> #REF! | H45: =VLOOKUP(E45,#REF!,10,FALSE) -> #REF! | I45: =G45-U45 -> #REF! | J45: AROPAK | K45: 6 | N45: COFFEE PLUS 20G (THAI) SET 1 AMD#2-20 | O45: 122300285 | P45: JANOSCHKA | R45: 6390 | S45: 0 | T45: 0 | U45: =SUM(R45:T45) -> 6390 | W45: 24 | X45: -6390 | Y45: 0 | Z45: 0 | AA45: 0 | AB45: 0 | AC45: 0 | AD45: 0 | AE45: 0 | AF45: 0 | AG45: 0 | AH45: 0 | AI45: 0 | AJ45: 0 | AK45: =SUM(Y45:AJ45) -> 0 | AL45: 0 | AM45: =X45+AK45+AL45 -> -6390 | AO45: =U45+AM45 -> 0 | AP45: =R45+X45 -> 0
A46: 44651 | C46: 22-0044 | D46: TP/CYL/22/0120 | E46: DCH21/006 | F46: =VLOOKUP(E46,#REF!,2,FALSE) -> #REF! | G46: =VLOOKUP(E46,#REF!,9,FALSE) -> #REF! | H46: =VLOOKUP(E46,#REF!,10,FALSE) -> #REF! | I46: =G46-U46 -> #REF! | J46: AROPAK | K46: 7 | N46: HORLICKS 3IN1 CEREAL 32G MY/SG (AMD#1-21) | O46: 122300362 | P46: JANOSCHKA | R46: 6237 | S46: 0 | T46: 0 | U46: =SUM(R46:T46) -> 6237 | W46: 24 | X46: -6237 | Y46: 0 | Z46: 0 | AA46: 0 | AB46: 0 | AC46: 0 | AD46: 0 | AE46: 0 | AF46: 0 | AG46: 0 | AH46: 0 | AI46: 0 | AJ46: 0 | AK46: =SUM(Y46:AJ46) -> 0 | AL46: 0 | AM46: =X46+AK46+AL46 -> -6237 | AO46: =U46+AM46 -> 0 | AP46: =R46+X46 -> 0
A47: 44651 | C47: 22-0050 | D47: TP/CYL/22/0056 | E47: ZHL10/119 | F47: =VLOOKUP(E47,#REF!,2,FALSE) -> #REF! | G47: =VLOOKUP(E47,#REF!,9,FALSE) -> #REF! | H47: =VLOOKUP(E47,#REF!,10,FALSE) -> #REF! | I47: =G47-U47 -> #REF! | J47: FORAYPACK | K47: 8 | N47: ZHULIAN COFFEE PLUS GINSENG 40'S X 20G - STAND UP POUCH | O47: 2202022 | P47: WELL EQUIPPED | R47: 6283.2 | S47: 0 | T47: 0 | U47: =SUM(R47:T47) -> 6283.2 | W47: 24 | X47: -6283.2 | Y47: 0 | Z47: 0 | AA47: 0 | AB47: 0 | AC47: 0 | AD47: 0 | AE47: 0 | AF47: 0 | AG47: 0 | AH47: 0 | AI47: 0 | AJ47: 0 | AK47: =SUM(Y47:AJ47) -> 0 | AL47: 0 | AM47: =X47+AK47+AL47 -> -6283.2 | AO47: =U47+AM47 -> 0 | AP47: =R47+X47 -> 0
A48: 44651 | C48: 22-0052 | D48: TP/CYL/22/0147 | E48: AJI21/169 | F48: =VLOOKUP(E48,#REF!,2,FALSE) -> #REF! | G48: =VLOOKUP(E48,#REF!,9,FALSE) -> #REF! | H48: =VLOOKUP(E48,#REF!,10,FALSE) -> #REF! | I48: =G48-U48 -> #REF! | J48: AROPAK | K48: 1 | N48: MSG 100G (CEBU) TPAC221100 | O48: LSO/MTM/9365 | P48: LIAN SENG | R48: 22445.55 | S48: 0 | T48: 0 | U48: =SUM(R48:T48) -> 22445.55 | W48: 24 | X48: -22445.551 | Y48: 0 | Z48: 0 | AA48: 0 | AB48: 0 | AC48: 0 | AD48: 0 | AE48: 0 | AF48: 0 | AG48: 0 | AH48: 0 | AI48: 0 | AJ48: 0 | AK48: =SUM(Y48:AJ48) -> 0 | AL48: 0 | AM48: =X48+AK48+AL48 -> -22445.551 | AO48: =U48+AM48 -> -0.00125 | AP48: =R48+X48 -> -0.00125
A49: 44651 | C49: 22-0062 | D49: TP/CYL/22/0101 | E49: ZHL19/104 | F49: =VLOOKUP(E49,#REF!,2,FALSE) -> #REF! | G49: =VLOOKUP(E49,#REF!,9,FALSE) -> #REF! | H49: =VLOOKUP(E49,#REF!,10,FALSE) -> #REF! | I49: =G49-U49 -> #REF! | J49: AROPAK | K49: 4 | N49: COFFEE PLUS WH GINSENG & COLLAGEN 18 X 20G THAI (SIDE GUSSET) | O49: SINV22-00418 | P49: FUJI ROTO | R49: 3837.6 | S49: 0 | T49: 0 | U49: =SUM(R49:T49) -> 3837.6 | W49: 24 | X49: -3837.6 | Y49: 0 | Z49: 0 | AA49: 0 | AB49: 0 | AC49: 0 | AD49: 0 | AE49: 0 | AF49: 0 | AG49: 0 | AH49: 0 | AI49: 0 | AJ49: 0 | AK49: =SUM(Y49:AJ49) -> 0 | AL49: 0 | AM49: =X49+AK49+AL49 -> -3837.6 | AO49: =U49+AM49 -> 0 | AP49: =R49+X49 -> 0
A50: 44651 | C50: 22-0063 | D50: TP/CYL/22/0100 | E50: ZHL19/103 | F50: =VLOOKUP(E50,#REF!,2,FALSE) -> #REF! | G50: =VLOOKUP(E50,#REF!,9,FALSE) -> #REF! | H50: =VLOOKUP(E50,#REF!,10,FALSE) -> #REF! | I50: =G50-U50 -> #REF! | J50: AROPAK | K50: 6 | N50: COFFEE PLUS WH GINSENG & COLLAGEN 18 X 20G THAI - AMD#1-21 | O50: SINV22-00415 | P50: FUJI ROTO | R50: 6304 | S50: 0 | T50: 0 | U50: =SUM(R50:T50) -> 6304 | W50: 24 | X50: -6303.9967 | Y50: 0 | Z50: 0 | AA50: 0 | AB50: 0 | AC50: 0 | AD50: 0 | AE50: 0 | AF50: 0 | AG50: 0 | AH50: 0 | AI50: 0 | AJ50: 0 | AK50: =SUM(Y50:AJ50) -> 0 | AL50: 0 | AM50: =X50+AK50+AL50 -> -6303.9967 | AO50: =U50+AM50 -> 0.0033333333 | AP50: =R50+X50 -> 0.0033333333
A51: 44651 | C51: 22-0064 | D51: TP/CYL/22/0099 | E51: ZHL19/102 | F51: =VLOOKUP(E51,#REF!,2,FALSE) -> #REF! | G51: =VLOOKUP(E51,#REF!,9,FALSE) -> #REF! | H51: =VLOOKUP(E51,#REF!,10,FALSE) -> #REF! | I51: =G51-U51 -> #REF! | J51: AROPAK | K51: 6 | N51: COFFEE PLUS WH GINSENG & COLLAGEN 20G THAI - AMD#1-21 | O51: SINV22-00419 | P51: FUJI ROTO | R51: 7202.38 | S51: 0 | T51: 0 | U51: =SUM(R51:T51) -> 7202.38 | W51: 24 | X51: -7202.3817 | Y51: 0 | Z51: 0 | AA51: 0 | AB51: 0 | AC51: 0 | AD51: 0 | AE51: 0 | AF51: 0 | AG51: 0 | AH51: 0 | AI51: 0 | AJ51: 0 | AK51: =SUM(Y51:AJ51) -> 0 | AL51: 0 | AM51: =X51+AK51+AL51 -> -7202.3817 | AO51: =U51+AM51 -> -0.0016666667 | AP51: =R51+X51 -> -0.0016666667
A52: 44651 | C52: 22-0074 | D52: TP/CYL/22/0022 | E52: UNI14/137 | F52: =VLOOKUP(E52,#REF!,2,FALSE) -> #REF! | G52: =VLOOKUP(E52,#REF!,9,FALSE) -> #REF! | H52: =VLOOKUP(E52,#REF!,10,FALSE) -> #REF! | I52: =G52-U52 -> #REF! | J52: FORAYPACK | K52: 7 | N52: KNORR LIME FLVRD POWDER 400G MYBNSG | O52: 085479 | P52: SIMCO | R52: 6804 | S52: 0 | T52: 0 | U52: =SUM(R52:T52) -> 6804 | W52: 24 | X52: -6804 | Y52: 0 | Z52: 0 | AA52: 0 | AB52: 0 | AC52: 0 | AD52: 0 | AE52: 0 | AF52: 0 | AG52: 0 | AH52: 0 | AI52: 0 | AJ52: 0 | AK52: =SUM(Y52:AJ52) -> 0 | AL52: 0 | AM52: =X52+AK52+AL52 -> -6804 | AO52: =U52+AM52 -> 0 | AP52: =R52+X52 -> 0
A53: 44651 | C53: 22-0077 | D53: TP/CYL/22/0021 | E53: UNI12/102 | F53: =VLOOKUP(E53,#REF!,2,FALSE) -> #REF! | G53: =VLOOKUP(E53,#REF!,9,FALSE) -> #REF! | H53: =VLOOKUP(E53,#REF!,10,FALSE) -> #REF! | I53: =G53-U53 -> #REF! | J53: FORAYPACK | K53: 7 | N53: KNORR CHICKEN FLAVOURED SEASONING 1KG MYSG (AMD#1-15) | O53: 122300201 | P53: JANOSCHKA | R53: 6468 | S53: 0 | T53: 0 | U53: =SUM(R53:T53) -> 6468 | W53: 24 | X53: -6468 | Y53: 0 | Z53: 0 | AA53: 0 | AB53: 0 | AC53: 0 | AD53: 0 | AE53: 0 | AF53: 0 | AG53: 0 | AH53: 0 | AI53: 0 | AJ53: 0 | AK53: =SUM(Y53:AJ53) -> 0 | AL53: 0 | AM53: =X53+AK53+AL53 -> -6468 | AO53: =U53+AM53 -> 0 | AP53: =R53+X53 -> 0
A54: 44651 | C54: 22-0078 | D54: TP/CYL/22/0096 | E54: ZHL10/063 | F54: =VLOOKUP(E54,#REF!,2,FALSE) -> #REF! | G54: =VLOOKUP(E54,#REF!,9,FALSE) -> #REF! | H54: =VLOOKUP(E54,#REF!,10,FALSE) -> #REF! | I54: =G54-U54 -> #REF! | J54: AROPAK | K54: 6 | N54: ROYALMIX 28G THAI (AMD#1-21) | O54: 122300361 | P54: JANOSCHKA | R54: 4320 | S54: 0 | T54: 0 | U54: =SUM(R54:T54) -> 4320 | W54: 24 | X54: -4320 | Y54: 0 | Z54: 0 | AA54: 0 | AB54: 0 | AC54: 0 | AD54: 0 | AE54: 0 | AF54: 0 | AG54: 0 | AH54: 0 | AI54: 0 | AJ54: 0 | AK54: =SUM(Y54:AJ54) -> 0 | AL54: 0 | AM54: =X54+AK54+AL54 -> -4320 | AO54: =U54+AM54 -> 0 | AP54: =R54+X54 -> 0
A55: 44651 | C55: 22-0080 | D55: TP/CYL/22/0030 | E55: AJI18/102 | F55: =VLOOKUP(E55,#REF!,2,FALSE) -> #REF! | G55: =VLOOKUP(E55,#REF!,9,FALSE) -> #REF! | H55: =VLOOKUP(E55,#REF!,10,FALSE) -> #REF! | I55: =G55-U55 -> #REF! | J55: HEXACHASE | K55: 2 | N55: AJINOMOTO MSG 10G-3L (MANILA) AGB TPH2220 | O55: LSO/MTM/9361 | P55: LIAN SENG | R55: 21846.07 | S55: 0 | T55: 0 | U55: =SUM(R55:T55) -> 21846.07 | W55: 24 | X55: -21846.066 | Y55: 0 | Z55: 0 | AA55: 0 | AB55: 0 | AC55: 0 | AD55: 0 | AE55: 0 | AF55: 0 | AG55: 0 | AH55: 0 | AI55: 0 | AJ55: 0 | AK55: =SUM(Y55:AJ55) -> 0 | AL55: 0 | AM55: =X55+AK55+AL55 -> -21846.066 | AO55: =U55+AM55 -> 0.00375 | AP55: =R55+X55 -> 0.00375
A56: 44651 | C56: 22-0083 | D56: TP/CYL/22/0136 | E56: TNF06/007 | F56: =VLOOKUP(E56,#REF!,2,FALSE) -> #REF! | G56: =VLOOKUP(E56,#REF!,9,FALSE) -> #REF! | H56: =VLOOKUP(E56,#REF!,10,FALSE) -> #REF! | I56: =G56-U56 -> #REF! | J56: SEMI CONVERTOR | K56: 6 | N56: FOURWAY ANCHOVY CRACKERS CHIP 110G (AMD#01-22) | O56: LSO/MTM/9369 | P56: LIAN SENG | R56: 6798.86 | S56: 0 | T56: 0 | U56: =SUM(R56:T56) -> 6798.86 | W56: 24 | X56: -6798.8583 | Y56: 0 | Z56: 0 | AA56: 0 | AB56: 0 | AC56: 0 | AD56: 0 | AE56: 0 | AF56: 0 | AG56: 0 | AH56: 0 | AI56: 0 | AJ56: 0 | AK56: =SUM(Y56:AJ56) -> 0 | AL56: 0 | AM56: =X56+AK56+AL56 -> -6798.8583 | AO56: =U56+AM56 -> 0.0016666667 | AP56: =R56+X56 -> 0.0016666667
